{"open":{"('AAPL', Timestamp('2023-10-13 08:00:00+0000', tz='UTC'))":181.05,"('AAPL', Timestamp('2023-10-13 08:05:00+0000', tz='UTC'))":181.1,"('AAPL', Timestamp('2023-10-13 08:10:00+0000', tz='UTC'))":181.12,"('AAPL', Timestamp('2023-10-13 08:15:00+0000', tz='UTC'))":181.1,"('AAPL', Timestamp('2023-10-13 08:25:00+0000', tz='UTC'))":181.09,"('AAPL', Timestamp('2023-10-13 08:30:00+0000', tz='UTC'))":180.93,"('AAPL', Timestamp('2023-10-13 08:40:00+0000', tz='UTC'))":180.86,"('AAPL', Timestamp('2023-10-13 08:45:00+0000', tz='UTC'))":180.78,"('AAPL', Timestamp('2023-10-13 08:50:00+0000', tz='UTC'))":180.72,"('AAPL', Timestamp('2023-10-13 08:55:00+0000', tz='UTC'))":180.74,"('AAPL', Timestamp('2023-10-13 09:00:00+0000', tz='UTC'))":180.73,"('AAPL', Timestamp('2023-10-13 09:05:00+0000', tz='UTC'))":180.65,"('AAPL', Timestamp('2023-10-13 09:10:00+0000', tz='UTC'))":180.65,"('AAPL', Timestamp('2023-10-13 09:15:00+0000', tz='UTC'))":180.61,"('AAPL', Timestamp('2023-10-13 09:20:00+0000', tz='UTC'))":180.6,"('AAPL', Timestamp('2023-10-13 09:25:00+0000', tz='UTC'))":180.65,"('AAPL', Timestamp('2023-10-13 09:30:00+0000', tz='UTC'))":180.71,"('AAPL', Timestamp('2023-10-13 09:35:00+0000', tz='UTC'))":180.71,"('AAPL', Timestamp('2023-10-13 09:40:00+0000', tz='UTC'))":180.62,"('AAPL', Timestamp('2023-10-13 09:45:00+0000', tz='UTC'))":180.53,"('AAPL', Timestamp('2023-10-13 09:50:00+0000', tz='UTC'))":180.5,"('AAPL', Timestamp('2023-10-13 09:55:00+0000', tz='UTC'))":180.35,"('AAPL', Timestamp('2023-10-13 10:00:00+0000', tz='UTC'))":180.32,"('AAPL', Timestamp('2023-10-13 10:05:00+0000', tz='UTC'))":180.3,"('AAPL', Timestamp('2023-10-13 10:10:00+0000', tz='UTC'))":180.11,"('AAPL', Timestamp('2023-10-13 10:15:00+0000', tz='UTC'))":180.06,"('AAPL', Timestamp('2023-10-13 10:20:00+0000', tz='UTC'))":180.16,"('AAPL', Timestamp('2023-10-13 10:25:00+0000', tz='UTC'))":180.09,"('AAPL', Timestamp('2023-10-13 10:30:00+0000', tz='UTC'))":180.1,"('AAPL', Timestamp('2023-10-13 10:35:00+0000', tz='UTC'))":180.11,"('AAPL', Timestamp('2023-10-13 10:40:00+0000', tz='UTC'))":180.09,"('AAPL', Timestamp('2023-10-13 10:45:00+0000', tz='UTC'))":180.15,"('AAPL', Timestamp('2023-10-13 10:50:00+0000', tz='UTC'))":180.22,"('AAPL', Timestamp('2023-10-13 10:55:00+0000', tz='UTC'))":180.25,"('AAPL', Timestamp('2023-10-13 11:00:00+0000', tz='UTC'))":180.35,"('AAPL', Timestamp('2023-10-13 11:05:00+0000', tz='UTC'))":180.36,"('AAPL', Timestamp('2023-10-13 11:10:00+0000', tz='UTC'))":180.4,"('AAPL', Timestamp('2023-10-13 11:15:00+0000', tz='UTC'))":180.38,"('AAPL', Timestamp('2023-10-13 11:20:00+0000', tz='UTC'))":180.26,"('AAPL', Timestamp('2023-10-13 11:25:00+0000', tz='UTC'))":180.29,"('AAPL', Timestamp('2023-10-13 11:30:00+0000', tz='UTC'))":180.31,"('AAPL', Timestamp('2023-10-13 11:35:00+0000', tz='UTC'))":180.33,"('AAPL', Timestamp('2023-10-13 11:40:00+0000', tz='UTC'))":180.29,"('AAPL', Timestamp('2023-10-13 11:45:00+0000', tz='UTC'))":180.11,"('AAPL', Timestamp('2023-10-13 11:50:00+0000', tz='UTC'))":180.2,"('AAPL', Timestamp('2023-10-13 11:55:00+0000', tz='UTC'))":180.25,"('AAPL', Timestamp('2023-10-13 12:00:00+0000', tz='UTC'))":180.1512,"('AAPL', Timestamp('2023-10-13 12:05:00+0000', tz='UTC'))":180.26,"('AAPL', Timestamp('2023-10-13 12:10:00+0000', tz='UTC'))":180.18,"('AAPL', Timestamp('2023-10-13 12:15:00+0000', tz='UTC'))":180.15,"('AAPL', Timestamp('2023-10-13 12:20:00+0000', tz='UTC'))":180.17,"('AAPL', Timestamp('2023-10-13 12:25:00+0000', tz='UTC'))":180.28,"('AAPL', Timestamp('2023-10-13 12:30:00+0000', tz='UTC'))":180.36,"('AAPL', Timestamp('2023-10-13 12:35:00+0000', tz='UTC'))":180.52,"('AAPL', Timestamp('2023-10-13 12:40:00+0000', tz='UTC'))":180.91,"('AAPL', Timestamp('2023-10-13 12:45:00+0000', tz='UTC'))":180.7444,"('AAPL', Timestamp('2023-10-13 12:50:00+0000', tz='UTC'))":180.73,"('AAPL', Timestamp('2023-10-13 12:55:00+0000', tz='UTC'))":180.97,"('AAPL', Timestamp('2023-10-13 13:00:00+0000', tz='UTC'))":181.03,"('AAPL', Timestamp('2023-10-13 13:05:00+0000', tz='UTC'))":181.06,"('AAPL', Timestamp('2023-10-13 13:10:00+0000', tz='UTC'))":181.13,"('AAPL', Timestamp('2023-10-13 13:15:00+0000', tz='UTC'))":181.23,"('AAPL', Timestamp('2023-10-13 13:20:00+0000', tz='UTC'))":181.21,"('AAPL', Timestamp('2023-10-13 13:25:00+0000', tz='UTC'))":181.15,"('AAPL', Timestamp('2023-10-13 13:30:00+0000', tz='UTC'))":181.39,"('AAPL', Timestamp('2023-10-13 13:35:00+0000', tz='UTC'))":181.48,"('AAPL', Timestamp('2023-10-13 13:40:00+0000', tz='UTC'))":181.28,"('AAPL', Timestamp('2023-10-13 13:45:00+0000', tz='UTC'))":181.195,"('AAPL', Timestamp('2023-10-13 13:50:00+0000', tz='UTC'))":181.37,"('AAPL', Timestamp('2023-10-13 13:55:00+0000', tz='UTC'))":181.16,"('AAPL', Timestamp('2023-10-13 14:00:00+0000', tz='UTC'))":181.15,"('AAPL', Timestamp('2023-10-13 14:05:00+0000', tz='UTC'))":181.03,"('AAPL', Timestamp('2023-10-13 14:10:00+0000', tz='UTC'))":180.98,"('AAPL', Timestamp('2023-10-13 14:15:00+0000', tz='UTC'))":180.59,"('AAPL', Timestamp('2023-10-13 14:20:00+0000', tz='UTC'))":180.61,"('AAPL', Timestamp('2023-10-13 14:25:00+0000', tz='UTC'))":180.37,"('AAPL', Timestamp('2023-10-13 14:30:00+0000', tz='UTC'))":180.52,"('AAPL', Timestamp('2023-10-13 14:35:00+0000', tz='UTC'))":180.73,"('AAPL', Timestamp('2023-10-13 14:40:00+0000', tz='UTC'))":180.4101,"('AAPL', Timestamp('2023-10-13 14:45:00+0000', tz='UTC'))":180.3,"('AAPL', Timestamp('2023-10-13 14:50:00+0000', tz='UTC'))":180.08,"('AAPL', Timestamp('2023-10-13 14:55:00+0000', tz='UTC'))":179.64,"('AAPL', Timestamp('2023-10-13 15:00:00+0000', tz='UTC'))":179.62,"('AAPL', Timestamp('2023-10-13 15:05:00+0000', tz='UTC'))":179.61,"('AAPL', Timestamp('2023-10-13 15:10:00+0000', tz='UTC'))":179.58,"('AAPL', Timestamp('2023-10-13 15:15:00+0000', tz='UTC'))":179.44,"('AAPL', Timestamp('2023-10-13 15:20:00+0000', tz='UTC'))":179.325,"('AAPL', Timestamp('2023-10-13 15:25:00+0000', tz='UTC'))":178.99,"('AAPL', Timestamp('2023-10-13 15:30:00+0000', tz='UTC'))":179.19,"('AAPL', Timestamp('2023-10-13 15:35:00+0000', tz='UTC'))":179.13,"('AAPL', Timestamp('2023-10-13 15:40:00+0000', tz='UTC'))":179.275,"('AAPL', Timestamp('2023-10-13 15:45:00+0000', tz='UTC'))":179.15,"('AAPL', Timestamp('2023-10-13 15:50:00+0000', tz='UTC'))":179.0096,"('AAPL', Timestamp('2023-10-13 15:55:00+0000', tz='UTC'))":178.665,"('AAPL', Timestamp('2023-10-13 16:00:00+0000', tz='UTC'))":178.6,"('AAPL', Timestamp('2023-10-13 16:05:00+0000', tz='UTC'))":178.7197,"('AAPL', Timestamp('2023-10-13 16:10:00+0000', tz='UTC'))":178.96,"('AAPL', Timestamp('2023-10-13 16:15:00+0000', tz='UTC'))":178.75,"('AAPL', Timestamp('2023-10-13 16:20:00+0000', tz='UTC'))":179.13,"('AAPL', Timestamp('2023-10-13 16:25:00+0000', tz='UTC'))":179.1905,"('AAPL', Timestamp('2023-10-13 16:30:00+0000', tz='UTC'))":179.26,"('AAPL', Timestamp('2023-10-13 16:35:00+0000', tz='UTC'))":179.39,"('AAPL', Timestamp('2023-10-13 16:40:00+0000', tz='UTC'))":179.22,"('AAPL', Timestamp('2023-10-13 16:45:00+0000', tz='UTC'))":179.322,"('AAPL', Timestamp('2023-10-13 16:50:00+0000', tz='UTC'))":179.1603,"('AAPL', Timestamp('2023-10-13 16:55:00+0000', tz='UTC'))":179.03,"('AAPL', Timestamp('2023-10-13 17:00:00+0000', tz='UTC'))":179.06,"('AAPL', Timestamp('2023-10-13 17:05:00+0000', tz='UTC'))":179.0,"('AAPL', Timestamp('2023-10-13 17:10:00+0000', tz='UTC'))":178.6908,"('AAPL', Timestamp('2023-10-13 17:15:00+0000', tz='UTC'))":178.57,"('AAPL', Timestamp('2023-10-13 17:20:00+0000', tz='UTC'))":178.555,"('AAPL', Timestamp('2023-10-13 17:25:00+0000', tz='UTC'))":178.6188,"('AAPL', Timestamp('2023-10-13 17:30:00+0000', tz='UTC'))":178.261,"('AAPL', Timestamp('2023-10-13 17:35:00+0000', tz='UTC'))":178.2849,"('AAPL', Timestamp('2023-10-13 17:40:00+0000', tz='UTC'))":178.305,"('AAPL', Timestamp('2023-10-13 17:45:00+0000', tz='UTC'))":178.845,"('AAPL', Timestamp('2023-10-13 17:50:00+0000', tz='UTC'))":178.78,"('AAPL', Timestamp('2023-10-13 17:55:00+0000', tz='UTC'))":178.8,"('AAPL', Timestamp('2023-10-13 18:00:00+0000', tz='UTC'))":178.82,"('AAPL', Timestamp('2023-10-13 18:05:00+0000', tz='UTC'))":178.765,"('AAPL', Timestamp('2023-10-13 18:10:00+0000', tz='UTC'))":178.9,"('AAPL', Timestamp('2023-10-13 18:15:00+0000', tz='UTC'))":178.96,"('AAPL', Timestamp('2023-10-13 18:20:00+0000', tz='UTC'))":179.11,"('AAPL', Timestamp('2023-10-13 18:25:00+0000', tz='UTC'))":179.1265,"('AAPL', Timestamp('2023-10-13 18:30:00+0000', tz='UTC'))":179.245,"('AAPL', Timestamp('2023-10-13 18:35:00+0000', tz='UTC'))":179.42,"('AAPL', Timestamp('2023-10-13 18:40:00+0000', tz='UTC'))":179.245,"('AAPL', Timestamp('2023-10-13 18:45:00+0000', tz='UTC'))":179.105,"('AAPL', Timestamp('2023-10-13 18:50:00+0000', tz='UTC'))":179.02,"('AAPL', Timestamp('2023-10-13 18:55:00+0000', tz='UTC'))":179.31,"('AAPL', Timestamp('2023-10-13 19:00:00+0000', tz='UTC'))":179.33,"('AAPL', Timestamp('2023-10-13 19:05:00+0000', tz='UTC'))":179.43,"('AAPL', Timestamp('2023-10-13 19:10:00+0000', tz='UTC'))":179.41,"('AAPL', Timestamp('2023-10-13 19:15:00+0000', tz='UTC'))":179.46,"('AAPL', Timestamp('2023-10-13 19:20:00+0000', tz='UTC'))":179.16,"('AAPL', Timestamp('2023-10-13 19:25:00+0000', tz='UTC'))":179.159,"('AAPL', Timestamp('2023-10-13 19:30:00+0000', tz='UTC'))":178.94,"('AAPL', Timestamp('2023-10-13 19:35:00+0000', tz='UTC'))":178.955,"('AAPL', Timestamp('2023-10-13 19:40:00+0000', tz='UTC'))":178.93,"('AAPL', Timestamp('2023-10-13 19:45:00+0000', tz='UTC'))":178.61,"('AAPL', Timestamp('2023-10-13 19:50:00+0000', tz='UTC'))":178.96,"('AAPL', Timestamp('2023-10-13 19:55:00+0000', tz='UTC'))":179.05,"('AAPL', Timestamp('2023-10-13 20:00:00+0000', tz='UTC'))":178.88,"('AAPL', Timestamp('2023-10-13 20:05:00+0000', tz='UTC'))":178.76,"('AAPL', Timestamp('2023-10-13 20:10:00+0000', tz='UTC'))":178.72,"('AAPL', Timestamp('2023-10-13 20:15:00+0000', tz='UTC'))":178.67,"('AAPL', Timestamp('2023-10-13 20:20:00+0000', tz='UTC'))":178.72,"('AAPL', Timestamp('2023-10-13 20:25:00+0000', tz='UTC'))":178.63,"('AAPL', Timestamp('2023-10-13 20:30:00+0000', tz='UTC'))":178.68,"('AAPL', Timestamp('2023-10-13 20:35:00+0000', tz='UTC'))":178.62,"('AAPL', Timestamp('2023-10-13 20:40:00+0000', tz='UTC'))":178.6,"('AAPL', Timestamp('2023-10-13 20:45:00+0000', tz='UTC'))":178.56,"('AAPL', Timestamp('2023-10-13 20:50:00+0000', tz='UTC'))":178.58,"('AAPL', Timestamp('2023-10-13 20:55:00+0000', tz='UTC'))":178.65,"('AAPL', Timestamp('2023-10-13 21:05:00+0000', tz='UTC'))":178.6502,"('AAPL', Timestamp('2023-10-13 21:10:00+0000', tz='UTC'))":178.65,"('AAPL', Timestamp('2023-10-13 21:15:00+0000', tz='UTC'))":178.66,"('AAPL', Timestamp('2023-10-13 21:20:00+0000', tz='UTC'))":178.61,"('AAPL', Timestamp('2023-10-13 21:25:00+0000', tz='UTC'))":178.63,"('AAPL', Timestamp('2023-10-13 21:30:00+0000', tz='UTC'))":178.61,"('AAPL', Timestamp('2023-10-13 21:35:00+0000', tz='UTC'))":178.54,"('AAPL', Timestamp('2023-10-13 21:40:00+0000', tz='UTC'))":178.6272,"('AAPL', Timestamp('2023-10-13 21:45:00+0000', tz='UTC'))":178.61,"('AAPL', Timestamp('2023-10-13 21:50:00+0000', tz='UTC'))":178.64,"('AAPL', Timestamp('2023-10-13 21:55:00+0000', tz='UTC'))":178.57,"('AAPL', Timestamp('2023-10-13 22:00:00+0000', tz='UTC'))":178.58,"('AAPL', Timestamp('2023-10-13 22:05:00+0000', tz='UTC'))":178.6,"('AAPL', Timestamp('2023-10-13 22:10:00+0000', tz='UTC'))":178.6,"('AAPL', Timestamp('2023-10-13 22:15:00+0000', tz='UTC'))":178.6,"('AAPL', Timestamp('2023-10-13 22:20:00+0000', tz='UTC'))":178.6,"('AAPL', Timestamp('2023-10-13 22:35:00+0000', tz='UTC'))":178.57,"('AAPL', Timestamp('2023-10-13 22:40:00+0000', tz='UTC'))":178.61,"('AAPL', Timestamp('2023-10-13 22:45:00+0000', tz='UTC'))":178.636,"('AAPL', Timestamp('2023-10-13 22:50:00+0000', tz='UTC'))":178.6046,"('AAPL', Timestamp('2023-10-13 22:55:00+0000', tz='UTC'))":178.64,"('AAPL', Timestamp('2023-10-13 23:00:00+0000', tz='UTC'))":178.64,"('AAPL', Timestamp('2023-10-13 23:05:00+0000', tz='UTC'))":178.62,"('AAPL', Timestamp('2023-10-13 23:10:00+0000', tz='UTC'))":178.59,"('AAPL', Timestamp('2023-10-13 23:15:00+0000', tz='UTC'))":178.6,"('AAPL', Timestamp('2023-10-13 23:20:00+0000', tz='UTC'))":178.55,"('AAPL', Timestamp('2023-10-13 23:25:00+0000', tz='UTC'))":178.52,"('AAPL', Timestamp('2023-10-13 23:30:00+0000', tz='UTC'))":178.53,"('AAPL', Timestamp('2023-10-13 23:35:00+0000', tz='UTC'))":178.53,"('AAPL', Timestamp('2023-10-13 23:40:00+0000', tz='UTC'))":178.52,"('AAPL', Timestamp('2023-10-13 23:45:00+0000', tz='UTC'))":178.51,"('AAPL', Timestamp('2023-10-13 23:50:00+0000', tz='UTC'))":178.5},"high":{"('AAPL', Timestamp('2023-10-13 08:00:00+0000', tz='UTC'))":181.05,"('AAPL', Timestamp('2023-10-13 08:05:00+0000', tz='UTC'))":181.1,"('AAPL', Timestamp('2023-10-13 08:10:00+0000', tz='UTC'))":181.12,"('AAPL', Timestamp('2023-10-13 08:15:00+0000', tz='UTC'))":181.1,"('AAPL', Timestamp('2023-10-13 08:25:00+0000', tz='UTC'))":181.09,"('AAPL', Timestamp('2023-10-13 08:30:00+0000', tz='UTC'))":180.93,"('AAPL', Timestamp('2023-10-13 08:40:00+0000', tz='UTC'))":180.86,"('AAPL', Timestamp('2023-10-13 08:45:00+0000', tz='UTC'))":180.78,"('AAPL', Timestamp('2023-10-13 08:50:00+0000', tz='UTC'))":180.75,"('AAPL', Timestamp('2023-10-13 08:55:00+0000', tz='UTC'))":180.8,"('AAPL', Timestamp('2023-10-13 09:00:00+0000', tz='UTC'))":180.73,"('AAPL', Timestamp('2023-10-13 09:05:00+0000', tz='UTC'))":180.65,"('AAPL', Timestamp('2023-10-13 09:10:00+0000', tz='UTC'))":180.65,"('AAPL', Timestamp('2023-10-13 09:15:00+0000', tz='UTC'))":180.65,"('AAPL', Timestamp('2023-10-13 09:20:00+0000', tz='UTC'))":180.61,"('AAPL', Timestamp('2023-10-13 09:25:00+0000', tz='UTC'))":180.71,"('AAPL', Timestamp('2023-10-13 09:30:00+0000', tz='UTC'))":180.71,"('AAPL', Timestamp('2023-10-13 09:35:00+0000', tz='UTC'))":180.71,"('AAPL', Timestamp('2023-10-13 09:40:00+0000', tz='UTC'))":180.62,"('AAPL', Timestamp('2023-10-13 09:45:00+0000', tz='UTC'))":180.53,"('AAPL', Timestamp('2023-10-13 09:50:00+0000', tz='UTC'))":180.5,"('AAPL', Timestamp('2023-10-13 09:55:00+0000', tz='UTC'))":180.35,"('AAPL', Timestamp('2023-10-13 10:00:00+0000', tz='UTC'))":180.32,"('AAPL', Timestamp('2023-10-13 10:05:00+0000', tz='UTC'))":180.31,"('AAPL', Timestamp('2023-10-13 10:10:00+0000', tz='UTC'))":180.11,"('AAPL', Timestamp('2023-10-13 10:15:00+0000', tz='UTC'))":180.15,"('AAPL', Timestamp('2023-10-13 10:20:00+0000', tz='UTC'))":180.16,"('AAPL', Timestamp('2023-10-13 10:25:00+0000', tz='UTC'))":180.14,"('AAPL', Timestamp('2023-10-13 10:30:00+0000', tz='UTC'))":180.15,"('AAPL', Timestamp('2023-10-13 10:35:00+0000', tz='UTC'))":180.11,"('AAPL', Timestamp('2023-10-13 10:40:00+0000', tz='UTC'))":180.09,"('AAPL', Timestamp('2023-10-13 10:45:00+0000', tz='UTC'))":180.28,"('AAPL', Timestamp('2023-10-13 10:50:00+0000', tz='UTC'))":180.37,"('AAPL', Timestamp('2023-10-13 10:55:00+0000', tz='UTC'))":180.25,"('AAPL', Timestamp('2023-10-13 11:00:00+0000', tz='UTC'))":180.35,"('AAPL', Timestamp('2023-10-13 11:05:00+0000', tz='UTC'))":180.45,"('AAPL', Timestamp('2023-10-13 11:10:00+0000', tz='UTC'))":180.45,"('AAPL', Timestamp('2023-10-13 11:15:00+0000', tz='UTC'))":180.38,"('AAPL', Timestamp('2023-10-13 11:20:00+0000', tz='UTC'))":180.32,"('AAPL', Timestamp('2023-10-13 11:25:00+0000', tz='UTC'))":180.29,"('AAPL', Timestamp('2023-10-13 11:30:00+0000', tz='UTC'))":180.35,"('AAPL', Timestamp('2023-10-13 11:35:00+0000', tz='UTC'))":180.34,"('AAPL', Timestamp('2023-10-13 11:40:00+0000', tz='UTC'))":180.3,"('AAPL', Timestamp('2023-10-13 11:45:00+0000', tz='UTC'))":180.19,"('AAPL', Timestamp('2023-10-13 11:50:00+0000', tz='UTC'))":180.29,"('AAPL', Timestamp('2023-10-13 11:55:00+0000', tz='UTC'))":180.25,"('AAPL', Timestamp('2023-10-13 12:00:00+0000', tz='UTC'))":181.23,"('AAPL', Timestamp('2023-10-13 12:05:00+0000', tz='UTC'))":180.26,"('AAPL', Timestamp('2023-10-13 12:10:00+0000', tz='UTC'))":180.21,"('AAPL', Timestamp('2023-10-13 12:15:00+0000', tz='UTC'))":180.2,"('AAPL', Timestamp('2023-10-13 12:20:00+0000', tz='UTC'))":180.28,"('AAPL', Timestamp('2023-10-13 12:25:00+0000', tz='UTC'))":180.71,"('AAPL', Timestamp('2023-10-13 12:30:00+0000', tz='UTC'))":180.58,"('AAPL', Timestamp('2023-10-13 12:35:00+0000', tz='UTC'))":180.91,"('AAPL', Timestamp('2023-10-13 12:40:00+0000', tz='UTC'))":180.91,"('AAPL', Timestamp('2023-10-13 12:45:00+0000', tz='UTC'))":180.85,"('AAPL', Timestamp('2023-10-13 12:50:00+0000', tz='UTC'))":180.98,"('AAPL', Timestamp('2023-10-13 12:55:00+0000', tz='UTC'))":181.09,"('AAPL', Timestamp('2023-10-13 13:00:00+0000', tz='UTC'))":181.09,"('AAPL', Timestamp('2023-10-13 13:05:00+0000', tz='UTC'))":181.19,"('AAPL', Timestamp('2023-10-13 13:10:00+0000', tz='UTC'))":181.29,"('AAPL', Timestamp('2023-10-13 13:15:00+0000', tz='UTC'))":181.26,"('AAPL', Timestamp('2023-10-13 13:20:00+0000', tz='UTC'))":181.25,"('AAPL', Timestamp('2023-10-13 13:25:00+0000', tz='UTC'))":181.44,"('AAPL', Timestamp('2023-10-13 13:30:00+0000', tz='UTC'))":181.93,"('AAPL', Timestamp('2023-10-13 13:35:00+0000', tz='UTC'))":181.54,"('AAPL', Timestamp('2023-10-13 13:40:00+0000', tz='UTC'))":181.4,"('AAPL', Timestamp('2023-10-13 13:45:00+0000', tz='UTC'))":181.36,"('AAPL', Timestamp('2023-10-13 13:50:00+0000', tz='UTC'))":181.45,"('AAPL', Timestamp('2023-10-13 13:55:00+0000', tz='UTC'))":181.41,"('AAPL', Timestamp('2023-10-13 14:00:00+0000', tz='UTC'))":181.26,"('AAPL', Timestamp('2023-10-13 14:05:00+0000', tz='UTC'))":181.132,"('AAPL', Timestamp('2023-10-13 14:10:00+0000', tz='UTC'))":181.0,"('AAPL', Timestamp('2023-10-13 14:15:00+0000', tz='UTC'))":180.74,"('AAPL', Timestamp('2023-10-13 14:20:00+0000', tz='UTC'))":180.84,"('AAPL', Timestamp('2023-10-13 14:25:00+0000', tz='UTC'))":180.66,"('AAPL', Timestamp('2023-10-13 14:30:00+0000', tz='UTC'))":180.74,"('AAPL', Timestamp('2023-10-13 14:35:00+0000', tz='UTC'))":180.765,"('AAPL', Timestamp('2023-10-13 14:40:00+0000', tz='UTC'))":180.45,"('AAPL', Timestamp('2023-10-13 14:45:00+0000', tz='UTC'))":180.34,"('AAPL', Timestamp('2023-10-13 14:50:00+0000', tz='UTC'))":180.09,"('AAPL', Timestamp('2023-10-13 14:55:00+0000', tz='UTC'))":179.715,"('AAPL', Timestamp('2023-10-13 15:00:00+0000', tz='UTC'))":179.69,"('AAPL', Timestamp('2023-10-13 15:05:00+0000', tz='UTC'))":179.63,"('AAPL', Timestamp('2023-10-13 15:10:00+0000', tz='UTC'))":179.65,"('AAPL', Timestamp('2023-10-13 15:15:00+0000', tz='UTC'))":179.449,"('AAPL', Timestamp('2023-10-13 15:20:00+0000', tz='UTC'))":179.39,"('AAPL', Timestamp('2023-10-13 15:25:00+0000', tz='UTC'))":179.21,"('AAPL', Timestamp('2023-10-13 15:30:00+0000', tz='UTC'))":179.26,"('AAPL', Timestamp('2023-10-13 15:35:00+0000', tz='UTC'))":179.31,"('AAPL', Timestamp('2023-10-13 15:40:00+0000', tz='UTC'))":179.3625,"('AAPL', Timestamp('2023-10-13 15:45:00+0000', tz='UTC'))":179.2085,"('AAPL', Timestamp('2023-10-13 15:50:00+0000', tz='UTC'))":179.02,"('AAPL', Timestamp('2023-10-13 15:55:00+0000', tz='UTC'))":178.67,"('AAPL', Timestamp('2023-10-13 16:00:00+0000', tz='UTC'))":178.8964,"('AAPL', Timestamp('2023-10-13 16:05:00+0000', tz='UTC'))":179.0,"('AAPL', Timestamp('2023-10-13 16:10:00+0000', tz='UTC'))":179.03,"('AAPL', Timestamp('2023-10-13 16:15:00+0000', tz='UTC'))":179.1484,"('AAPL', Timestamp('2023-10-13 16:20:00+0000', tz='UTC'))":179.26,"('AAPL', Timestamp('2023-10-13 16:25:00+0000', tz='UTC'))":179.27,"('AAPL', Timestamp('2023-10-13 16:30:00+0000', tz='UTC'))":179.47,"('AAPL', Timestamp('2023-10-13 16:35:00+0000', tz='UTC'))":179.435,"('AAPL', Timestamp('2023-10-13 16:40:00+0000', tz='UTC'))":179.42,"('AAPL', Timestamp('2023-10-13 16:45:00+0000', tz='UTC'))":179.33,"('AAPL', Timestamp('2023-10-13 16:50:00+0000', tz='UTC'))":179.2,"('AAPL', Timestamp('2023-10-13 16:55:00+0000', tz='UTC'))":179.15,"('AAPL', Timestamp('2023-10-13 17:00:00+0000', tz='UTC'))":179.105,"('AAPL', Timestamp('2023-10-13 17:05:00+0000', tz='UTC'))":179.0,"('AAPL', Timestamp('2023-10-13 17:10:00+0000', tz='UTC'))":178.895,"('AAPL', Timestamp('2023-10-13 17:15:00+0000', tz='UTC'))":178.72,"('AAPL', Timestamp('2023-10-13 17:20:00+0000', tz='UTC'))":178.76,"('AAPL', Timestamp('2023-10-13 17:25:00+0000', tz='UTC'))":178.64,"('AAPL', Timestamp('2023-10-13 17:30:00+0000', tz='UTC'))":178.3576,"('AAPL', Timestamp('2023-10-13 17:35:00+0000', tz='UTC'))":178.34,"('AAPL', Timestamp('2023-10-13 17:40:00+0000', tz='UTC'))":179.02,"('AAPL', Timestamp('2023-10-13 17:45:00+0000', tz='UTC'))":178.96,"('AAPL', Timestamp('2023-10-13 17:50:00+0000', tz='UTC'))":178.91,"('AAPL', Timestamp('2023-10-13 17:55:00+0000', tz='UTC'))":178.97,"('AAPL', Timestamp('2023-10-13 18:00:00+0000', tz='UTC'))":178.94,"('AAPL', Timestamp('2023-10-13 18:05:00+0000', tz='UTC'))":179.11,"('AAPL', Timestamp('2023-10-13 18:10:00+0000', tz='UTC'))":179.01,"('AAPL', Timestamp('2023-10-13 18:15:00+0000', tz='UTC'))":179.17,"('AAPL', Timestamp('2023-10-13 18:20:00+0000', tz='UTC'))":179.31,"('AAPL', Timestamp('2023-10-13 18:25:00+0000', tz='UTC'))":179.265,"('AAPL', Timestamp('2023-10-13 18:30:00+0000', tz='UTC'))":179.54,"('AAPL', Timestamp('2023-10-13 18:35:00+0000', tz='UTC'))":179.47,"('AAPL', Timestamp('2023-10-13 18:40:00+0000', tz='UTC'))":179.35,"('AAPL', Timestamp('2023-10-13 18:45:00+0000', tz='UTC'))":179.2085,"('AAPL', Timestamp('2023-10-13 18:50:00+0000', tz='UTC'))":179.3309,"('AAPL', Timestamp('2023-10-13 18:55:00+0000', tz='UTC'))":179.405,"('AAPL', Timestamp('2023-10-13 19:00:00+0000', tz='UTC'))":179.5,"('AAPL', Timestamp('2023-10-13 19:05:00+0000', tz='UTC'))":179.445,"('AAPL', Timestamp('2023-10-13 19:10:00+0000', tz='UTC'))":179.74,"('AAPL', Timestamp('2023-10-13 19:15:00+0000', tz='UTC'))":179.47,"('AAPL', Timestamp('2023-10-13 19:20:00+0000', tz='UTC'))":179.2,"('AAPL', Timestamp('2023-10-13 19:25:00+0000', tz='UTC'))":179.17,"('AAPL', Timestamp('2023-10-13 19:30:00+0000', tz='UTC'))":179.06,"('AAPL', Timestamp('2023-10-13 19:35:00+0000', tz='UTC'))":179.05,"('AAPL', Timestamp('2023-10-13 19:40:00+0000', tz='UTC'))":178.945,"('AAPL', Timestamp('2023-10-13 19:45:00+0000', tz='UTC'))":178.98,"('AAPL', Timestamp('2023-10-13 19:50:00+0000', tz='UTC'))":179.09,"('AAPL', Timestamp('2023-10-13 19:55:00+0000', tz='UTC'))":179.05,"('AAPL', Timestamp('2023-10-13 20:00:00+0000', tz='UTC'))":178.9,"('AAPL', Timestamp('2023-10-13 20:05:00+0000', tz='UTC'))":178.85,"('AAPL', Timestamp('2023-10-13 20:10:00+0000', tz='UTC'))":178.85,"('AAPL', Timestamp('2023-10-13 20:15:00+0000', tz='UTC'))":178.85,"('AAPL', Timestamp('2023-10-13 20:20:00+0000', tz='UTC'))":178.73,"('AAPL', Timestamp('2023-10-13 20:25:00+0000', tz='UTC'))":178.6557,"('AAPL', Timestamp('2023-10-13 20:30:00+0000', tz='UTC'))":178.68,"('AAPL', Timestamp('2023-10-13 20:35:00+0000', tz='UTC'))":178.65,"('AAPL', Timestamp('2023-10-13 20:40:00+0000', tz='UTC'))":178.61,"('AAPL', Timestamp('2023-10-13 20:45:00+0000', tz='UTC'))":178.85,"('AAPL', Timestamp('2023-10-13 20:50:00+0000', tz='UTC'))":178.75,"('AAPL', Timestamp('2023-10-13 20:55:00+0000', tz='UTC'))":178.66,"('AAPL', Timestamp('2023-10-13 21:05:00+0000', tz='UTC'))":178.69,"('AAPL', Timestamp('2023-10-13 21:10:00+0000', tz='UTC'))":178.66,"('AAPL', Timestamp('2023-10-13 21:15:00+0000', tz='UTC'))":178.85,"('AAPL', Timestamp('2023-10-13 21:20:00+0000', tz='UTC'))":178.62,"('AAPL', Timestamp('2023-10-13 21:25:00+0000', tz='UTC'))":178.63,"('AAPL', Timestamp('2023-10-13 21:30:00+0000', tz='UTC'))":178.65,"('AAPL', Timestamp('2023-10-13 21:35:00+0000', tz='UTC'))":178.54,"('AAPL', Timestamp('2023-10-13 21:40:00+0000', tz='UTC'))":178.6272,"('AAPL', Timestamp('2023-10-13 21:45:00+0000', tz='UTC'))":178.65,"('AAPL', Timestamp('2023-10-13 21:50:00+0000', tz='UTC'))":178.65,"('AAPL', Timestamp('2023-10-13 21:55:00+0000', tz='UTC'))":178.57,"('AAPL', Timestamp('2023-10-13 22:00:00+0000', tz='UTC'))":178.65,"('AAPL', Timestamp('2023-10-13 22:05:00+0000', tz='UTC'))":178.6,"('AAPL', Timestamp('2023-10-13 22:10:00+0000', tz='UTC'))":178.6001,"('AAPL', Timestamp('2023-10-13 22:15:00+0000', tz='UTC'))":178.6,"('AAPL', Timestamp('2023-10-13 22:20:00+0000', tz='UTC'))":178.6,"('AAPL', Timestamp('2023-10-13 22:35:00+0000', tz='UTC'))":178.6,"('AAPL', Timestamp('2023-10-13 22:40:00+0000', tz='UTC'))":178.61,"('AAPL', Timestamp('2023-10-13 22:45:00+0000', tz='UTC'))":178.64,"('AAPL', Timestamp('2023-10-13 22:50:00+0000', tz='UTC'))":178.61,"('AAPL', Timestamp('2023-10-13 22:55:00+0000', tz='UTC'))":178.64,"('AAPL', Timestamp('2023-10-13 23:00:00+0000', tz='UTC'))":178.64,"('AAPL', Timestamp('2023-10-13 23:05:00+0000', tz='UTC'))":178.64,"('AAPL', Timestamp('2023-10-13 23:10:00+0000', tz='UTC'))":178.59,"('AAPL', Timestamp('2023-10-13 23:15:00+0000', tz='UTC'))":178.6,"('AAPL', Timestamp('2023-10-13 23:20:00+0000', tz='UTC'))":178.55,"('AAPL', Timestamp('2023-10-13 23:25:00+0000', tz='UTC'))":178.53,"('AAPL', Timestamp('2023-10-13 23:30:00+0000', tz='UTC'))":178.54,"('AAPL', Timestamp('2023-10-13 23:35:00+0000', tz='UTC'))":178.53,"('AAPL', Timestamp('2023-10-13 23:40:00+0000', tz='UTC'))":178.52,"('AAPL', Timestamp('2023-10-13 23:45:00+0000', tz='UTC'))":178.51,"('AAPL', Timestamp('2023-10-13 23:50:00+0000', tz='UTC'))":178.5},"low":{"('AAPL', Timestamp('2023-10-13 08:00:00+0000', tz='UTC'))":181.05,"('AAPL', Timestamp('2023-10-13 08:05:00+0000', tz='UTC'))":181.1,"('AAPL', Timestamp('2023-10-13 08:10:00+0000', tz='UTC'))":181.05,"('AAPL', Timestamp('2023-10-13 08:15:00+0000', tz='UTC'))":181.03,"('AAPL', Timestamp('2023-10-13 08:25:00+0000', tz='UTC'))":181.0,"('AAPL', Timestamp('2023-10-13 08:30:00+0000', tz='UTC'))":180.92,"('AAPL', Timestamp('2023-10-13 08:40:00+0000', tz='UTC'))":180.65,"('AAPL', Timestamp('2023-10-13 08:45:00+0000', tz='UTC'))":180.72,"('AAPL', Timestamp('2023-10-13 08:50:00+0000', tz='UTC'))":180.72,"('AAPL', Timestamp('2023-10-13 08:55:00+0000', tz='UTC'))":180.74,"('AAPL', Timestamp('2023-10-13 09:00:00+0000', tz='UTC'))":180.65,"('AAPL', Timestamp('2023-10-13 09:05:00+0000', tz='UTC'))":180.52,"('AAPL', Timestamp('2023-10-13 09:10:00+0000', tz='UTC'))":180.65,"('AAPL', Timestamp('2023-10-13 09:15:00+0000', tz='UTC'))":180.57,"('AAPL', Timestamp('2023-10-13 09:20:00+0000', tz='UTC'))":180.6,"('AAPL', Timestamp('2023-10-13 09:25:00+0000', tz='UTC'))":180.65,"('AAPL', Timestamp('2023-10-13 09:30:00+0000', tz='UTC'))":180.58,"('AAPL', Timestamp('2023-10-13 09:35:00+0000', tz='UTC'))":180.58,"('AAPL', Timestamp('2023-10-13 09:40:00+0000', tz='UTC'))":180.51,"('AAPL', Timestamp('2023-10-13 09:45:00+0000', tz='UTC'))":180.51,"('AAPL', Timestamp('2023-10-13 09:50:00+0000', tz='UTC'))":180.24,"('AAPL', Timestamp('2023-10-13 09:55:00+0000', tz='UTC'))":180.22,"('AAPL', Timestamp('2023-10-13 10:00:00+0000', tz='UTC'))":180.24,"('AAPL', Timestamp('2023-10-13 10:05:00+0000', tz='UTC'))":180.11,"('AAPL', Timestamp('2023-10-13 10:10:00+0000', tz='UTC'))":180.04,"('AAPL', Timestamp('2023-10-13 10:15:00+0000', tz='UTC'))":180.06,"('AAPL', Timestamp('2023-10-13 10:20:00+0000', tz='UTC'))":180.08,"('AAPL', Timestamp('2023-10-13 10:25:00+0000', tz='UTC'))":180.09,"('AAPL', Timestamp('2023-10-13 10:30:00+0000', tz='UTC'))":180.08,"('AAPL', Timestamp('2023-10-13 10:35:00+0000', tz='UTC'))":180.11,"('AAPL', Timestamp('2023-10-13 10:40:00+0000', tz='UTC'))":180.09,"('AAPL', Timestamp('2023-10-13 10:45:00+0000', tz='UTC'))":180.15,"('AAPL', Timestamp('2023-10-13 10:50:00+0000', tz='UTC'))":180.22,"('AAPL', Timestamp('2023-10-13 10:55:00+0000', tz='UTC'))":180.25,"('AAPL', Timestamp('2023-10-13 11:00:00+0000', tz='UTC'))":180.26,"('AAPL', Timestamp('2023-10-13 11:05:00+0000', tz='UTC'))":180.36,"('AAPL', Timestamp('2023-10-13 11:10:00+0000', tz='UTC'))":180.4,"('AAPL', Timestamp('2023-10-13 11:15:00+0000', tz='UTC'))":180.3,"('AAPL', Timestamp('2023-10-13 11:20:00+0000', tz='UTC'))":180.25,"('AAPL', Timestamp('2023-10-13 11:25:00+0000', tz='UTC'))":180.29,"('AAPL', Timestamp('2023-10-13 11:30:00+0000', tz='UTC'))":180.31,"('AAPL', Timestamp('2023-10-13 11:35:00+0000', tz='UTC'))":180.25,"('AAPL', Timestamp('2023-10-13 11:40:00+0000', tz='UTC'))":180.12,"('AAPL', Timestamp('2023-10-13 11:45:00+0000', tz='UTC'))":180.11,"('AAPL', Timestamp('2023-10-13 11:50:00+0000', tz='UTC'))":180.2,"('AAPL', Timestamp('2023-10-13 11:55:00+0000', tz='UTC'))":180.25,"('AAPL', Timestamp('2023-10-13 12:00:00+0000', tz='UTC'))":180.1,"('AAPL', Timestamp('2023-10-13 12:05:00+0000', tz='UTC'))":180.16,"('AAPL', Timestamp('2023-10-13 12:10:00+0000', tz='UTC'))":180.16,"('AAPL', Timestamp('2023-10-13 12:15:00+0000', tz='UTC'))":180.1,"('AAPL', Timestamp('2023-10-13 12:20:00+0000', tz='UTC'))":180.1106,"('AAPL', Timestamp('2023-10-13 12:25:00+0000', tz='UTC'))":180.2799,"('AAPL', Timestamp('2023-10-13 12:30:00+0000', tz='UTC'))":180.35,"('AAPL', Timestamp('2023-10-13 12:35:00+0000', tz='UTC'))":180.51,"('AAPL', Timestamp('2023-10-13 12:40:00+0000', tz='UTC'))":180.73,"('AAPL', Timestamp('2023-10-13 12:45:00+0000', tz='UTC'))":180.71,"('AAPL', Timestamp('2023-10-13 12:50:00+0000', tz='UTC'))":180.73,"('AAPL', Timestamp('2023-10-13 12:55:00+0000', tz='UTC'))":180.93,"('AAPL', Timestamp('2023-10-13 13:00:00+0000', tz='UTC'))":180.92,"('AAPL', Timestamp('2023-10-13 13:05:00+0000', tz='UTC'))":181.0,"('AAPL', Timestamp('2023-10-13 13:10:00+0000', tz='UTC'))":181.11,"('AAPL', Timestamp('2023-10-13 13:15:00+0000', tz='UTC'))":181.11,"('AAPL', Timestamp('2023-10-13 13:20:00+0000', tz='UTC'))":181.1,"('AAPL', Timestamp('2023-10-13 13:25:00+0000', tz='UTC'))":181.05,"('AAPL', Timestamp('2023-10-13 13:30:00+0000', tz='UTC'))":181.28,"('AAPL', Timestamp('2023-10-13 13:35:00+0000', tz='UTC'))":180.93,"('AAPL', Timestamp('2023-10-13 13:40:00+0000', tz='UTC'))":181.02,"('AAPL', Timestamp('2023-10-13 13:45:00+0000', tz='UTC'))":181.01,"('AAPL', Timestamp('2023-10-13 13:50:00+0000', tz='UTC'))":181.03,"('AAPL', Timestamp('2023-10-13 13:55:00+0000', tz='UTC'))":181.04,"('AAPL', Timestamp('2023-10-13 14:00:00+0000', tz='UTC'))":180.57,"('AAPL', Timestamp('2023-10-13 14:05:00+0000', tz='UTC'))":180.7,"('AAPL', Timestamp('2023-10-13 14:10:00+0000', tz='UTC'))":180.55,"('AAPL', Timestamp('2023-10-13 14:15:00+0000', tz='UTC'))":180.47,"('AAPL', Timestamp('2023-10-13 14:20:00+0000', tz='UTC'))":180.36,"('AAPL', Timestamp('2023-10-13 14:25:00+0000', tz='UTC'))":180.36,"('AAPL', Timestamp('2023-10-13 14:30:00+0000', tz='UTC'))":180.4,"('AAPL', Timestamp('2023-10-13 14:35:00+0000', tz='UTC'))":180.3929,"('AAPL', Timestamp('2023-10-13 14:40:00+0000', tz='UTC'))":180.22,"('AAPL', Timestamp('2023-10-13 14:45:00+0000', tz='UTC'))":179.97,"('AAPL', Timestamp('2023-10-13 14:50:00+0000', tz='UTC'))":179.3701,"('AAPL', Timestamp('2023-10-13 14:55:00+0000', tz='UTC'))":179.53,"('AAPL', Timestamp('2023-10-13 15:00:00+0000', tz='UTC'))":179.53,"('AAPL', Timestamp('2023-10-13 15:05:00+0000', tz='UTC'))":179.2493,"('AAPL', Timestamp('2023-10-13 15:10:00+0000', tz='UTC'))":179.415,"('AAPL', Timestamp('2023-10-13 15:15:00+0000', tz='UTC'))":179.16,"('AAPL', Timestamp('2023-10-13 15:20:00+0000', tz='UTC'))":178.95,"('AAPL', Timestamp('2023-10-13 15:25:00+0000', tz='UTC'))":178.97,"('AAPL', Timestamp('2023-10-13 15:30:00+0000', tz='UTC'))":179.035,"('AAPL', Timestamp('2023-10-13 15:35:00+0000', tz='UTC'))":178.95,"('AAPL', Timestamp('2023-10-13 15:40:00+0000', tz='UTC'))":179.11,"('AAPL', Timestamp('2023-10-13 15:45:00+0000', tz='UTC'))":178.95,"('AAPL', Timestamp('2023-10-13 15:50:00+0000', tz='UTC'))":178.58,"('AAPL', Timestamp('2023-10-13 15:55:00+0000', tz='UTC'))":178.47,"('AAPL', Timestamp('2023-10-13 16:00:00+0000', tz='UTC'))":178.5301,"('AAPL', Timestamp('2023-10-13 16:05:00+0000', tz='UTC'))":178.7,"('AAPL', Timestamp('2023-10-13 16:10:00+0000', tz='UTC'))":178.73,"('AAPL', Timestamp('2023-10-13 16:15:00+0000', tz='UTC'))":178.71,"('AAPL', Timestamp('2023-10-13 16:20:00+0000', tz='UTC'))":179.08,"('AAPL', Timestamp('2023-10-13 16:25:00+0000', tz='UTC'))":179.12,"('AAPL', Timestamp('2023-10-13 16:30:00+0000', tz='UTC'))":179.22,"('AAPL', Timestamp('2023-10-13 16:35:00+0000', tz='UTC'))":179.19,"('AAPL', Timestamp('2023-10-13 16:40:00+0000', tz='UTC'))":179.22,"('AAPL', Timestamp('2023-10-13 16:45:00+0000', tz='UTC'))":179.16,"('AAPL', Timestamp('2023-10-13 16:50:00+0000', tz='UTC'))":178.84,"('AAPL', Timestamp('2023-10-13 16:55:00+0000', tz='UTC'))":178.995,"('AAPL', Timestamp('2023-10-13 17:00:00+0000', tz='UTC'))":178.96,"('AAPL', Timestamp('2023-10-13 17:05:00+0000', tz='UTC'))":178.61,"('AAPL', Timestamp('2023-10-13 17:10:00+0000', tz='UTC'))":178.575,"('AAPL', Timestamp('2023-10-13 17:15:00+0000', tz='UTC'))":178.5001,"('AAPL', Timestamp('2023-10-13 17:20:00+0000', tz='UTC'))":178.53,"('AAPL', Timestamp('2023-10-13 17:25:00+0000', tz='UTC'))":178.22,"('AAPL', Timestamp('2023-10-13 17:30:00+0000', tz='UTC'))":178.16,"('AAPL', Timestamp('2023-10-13 17:35:00+0000', tz='UTC'))":178.14,"('AAPL', Timestamp('2023-10-13 17:40:00+0000', tz='UTC'))":178.3,"('AAPL', Timestamp('2023-10-13 17:45:00+0000', tz='UTC'))":178.69,"('AAPL', Timestamp('2023-10-13 17:50:00+0000', tz='UTC'))":178.7206,"('AAPL', Timestamp('2023-10-13 17:55:00+0000', tz='UTC'))":178.75,"('AAPL', Timestamp('2023-10-13 18:00:00+0000', tz='UTC'))":178.69,"('AAPL', Timestamp('2023-10-13 18:05:00+0000', tz='UTC'))":178.76,"('AAPL', Timestamp('2023-10-13 18:10:00+0000', tz='UTC'))":178.83,"('AAPL', Timestamp('2023-10-13 18:15:00+0000', tz='UTC'))":178.8,"('AAPL', Timestamp('2023-10-13 18:20:00+0000', tz='UTC'))":179.05,"('AAPL', Timestamp('2023-10-13 18:25:00+0000', tz='UTC'))":179.03,"('AAPL', Timestamp('2023-10-13 18:30:00+0000', tz='UTC'))":179.21,"('AAPL', Timestamp('2023-10-13 18:35:00+0000', tz='UTC'))":179.14,"('AAPL', Timestamp('2023-10-13 18:40:00+0000', tz='UTC'))":179.065,"('AAPL', Timestamp('2023-10-13 18:45:00+0000', tz='UTC'))":178.9688,"('AAPL', Timestamp('2023-10-13 18:50:00+0000', tz='UTC'))":178.99,"('AAPL', Timestamp('2023-10-13 18:55:00+0000', tz='UTC'))":179.16,"('AAPL', Timestamp('2023-10-13 19:00:00+0000', tz='UTC'))":179.23,"('AAPL', Timestamp('2023-10-13 19:05:00+0000', tz='UTC'))":179.09,"('AAPL', Timestamp('2023-10-13 19:10:00+0000', tz='UTC'))":179.31,"('AAPL', Timestamp('2023-10-13 19:15:00+0000', tz='UTC'))":179.09,"('AAPL', Timestamp('2023-10-13 19:20:00+0000', tz='UTC'))":178.97,"('AAPL', Timestamp('2023-10-13 19:25:00+0000', tz='UTC'))":178.85,"('AAPL', Timestamp('2023-10-13 19:30:00+0000', tz='UTC'))":178.905,"('AAPL', Timestamp('2023-10-13 19:35:00+0000', tz='UTC'))":178.85,"('AAPL', Timestamp('2023-10-13 19:40:00+0000', tz='UTC'))":178.52,"('AAPL', Timestamp('2023-10-13 19:45:00+0000', tz='UTC'))":178.59,"('AAPL', Timestamp('2023-10-13 19:50:00+0000', tz='UTC'))":178.8,"('AAPL', Timestamp('2023-10-13 19:55:00+0000', tz='UTC'))":178.7,"('AAPL', Timestamp('2023-10-13 20:00:00+0000', tz='UTC'))":178.76,"('AAPL', Timestamp('2023-10-13 20:05:00+0000', tz='UTC'))":178.7,"('AAPL', Timestamp('2023-10-13 20:10:00+0000', tz='UTC'))":178.72,"('AAPL', Timestamp('2023-10-13 20:15:00+0000', tz='UTC'))":178.65,"('AAPL', Timestamp('2023-10-13 20:20:00+0000', tz='UTC'))":178.6,"('AAPL', Timestamp('2023-10-13 20:25:00+0000', tz='UTC'))":178.63,"('AAPL', Timestamp('2023-10-13 20:30:00+0000', tz='UTC'))":178.6499,"('AAPL', Timestamp('2023-10-13 20:35:00+0000', tz='UTC'))":178.6,"('AAPL', Timestamp('2023-10-13 20:40:00+0000', tz='UTC'))":178.55,"('AAPL', Timestamp('2023-10-13 20:45:00+0000', tz='UTC'))":178.56,"('AAPL', Timestamp('2023-10-13 20:50:00+0000', tz='UTC'))":178.58,"('AAPL', Timestamp('2023-10-13 20:55:00+0000', tz='UTC'))":178.65,"('AAPL', Timestamp('2023-10-13 21:05:00+0000', tz='UTC'))":178.65,"('AAPL', Timestamp('2023-10-13 21:10:00+0000', tz='UTC'))":178.65,"('AAPL', Timestamp('2023-10-13 21:15:00+0000', tz='UTC'))":178.65,"('AAPL', Timestamp('2023-10-13 21:20:00+0000', tz='UTC'))":178.6,"('AAPL', Timestamp('2023-10-13 21:25:00+0000', tz='UTC'))":178.63,"('AAPL', Timestamp('2023-10-13 21:30:00+0000', tz='UTC'))":178.56,"('AAPL', Timestamp('2023-10-13 21:35:00+0000', tz='UTC'))":178.54,"('AAPL', Timestamp('2023-10-13 21:40:00+0000', tz='UTC'))":178.6272,"('AAPL', Timestamp('2023-10-13 21:45:00+0000', tz='UTC'))":178.61,"('AAPL', Timestamp('2023-10-13 21:50:00+0000', tz='UTC'))":178.56,"('AAPL', Timestamp('2023-10-13 21:55:00+0000', tz='UTC'))":178.57,"('AAPL', Timestamp('2023-10-13 22:00:00+0000', tz='UTC'))":178.58,"('AAPL', Timestamp('2023-10-13 22:05:00+0000', tz='UTC'))":178.6,"('AAPL', Timestamp('2023-10-13 22:10:00+0000', tz='UTC'))":178.5367,"('AAPL', Timestamp('2023-10-13 22:15:00+0000', tz='UTC'))":178.6,"('AAPL', Timestamp('2023-10-13 22:20:00+0000', tz='UTC'))":178.56,"('AAPL', Timestamp('2023-10-13 22:35:00+0000', tz='UTC'))":178.57,"('AAPL', Timestamp('2023-10-13 22:40:00+0000', tz='UTC'))":178.57,"('AAPL', Timestamp('2023-10-13 22:45:00+0000', tz='UTC'))":178.636,"('AAPL', Timestamp('2023-10-13 22:50:00+0000', tz='UTC'))":178.6046,"('AAPL', Timestamp('2023-10-13 22:55:00+0000', tz='UTC'))":178.64,"('AAPL', Timestamp('2023-10-13 23:00:00+0000', tz='UTC'))":178.59,"('AAPL', Timestamp('2023-10-13 23:05:00+0000', tz='UTC'))":178.62,"('AAPL', Timestamp('2023-10-13 23:10:00+0000', tz='UTC'))":178.59,"('AAPL', Timestamp('2023-10-13 23:15:00+0000', tz='UTC'))":178.6,"('AAPL', Timestamp('2023-10-13 23:20:00+0000', tz='UTC'))":178.54,"('AAPL', Timestamp('2023-10-13 23:25:00+0000', tz='UTC'))":178.52,"('AAPL', Timestamp('2023-10-13 23:30:00+0000', tz='UTC'))":178.53,"('AAPL', Timestamp('2023-10-13 23:35:00+0000', tz='UTC'))":178.52,"('AAPL', Timestamp('2023-10-13 23:40:00+0000', tz='UTC'))":178.51,"('AAPL', Timestamp('2023-10-13 23:45:00+0000', tz='UTC'))":178.5,"('AAPL', Timestamp('2023-10-13 23:50:00+0000', tz='UTC'))":178.5},"close":{"('AAPL', Timestamp('2023-10-13 08:00:00+0000', tz='UTC'))":181.05,"('AAPL', Timestamp('2023-10-13 08:05:00+0000', tz='UTC'))":181.1,"('AAPL', Timestamp('2023-10-13 08:10:00+0000', tz='UTC'))":181.05,"('AAPL', Timestamp('2023-10-13 08:15:00+0000', tz='UTC'))":181.03,"('AAPL', Timestamp('2023-10-13 08:25:00+0000', tz='UTC'))":181.0,"('AAPL', Timestamp('2023-10-13 08:30:00+0000', tz='UTC'))":180.92,"('AAPL', Timestamp('2023-10-13 08:40:00+0000', tz='UTC'))":180.65,"('AAPL', Timestamp('2023-10-13 08:45:00+0000', tz='UTC'))":180.72,"('AAPL', Timestamp('2023-10-13 08:50:00+0000', tz='UTC'))":180.75,"('AAPL', Timestamp('2023-10-13 08:55:00+0000', tz='UTC'))":180.8,"('AAPL', Timestamp('2023-10-13 09:00:00+0000', tz='UTC'))":180.65,"('AAPL', Timestamp('2023-10-13 09:05:00+0000', tz='UTC'))":180.57,"('AAPL', Timestamp('2023-10-13 09:10:00+0000', tz='UTC'))":180.65,"('AAPL', Timestamp('2023-10-13 09:15:00+0000', tz='UTC'))":180.57,"('AAPL', Timestamp('2023-10-13 09:20:00+0000', tz='UTC'))":180.61,"('AAPL', Timestamp('2023-10-13 09:25:00+0000', tz='UTC'))":180.71,"('AAPL', Timestamp('2023-10-13 09:30:00+0000', tz='UTC'))":180.58,"('AAPL', Timestamp('2023-10-13 09:35:00+0000', tz='UTC'))":180.58,"('AAPL', Timestamp('2023-10-13 09:40:00+0000', tz='UTC'))":180.52,"('AAPL', Timestamp('2023-10-13 09:45:00+0000', tz='UTC'))":180.51,"('AAPL', Timestamp('2023-10-13 09:50:00+0000', tz='UTC'))":180.26,"('AAPL', Timestamp('2023-10-13 09:55:00+0000', tz='UTC'))":180.22,"('AAPL', Timestamp('2023-10-13 10:00:00+0000', tz='UTC'))":180.24,"('AAPL', Timestamp('2023-10-13 10:05:00+0000', tz='UTC'))":180.11,"('AAPL', Timestamp('2023-10-13 10:10:00+0000', tz='UTC'))":180.04,"('AAPL', Timestamp('2023-10-13 10:15:00+0000', tz='UTC'))":180.15,"('AAPL', Timestamp('2023-10-13 10:20:00+0000', tz='UTC'))":180.09,"('AAPL', Timestamp('2023-10-13 10:25:00+0000', tz='UTC'))":180.09,"('AAPL', Timestamp('2023-10-13 10:30:00+0000', tz='UTC'))":180.11,"('AAPL', Timestamp('2023-10-13 10:35:00+0000', tz='UTC'))":180.11,"('AAPL', Timestamp('2023-10-13 10:40:00+0000', tz='UTC'))":180.09,"('AAPL', Timestamp('2023-10-13 10:45:00+0000', tz='UTC'))":180.22,"('AAPL', Timestamp('2023-10-13 10:50:00+0000', tz='UTC'))":180.22,"('AAPL', Timestamp('2023-10-13 10:55:00+0000', tz='UTC'))":180.25,"('AAPL', Timestamp('2023-10-13 11:00:00+0000', tz='UTC'))":180.3,"('AAPL', Timestamp('2023-10-13 11:05:00+0000', tz='UTC'))":180.45,"('AAPL', Timestamp('2023-10-13 11:10:00+0000', tz='UTC'))":180.44,"('AAPL', Timestamp('2023-10-13 11:15:00+0000', tz='UTC'))":180.37,"('AAPL', Timestamp('2023-10-13 11:20:00+0000', tz='UTC'))":180.29,"('AAPL', Timestamp('2023-10-13 11:25:00+0000', tz='UTC'))":180.29,"('AAPL', Timestamp('2023-10-13 11:30:00+0000', tz='UTC'))":180.35,"('AAPL', Timestamp('2023-10-13 11:35:00+0000', tz='UTC'))":180.31,"('AAPL', Timestamp('2023-10-13 11:40:00+0000', tz='UTC'))":180.12,"('AAPL', Timestamp('2023-10-13 11:45:00+0000', tz='UTC'))":180.16,"('AAPL', Timestamp('2023-10-13 11:50:00+0000', tz='UTC'))":180.25,"('AAPL', Timestamp('2023-10-13 11:55:00+0000', tz='UTC'))":180.25,"('AAPL', Timestamp('2023-10-13 12:00:00+0000', tz='UTC'))":180.2,"('AAPL', Timestamp('2023-10-13 12:05:00+0000', tz='UTC'))":180.18,"('AAPL', Timestamp('2023-10-13 12:10:00+0000', tz='UTC'))":180.17,"('AAPL', Timestamp('2023-10-13 12:15:00+0000', tz='UTC'))":180.17,"('AAPL', Timestamp('2023-10-13 12:20:00+0000', tz='UTC'))":180.28,"('AAPL', Timestamp('2023-10-13 12:25:00+0000', tz='UTC'))":180.31,"('AAPL', Timestamp('2023-10-13 12:30:00+0000', tz='UTC'))":180.58,"('AAPL', Timestamp('2023-10-13 12:35:00+0000', tz='UTC'))":180.88,"('AAPL', Timestamp('2023-10-13 12:40:00+0000', tz='UTC'))":180.75,"('AAPL', Timestamp('2023-10-13 12:45:00+0000', tz='UTC'))":180.8,"('AAPL', Timestamp('2023-10-13 12:50:00+0000', tz='UTC'))":180.88,"('AAPL', Timestamp('2023-10-13 12:55:00+0000', tz='UTC'))":181.05,"('AAPL', Timestamp('2023-10-13 13:00:00+0000', tz='UTC'))":181.09,"('AAPL', Timestamp('2023-10-13 13:05:00+0000', tz='UTC'))":181.11,"('AAPL', Timestamp('2023-10-13 13:10:00+0000', tz='UTC'))":181.24,"('AAPL', Timestamp('2023-10-13 13:15:00+0000', tz='UTC'))":181.2,"('AAPL', Timestamp('2023-10-13 13:20:00+0000', tz='UTC'))":181.11,"('AAPL', Timestamp('2023-10-13 13:25:00+0000', tz='UTC'))":181.39,"('AAPL', Timestamp('2023-10-13 13:30:00+0000', tz='UTC'))":181.48,"('AAPL', Timestamp('2023-10-13 13:35:00+0000', tz='UTC'))":181.285,"('AAPL', Timestamp('2023-10-13 13:40:00+0000', tz='UTC'))":181.18,"('AAPL', Timestamp('2023-10-13 13:45:00+0000', tz='UTC'))":181.36,"('AAPL', Timestamp('2023-10-13 13:50:00+0000', tz='UTC'))":181.17,"('AAPL', Timestamp('2023-10-13 13:55:00+0000', tz='UTC'))":181.17,"('AAPL', Timestamp('2023-10-13 14:00:00+0000', tz='UTC'))":181.02,"('AAPL', Timestamp('2023-10-13 14:05:00+0000', tz='UTC'))":181.0,"('AAPL', Timestamp('2023-10-13 14:10:00+0000', tz='UTC'))":180.58,"('AAPL', Timestamp('2023-10-13 14:15:00+0000', tz='UTC'))":180.59,"('AAPL', Timestamp('2023-10-13 14:20:00+0000', tz='UTC'))":180.37,"('AAPL', Timestamp('2023-10-13 14:25:00+0000', tz='UTC'))":180.53,"('AAPL', Timestamp('2023-10-13 14:30:00+0000', tz='UTC'))":180.735,"('AAPL', Timestamp('2023-10-13 14:35:00+0000', tz='UTC'))":180.405,"('AAPL', Timestamp('2023-10-13 14:40:00+0000', tz='UTC'))":180.3087,"('AAPL', Timestamp('2023-10-13 14:45:00+0000', tz='UTC'))":180.0899,"('AAPL', Timestamp('2023-10-13 14:50:00+0000', tz='UTC'))":179.64,"('AAPL', Timestamp('2023-10-13 14:55:00+0000', tz='UTC'))":179.625,"('AAPL', Timestamp('2023-10-13 15:00:00+0000', tz='UTC'))":179.62,"('AAPL', Timestamp('2023-10-13 15:05:00+0000', tz='UTC'))":179.58,"('AAPL', Timestamp('2023-10-13 15:10:00+0000', tz='UTC'))":179.4575,"('AAPL', Timestamp('2023-10-13 15:15:00+0000', tz='UTC'))":179.3299,"('AAPL', Timestamp('2023-10-13 15:20:00+0000', tz='UTC'))":178.97,"('AAPL', Timestamp('2023-10-13 15:25:00+0000', tz='UTC'))":179.19,"('AAPL', Timestamp('2023-10-13 15:30:00+0000', tz='UTC'))":179.13,"('AAPL', Timestamp('2023-10-13 15:35:00+0000', tz='UTC'))":179.29,"('AAPL', Timestamp('2023-10-13 15:40:00+0000', tz='UTC'))":179.14,"('AAPL', Timestamp('2023-10-13 15:45:00+0000', tz='UTC'))":179.0,"('AAPL', Timestamp('2023-10-13 15:50:00+0000', tz='UTC'))":178.66,"('AAPL', Timestamp('2023-10-13 15:55:00+0000', tz='UTC'))":178.61,"('AAPL', Timestamp('2023-10-13 16:00:00+0000', tz='UTC'))":178.71,"('AAPL', Timestamp('2023-10-13 16:05:00+0000', tz='UTC'))":178.9587,"('AAPL', Timestamp('2023-10-13 16:10:00+0000', tz='UTC'))":178.75,"('AAPL', Timestamp('2023-10-13 16:15:00+0000', tz='UTC'))":179.13,"('AAPL', Timestamp('2023-10-13 16:20:00+0000', tz='UTC'))":179.19,"('AAPL', Timestamp('2023-10-13 16:25:00+0000', tz='UTC'))":179.255,"('AAPL', Timestamp('2023-10-13 16:30:00+0000', tz='UTC'))":179.4,"('AAPL', Timestamp('2023-10-13 16:35:00+0000', tz='UTC'))":179.21,"('AAPL', Timestamp('2023-10-13 16:40:00+0000', tz='UTC'))":179.32,"('AAPL', Timestamp('2023-10-13 16:45:00+0000', tz='UTC'))":179.1601,"('AAPL', Timestamp('2023-10-13 16:50:00+0000', tz='UTC'))":179.03,"('AAPL', Timestamp('2023-10-13 16:55:00+0000', tz='UTC'))":179.06,"('AAPL', Timestamp('2023-10-13 17:00:00+0000', tz='UTC'))":179.005,"('AAPL', Timestamp('2023-10-13 17:05:00+0000', tz='UTC'))":178.69,"('AAPL', Timestamp('2023-10-13 17:10:00+0000', tz='UTC'))":178.58,"('AAPL', Timestamp('2023-10-13 17:15:00+0000', tz='UTC'))":178.555,"('AAPL', Timestamp('2023-10-13 17:20:00+0000', tz='UTC'))":178.62,"('AAPL', Timestamp('2023-10-13 17:25:00+0000', tz='UTC'))":178.26,"('AAPL', Timestamp('2023-10-13 17:30:00+0000', tz='UTC'))":178.29,"('AAPL', Timestamp('2023-10-13 17:35:00+0000', tz='UTC'))":178.31,"('AAPL', Timestamp('2023-10-13 17:40:00+0000', tz='UTC'))":178.84,"('AAPL', Timestamp('2023-10-13 17:45:00+0000', tz='UTC'))":178.77,"('AAPL', Timestamp('2023-10-13 17:50:00+0000', tz='UTC'))":178.79,"('AAPL', Timestamp('2023-10-13 17:55:00+0000', tz='UTC'))":178.82,"('AAPL', Timestamp('2023-10-13 18:00:00+0000', tz='UTC'))":178.7773,"('AAPL', Timestamp('2023-10-13 18:05:00+0000', tz='UTC'))":178.89,"('AAPL', Timestamp('2023-10-13 18:10:00+0000', tz='UTC'))":178.9601,"('AAPL', Timestamp('2023-10-13 18:15:00+0000', tz='UTC'))":179.12,"('AAPL', Timestamp('2023-10-13 18:20:00+0000', tz='UTC'))":179.13,"('AAPL', Timestamp('2023-10-13 18:25:00+0000', tz='UTC'))":179.24,"('AAPL', Timestamp('2023-10-13 18:30:00+0000', tz='UTC'))":179.42,"('AAPL', Timestamp('2023-10-13 18:35:00+0000', tz='UTC'))":179.24,"('AAPL', Timestamp('2023-10-13 18:40:00+0000', tz='UTC'))":179.1,"('AAPL', Timestamp('2023-10-13 18:45:00+0000', tz='UTC'))":179.03,"('AAPL', Timestamp('2023-10-13 18:50:00+0000', tz='UTC'))":179.3,"('AAPL', Timestamp('2023-10-13 18:55:00+0000', tz='UTC'))":179.3399,"('AAPL', Timestamp('2023-10-13 19:00:00+0000', tz='UTC'))":179.4201,"('AAPL', Timestamp('2023-10-13 19:05:00+0000', tz='UTC'))":179.41,"('AAPL', Timestamp('2023-10-13 19:10:00+0000', tz='UTC'))":179.4689,"('AAPL', Timestamp('2023-10-13 19:15:00+0000', tz='UTC'))":179.17,"('AAPL', Timestamp('2023-10-13 19:20:00+0000', tz='UTC'))":179.15,"('AAPL', Timestamp('2023-10-13 19:25:00+0000', tz='UTC'))":178.935,"('AAPL', Timestamp('2023-10-13 19:30:00+0000', tz='UTC'))":178.96,"('AAPL', Timestamp('2023-10-13 19:35:00+0000', tz='UTC'))":178.935,"('AAPL', Timestamp('2023-10-13 19:40:00+0000', tz='UTC'))":178.61,"('AAPL', Timestamp('2023-10-13 19:45:00+0000', tz='UTC'))":178.96,"('AAPL', Timestamp('2023-10-13 19:50:00+0000', tz='UTC'))":179.06,"('AAPL', Timestamp('2023-10-13 19:55:00+0000', tz='UTC'))":178.87,"('AAPL', Timestamp('2023-10-13 20:00:00+0000', tz='UTC'))":178.76,"('AAPL', Timestamp('2023-10-13 20:05:00+0000', tz='UTC'))":178.7,"('AAPL', Timestamp('2023-10-13 20:10:00+0000', tz='UTC'))":178.72,"('AAPL', Timestamp('2023-10-13 20:15:00+0000', tz='UTC'))":178.72,"('AAPL', Timestamp('2023-10-13 20:20:00+0000', tz='UTC'))":178.63,"('AAPL', Timestamp('2023-10-13 20:25:00+0000', tz='UTC'))":178.65,"('AAPL', Timestamp('2023-10-13 20:30:00+0000', tz='UTC'))":178.6499,"('AAPL', Timestamp('2023-10-13 20:35:00+0000', tz='UTC'))":178.61,"('AAPL', Timestamp('2023-10-13 20:40:00+0000', tz='UTC'))":178.55,"('AAPL', Timestamp('2023-10-13 20:45:00+0000', tz='UTC'))":178.85,"('AAPL', Timestamp('2023-10-13 20:50:00+0000', tz='UTC'))":178.65,"('AAPL', Timestamp('2023-10-13 20:55:00+0000', tz='UTC'))":178.65,"('AAPL', Timestamp('2023-10-13 21:05:00+0000', tz='UTC'))":178.65,"('AAPL', Timestamp('2023-10-13 21:10:00+0000', tz='UTC'))":178.66,"('AAPL', Timestamp('2023-10-13 21:15:00+0000', tz='UTC'))":178.65,"('AAPL', Timestamp('2023-10-13 21:20:00+0000', tz='UTC'))":178.6,"('AAPL', Timestamp('2023-10-13 21:25:00+0000', tz='UTC'))":178.63,"('AAPL', Timestamp('2023-10-13 21:30:00+0000', tz='UTC'))":178.65,"('AAPL', Timestamp('2023-10-13 21:35:00+0000', tz='UTC'))":178.54,"('AAPL', Timestamp('2023-10-13 21:40:00+0000', tz='UTC'))":178.6272,"('AAPL', Timestamp('2023-10-13 21:45:00+0000', tz='UTC'))":178.65,"('AAPL', Timestamp('2023-10-13 21:50:00+0000', tz='UTC'))":178.56,"('AAPL', Timestamp('2023-10-13 21:55:00+0000', tz='UTC'))":178.57,"('AAPL', Timestamp('2023-10-13 22:00:00+0000', tz='UTC'))":178.64,"('AAPL', Timestamp('2023-10-13 22:05:00+0000', tz='UTC'))":178.6,"('AAPL', Timestamp('2023-10-13 22:10:00+0000', tz='UTC'))":178.5404,"('AAPL', Timestamp('2023-10-13 22:15:00+0000', tz='UTC'))":178.6,"('AAPL', Timestamp('2023-10-13 22:20:00+0000', tz='UTC'))":178.56,"('AAPL', Timestamp('2023-10-13 22:35:00+0000', tz='UTC'))":178.6,"('AAPL', Timestamp('2023-10-13 22:40:00+0000', tz='UTC'))":178.61,"('AAPL', Timestamp('2023-10-13 22:45:00+0000', tz='UTC'))":178.64,"('AAPL', Timestamp('2023-10-13 22:50:00+0000', tz='UTC'))":178.61,"('AAPL', Timestamp('2023-10-13 22:55:00+0000', tz='UTC'))":178.64,"('AAPL', Timestamp('2023-10-13 23:00:00+0000', tz='UTC'))":178.59,"('AAPL', Timestamp('2023-10-13 23:05:00+0000', tz='UTC'))":178.64,"('AAPL', Timestamp('2023-10-13 23:10:00+0000', tz='UTC'))":178.59,"('AAPL', Timestamp('2023-10-13 23:15:00+0000', tz='UTC'))":178.6,"('AAPL', Timestamp('2023-10-13 23:20:00+0000', tz='UTC'))":178.54,"('AAPL', Timestamp('2023-10-13 23:25:00+0000', tz='UTC'))":178.52,"('AAPL', Timestamp('2023-10-13 23:30:00+0000', tz='UTC'))":178.5301,"('AAPL', Timestamp('2023-10-13 23:35:00+0000', tz='UTC'))":178.52,"('AAPL', Timestamp('2023-10-13 23:40:00+0000', tz='UTC'))":178.51,"('AAPL', Timestamp('2023-10-13 23:45:00+0000', tz='UTC'))":178.5,"('AAPL', Timestamp('2023-10-13 23:50:00+0000', tz='UTC'))":178.5},"volume":{"('AAPL', Timestamp('2023-10-13 08:00:00+0000', tz='UTC'))":584.0,"('AAPL', Timestamp('2023-10-13 08:05:00+0000', tz='UTC'))":491.0,"('AAPL', Timestamp('2023-10-13 08:10:00+0000', tz='UTC'))":1014.0,"('AAPL', Timestamp('2023-10-13 08:15:00+0000', tz='UTC'))":1243.0,"('AAPL', Timestamp('2023-10-13 08:25:00+0000', tz='UTC'))":2260.0,"('AAPL', Timestamp('2023-10-13 08:30:00+0000', tz='UTC'))":4257.0,"('AAPL', Timestamp('2023-10-13 08:40:00+0000', tz='UTC'))":5422.0,"('AAPL', Timestamp('2023-10-13 08:45:00+0000', tz='UTC'))":568.0,"('AAPL', Timestamp('2023-10-13 08:50:00+0000', tz='UTC'))":1218.0,"('AAPL', Timestamp('2023-10-13 08:55:00+0000', tz='UTC'))":2052.0,"('AAPL', Timestamp('2023-10-13 09:00:00+0000', tz='UTC'))":2721.0,"('AAPL', Timestamp('2023-10-13 09:05:00+0000', tz='UTC'))":2129.0,"('AAPL', Timestamp('2023-10-13 09:10:00+0000', tz='UTC'))":266.0,"('AAPL', Timestamp('2023-10-13 09:15:00+0000', tz='UTC'))":3833.0,"('AAPL', Timestamp('2023-10-13 09:20:00+0000', tz='UTC'))":277.0,"('AAPL', Timestamp('2023-10-13 09:25:00+0000', tz='UTC'))":2672.0,"('AAPL', Timestamp('2023-10-13 09:30:00+0000', tz='UTC'))":1226.0,"('AAPL', Timestamp('2023-10-13 09:35:00+0000', tz='UTC'))":1187.0,"('AAPL', Timestamp('2023-10-13 09:40:00+0000', tz='UTC'))":3384.0,"('AAPL', Timestamp('2023-10-13 09:45:00+0000', tz='UTC'))":2144.0,"('AAPL', Timestamp('2023-10-13 09:50:00+0000', tz='UTC'))":4835.0,"('AAPL', Timestamp('2023-10-13 09:55:00+0000', tz='UTC'))":1657.0,"('AAPL', Timestamp('2023-10-13 10:00:00+0000', tz='UTC'))":1920.0,"('AAPL', Timestamp('2023-10-13 10:05:00+0000', tz='UTC'))":3490.0,"('AAPL', Timestamp('2023-10-13 10:10:00+0000', tz='UTC'))":972.0,"('AAPL', Timestamp('2023-10-13 10:15:00+0000', tz='UTC'))":1449.0,"('AAPL', Timestamp('2023-10-13 10:20:00+0000', tz='UTC'))":2527.0,"('AAPL', Timestamp('2023-10-13 10:25:00+0000', tz='UTC'))":6229.0,"('AAPL', Timestamp('2023-10-13 10:30:00+0000', tz='UTC'))":3821.0,"('AAPL', Timestamp('2023-10-13 10:35:00+0000', tz='UTC'))":631.0,"('AAPL', Timestamp('2023-10-13 10:40:00+0000', tz='UTC'))":235.0,"('AAPL', Timestamp('2023-10-13 10:45:00+0000', tz='UTC'))":1661.0,"('AAPL', Timestamp('2023-10-13 10:50:00+0000', tz='UTC'))":4657.0,"('AAPL', Timestamp('2023-10-13 10:55:00+0000', tz='UTC'))":307.0,"('AAPL', Timestamp('2023-10-13 11:00:00+0000', tz='UTC'))":5576.0,"('AAPL', Timestamp('2023-10-13 11:05:00+0000', tz='UTC'))":3325.0,"('AAPL', Timestamp('2023-10-13 11:10:00+0000', tz='UTC'))":2495.0,"('AAPL', Timestamp('2023-10-13 11:15:00+0000', tz='UTC'))":3851.0,"('AAPL', Timestamp('2023-10-13 11:20:00+0000', tz='UTC'))":1395.0,"('AAPL', Timestamp('2023-10-13 11:25:00+0000', tz='UTC'))":391.0,"('AAPL', Timestamp('2023-10-13 11:30:00+0000', tz='UTC'))":1366.0,"('AAPL', Timestamp('2023-10-13 11:35:00+0000', tz='UTC'))":12503.0,"('AAPL', Timestamp('2023-10-13 11:40:00+0000', tz='UTC'))":8983.0,"('AAPL', Timestamp('2023-10-13 11:45:00+0000', tz='UTC'))":3099.0,"('AAPL', Timestamp('2023-10-13 11:50:00+0000', tz='UTC'))":5190.0,"('AAPL', Timestamp('2023-10-13 11:55:00+0000', tz='UTC'))":1433.0,"('AAPL', Timestamp('2023-10-13 12:00:00+0000', tz='UTC'))":28555.0,"('AAPL', Timestamp('2023-10-13 12:05:00+0000', tz='UTC'))":8067.0,"('AAPL', Timestamp('2023-10-13 12:10:00+0000', tz='UTC'))":3691.0,"('AAPL', Timestamp('2023-10-13 12:15:00+0000', tz='UTC'))":10062.0,"('AAPL', Timestamp('2023-10-13 12:20:00+0000', tz='UTC'))":7210.0,"('AAPL', Timestamp('2023-10-13 12:25:00+0000', tz='UTC'))":12856.0,"('AAPL', Timestamp('2023-10-13 12:30:00+0000', tz='UTC'))":10859.0,"('AAPL', Timestamp('2023-10-13 12:35:00+0000', tz='UTC'))":17685.0,"('AAPL', Timestamp('2023-10-13 12:40:00+0000', tz='UTC'))":20572.0,"('AAPL', Timestamp('2023-10-13 12:45:00+0000', tz='UTC'))":9167.0,"('AAPL', Timestamp('2023-10-13 12:50:00+0000', tz='UTC'))":10014.0,"('AAPL', Timestamp('2023-10-13 12:55:00+0000', tz='UTC'))":18641.0,"('AAPL', Timestamp('2023-10-13 13:00:00+0000', tz='UTC'))":17046.0,"('AAPL', Timestamp('2023-10-13 13:05:00+0000', tz='UTC'))":14578.0,"('AAPL', Timestamp('2023-10-13 13:10:00+0000', tz='UTC'))":28006.0,"('AAPL', Timestamp('2023-10-13 13:15:00+0000', tz='UTC'))":13292.0,"('AAPL', Timestamp('2023-10-13 13:20:00+0000', tz='UTC'))":32380.0,"('AAPL', Timestamp('2023-10-13 13:25:00+0000', tz='UTC'))":24252.0,"('AAPL', Timestamp('2023-10-13 13:30:00+0000', tz='UTC'))":1705390.0,"('AAPL', Timestamp('2023-10-13 13:35:00+0000', tz='UTC'))":796663.0,"('AAPL', Timestamp('2023-10-13 13:40:00+0000', tz='UTC'))":560485.0,"('AAPL', Timestamp('2023-10-13 13:45:00+0000', tz='UTC'))":580030.0,"('AAPL', Timestamp('2023-10-13 13:50:00+0000', tz='UTC'))":543739.0,"('AAPL', Timestamp('2023-10-13 13:55:00+0000', tz='UTC'))":570901.0,"('AAPL', Timestamp('2023-10-13 14:00:00+0000', tz='UTC'))":869173.0,"('AAPL', Timestamp('2023-10-13 14:05:00+0000', tz='UTC'))":535106.0,"('AAPL', Timestamp('2023-10-13 14:10:00+0000', tz='UTC'))":1773544.0,"('AAPL', Timestamp('2023-10-13 14:15:00+0000', tz='UTC'))":509511.0,"('AAPL', Timestamp('2023-10-13 14:20:00+0000', tz='UTC'))":462130.0,"('AAPL', Timestamp('2023-10-13 14:25:00+0000', tz='UTC'))":427571.0,"('AAPL', Timestamp('2023-10-13 14:30:00+0000', tz='UTC'))":427335.0,"('AAPL', Timestamp('2023-10-13 14:35:00+0000', tz='UTC'))":415495.0,"('AAPL', Timestamp('2023-10-13 14:40:00+0000', tz='UTC'))":408796.0,"('AAPL', Timestamp('2023-10-13 14:45:00+0000', tz='UTC'))":632091.0,"('AAPL', Timestamp('2023-10-13 14:50:00+0000', tz='UTC'))":774063.0,"('AAPL', Timestamp('2023-10-13 14:55:00+0000', tz='UTC'))":460812.0,"('AAPL', Timestamp('2023-10-13 15:00:00+0000', tz='UTC'))":337505.0,"('AAPL', Timestamp('2023-10-13 15:05:00+0000', tz='UTC'))":538920.0,"('AAPL', Timestamp('2023-10-13 15:10:00+0000', tz='UTC'))":431028.0,"('AAPL', Timestamp('2023-10-13 15:15:00+0000', tz='UTC'))":604075.0,"('AAPL', Timestamp('2023-10-13 15:20:00+0000', tz='UTC'))":705975.0,"('AAPL', Timestamp('2023-10-13 15:25:00+0000', tz='UTC'))":538061.0,"('AAPL', Timestamp('2023-10-13 15:30:00+0000', tz='UTC'))":509381.0,"('AAPL', Timestamp('2023-10-13 15:35:00+0000', tz='UTC'))":507633.0,"('AAPL', Timestamp('2023-10-13 15:40:00+0000', tz='UTC'))":335014.0,"('AAPL', Timestamp('2023-10-13 15:45:00+0000', tz='UTC'))":282161.0,"('AAPL', Timestamp('2023-10-13 15:50:00+0000', tz='UTC'))":668944.0,"('AAPL', Timestamp('2023-10-13 15:55:00+0000', tz='UTC'))":1044115.0,"('AAPL', Timestamp('2023-10-13 16:00:00+0000', tz='UTC'))":790933.0,"('AAPL', Timestamp('2023-10-13 16:05:00+0000', tz='UTC'))":351267.0,"('AAPL', Timestamp('2023-10-13 16:10:00+0000', tz='UTC'))":342049.0,"('AAPL', Timestamp('2023-10-13 16:15:00+0000', tz='UTC'))":398971.0,"('AAPL', Timestamp('2023-10-13 16:20:00+0000', tz='UTC'))":407843.0,"('AAPL', Timestamp('2023-10-13 16:25:00+0000', tz='UTC'))":262504.0,"('AAPL', Timestamp('2023-10-13 16:30:00+0000', tz='UTC'))":401583.0,"('AAPL', Timestamp('2023-10-13 16:35:00+0000', tz='UTC'))":323195.0,"('AAPL', Timestamp('2023-10-13 16:40:00+0000', tz='UTC'))":245097.0,"('AAPL', Timestamp('2023-10-13 16:45:00+0000', tz='UTC'))":231427.0,"('AAPL', Timestamp('2023-10-13 16:50:00+0000', tz='UTC'))":414420.0,"('AAPL', Timestamp('2023-10-13 16:55:00+0000', tz='UTC'))":274345.0,"('AAPL', Timestamp('2023-10-13 17:00:00+0000', tz='UTC'))":240835.0,"('AAPL', Timestamp('2023-10-13 17:05:00+0000', tz='UTC'))":474962.0,"('AAPL', Timestamp('2023-10-13 17:10:00+0000', tz='UTC'))":538536.0,"('AAPL', Timestamp('2023-10-13 17:15:00+0000', tz='UTC'))":349449.0,"('AAPL', Timestamp('2023-10-13 17:20:00+0000', tz='UTC'))":310471.0,"('AAPL', Timestamp('2023-10-13 17:25:00+0000', tz='UTC'))":613818.0,"('AAPL', Timestamp('2023-10-13 17:30:00+0000', tz='UTC'))":509346.0,"('AAPL', Timestamp('2023-10-13 17:35:00+0000', tz='UTC'))":446968.0,"('AAPL', Timestamp('2023-10-13 17:40:00+0000', tz='UTC'))":763591.0,"('AAPL', Timestamp('2023-10-13 17:45:00+0000', tz='UTC'))":420497.0,"('AAPL', Timestamp('2023-10-13 17:50:00+0000', tz='UTC'))":384962.0,"('AAPL', Timestamp('2023-10-13 17:55:00+0000', tz='UTC'))":278234.0,"('AAPL', Timestamp('2023-10-13 18:00:00+0000', tz='UTC'))":337660.0,"('AAPL', Timestamp('2023-10-13 18:05:00+0000', tz='UTC'))":566785.0,"('AAPL', Timestamp('2023-10-13 18:10:00+0000', tz='UTC'))":256504.0,"('AAPL', Timestamp('2023-10-13 18:15:00+0000', tz='UTC'))":479144.0,"('AAPL', Timestamp('2023-10-13 18:20:00+0000', tz='UTC'))":401941.0,"('AAPL', Timestamp('2023-10-13 18:25:00+0000', tz='UTC'))":359554.0,"('AAPL', Timestamp('2023-10-13 18:30:00+0000', tz='UTC'))":634085.0,"('AAPL', Timestamp('2023-10-13 18:35:00+0000', tz='UTC'))":454427.0,"('AAPL', Timestamp('2023-10-13 18:40:00+0000', tz='UTC'))":323733.0,"('AAPL', Timestamp('2023-10-13 18:45:00+0000', tz='UTC'))":415811.0,"('AAPL', Timestamp('2023-10-13 18:50:00+0000', tz='UTC'))":488644.0,"('AAPL', Timestamp('2023-10-13 18:55:00+0000', tz='UTC'))":405454.0,"('AAPL', Timestamp('2023-10-13 19:00:00+0000', tz='UTC'))":420757.0,"('AAPL', Timestamp('2023-10-13 19:05:00+0000', tz='UTC'))":412248.0,"('AAPL', Timestamp('2023-10-13 19:10:00+0000', tz='UTC'))":584630.0,"('AAPL', Timestamp('2023-10-13 19:15:00+0000', tz='UTC'))":525414.0,"('AAPL', Timestamp('2023-10-13 19:20:00+0000', tz='UTC'))":428655.0,"('AAPL', Timestamp('2023-10-13 19:25:00+0000', tz='UTC'))":539051.0,"('AAPL', Timestamp('2023-10-13 19:30:00+0000', tz='UTC'))":542214.0,"('AAPL', Timestamp('2023-10-13 19:35:00+0000', tz='UTC'))":528096.0,"('AAPL', Timestamp('2023-10-13 19:40:00+0000', tz='UTC'))":617470.0,"('AAPL', Timestamp('2023-10-13 19:45:00+0000', tz='UTC'))":742283.0,"('AAPL', Timestamp('2023-10-13 19:50:00+0000', tz='UTC'))":1016092.0,"('AAPL', Timestamp('2023-10-13 19:55:00+0000', tz='UTC'))":2289288.0,"('AAPL', Timestamp('2023-10-13 20:00:00+0000', tz='UTC'))":7864314.0,"('AAPL', Timestamp('2023-10-13 20:05:00+0000', tz='UTC'))":172456.0,"('AAPL', Timestamp('2023-10-13 20:10:00+0000', tz='UTC'))":86272.0,"('AAPL', Timestamp('2023-10-13 20:15:00+0000', tz='UTC'))":21139.0,"('AAPL', Timestamp('2023-10-13 20:20:00+0000', tz='UTC'))":5252.0,"('AAPL', Timestamp('2023-10-13 20:25:00+0000', tz='UTC'))":2102.0,"('AAPL', Timestamp('2023-10-13 20:30:00+0000', tz='UTC'))":5940.0,"('AAPL', Timestamp('2023-10-13 20:35:00+0000', tz='UTC'))":2508.0,"('AAPL', Timestamp('2023-10-13 20:40:00+0000', tz='UTC'))":5483.0,"('AAPL', Timestamp('2023-10-13 20:45:00+0000', tz='UTC'))":30113.0,"('AAPL', Timestamp('2023-10-13 20:50:00+0000', tz='UTC'))":200624.0,"('AAPL', Timestamp('2023-10-13 20:55:00+0000', tz='UTC'))":2633.0,"('AAPL', Timestamp('2023-10-13 21:05:00+0000', tz='UTC'))":2664.0,"('AAPL', Timestamp('2023-10-13 21:10:00+0000', tz='UTC'))":1269.0,"('AAPL', Timestamp('2023-10-13 21:15:00+0000', tz='UTC'))":72494.0,"('AAPL', Timestamp('2023-10-13 21:20:00+0000', tz='UTC'))":5503.0,"('AAPL', Timestamp('2023-10-13 21:25:00+0000', tz='UTC'))":655.0,"('AAPL', Timestamp('2023-10-13 21:30:00+0000', tz='UTC'))":3289.0,"('AAPL', Timestamp('2023-10-13 21:35:00+0000', tz='UTC'))":226.0,"('AAPL', Timestamp('2023-10-13 21:40:00+0000', tz='UTC'))":1433.0,"('AAPL', Timestamp('2023-10-13 21:45:00+0000', tz='UTC'))":2502.0,"('AAPL', Timestamp('2023-10-13 21:50:00+0000', tz='UTC'))":866.0,"('AAPL', Timestamp('2023-10-13 21:55:00+0000', tz='UTC'))":137.0,"('AAPL', Timestamp('2023-10-13 22:00:00+0000', tz='UTC'))":2237.0,"('AAPL', Timestamp('2023-10-13 22:05:00+0000', tz='UTC'))":215.0,"('AAPL', Timestamp('2023-10-13 22:10:00+0000', tz='UTC'))":2244.0,"('AAPL', Timestamp('2023-10-13 22:15:00+0000', tz='UTC'))":144.0,"('AAPL', Timestamp('2023-10-13 22:20:00+0000', tz='UTC'))":808.0,"('AAPL', Timestamp('2023-10-13 22:35:00+0000', tz='UTC'))":1355.0,"('AAPL', Timestamp('2023-10-13 22:40:00+0000', tz='UTC'))":1488.0,"('AAPL', Timestamp('2023-10-13 22:45:00+0000', tz='UTC'))":250.0,"('AAPL', Timestamp('2023-10-13 22:50:00+0000', tz='UTC'))":492.0,"('AAPL', Timestamp('2023-10-13 22:55:00+0000', tz='UTC'))":5135.0,"('AAPL', Timestamp('2023-10-13 23:00:00+0000', tz='UTC'))":398.0,"('AAPL', Timestamp('2023-10-13 23:05:00+0000', tz='UTC'))":823.0,"('AAPL', Timestamp('2023-10-13 23:10:00+0000', tz='UTC'))":361.0,"('AAPL', Timestamp('2023-10-13 23:15:00+0000', tz='UTC'))":114.0,"('AAPL', Timestamp('2023-10-13 23:20:00+0000', tz='UTC'))":805.0,"('AAPL', Timestamp('2023-10-13 23:25:00+0000', tz='UTC'))":1831.0,"('AAPL', Timestamp('2023-10-13 23:30:00+0000', tz='UTC'))":516.0,"('AAPL', Timestamp('2023-10-13 23:35:00+0000', tz='UTC'))":598.0,"('AAPL', Timestamp('2023-10-13 23:40:00+0000', tz='UTC'))":645.0,"('AAPL', Timestamp('2023-10-13 23:45:00+0000', tz='UTC'))":3481.0,"('AAPL', Timestamp('2023-10-13 23:50:00+0000', tz='UTC'))":2334.0},"trade_count":{"('AAPL', Timestamp('2023-10-13 08:00:00+0000', tz='UTC'))":21.0,"('AAPL', Timestamp('2023-10-13 08:05:00+0000', tz='UTC'))":13.0,"('AAPL', Timestamp('2023-10-13 08:10:00+0000', tz='UTC'))":15.0,"('AAPL', Timestamp('2023-10-13 08:15:00+0000', tz='UTC'))":28.0,"('AAPL', Timestamp('2023-10-13 08:25:00+0000', tz='UTC'))":53.0,"('AAPL', Timestamp('2023-10-13 08:30:00+0000', tz='UTC'))":39.0,"('AAPL', Timestamp('2023-10-13 08:40:00+0000', tz='UTC'))":89.0,"('AAPL', Timestamp('2023-10-13 08:45:00+0000', tz='UTC'))":13.0,"('AAPL', Timestamp('2023-10-13 08:50:00+0000', tz='UTC'))":23.0,"('AAPL', Timestamp('2023-10-13 08:55:00+0000', tz='UTC'))":54.0,"('AAPL', Timestamp('2023-10-13 09:00:00+0000', tz='UTC'))":62.0,"('AAPL', Timestamp('2023-10-13 09:05:00+0000', tz='UTC'))":42.0,"('AAPL', Timestamp('2023-10-13 09:10:00+0000', tz='UTC'))":3.0,"('AAPL', Timestamp('2023-10-13 09:15:00+0000', tz='UTC'))":83.0,"('AAPL', Timestamp('2023-10-13 09:20:00+0000', tz='UTC'))":7.0,"('AAPL', Timestamp('2023-10-13 09:25:00+0000', tz='UTC'))":42.0,"('AAPL', Timestamp('2023-10-13 09:30:00+0000', tz='UTC'))":37.0,"('AAPL', Timestamp('2023-10-13 09:35:00+0000', tz='UTC'))":22.0,"('AAPL', Timestamp('2023-10-13 09:40:00+0000', tz='UTC'))":80.0,"('AAPL', Timestamp('2023-10-13 09:45:00+0000', tz='UTC'))":31.0,"('AAPL', Timestamp('2023-10-13 09:50:00+0000', tz='UTC'))":70.0,"('AAPL', Timestamp('2023-10-13 09:55:00+0000', tz='UTC'))":39.0,"('AAPL', Timestamp('2023-10-13 10:00:00+0000', tz='UTC'))":46.0,"('AAPL', Timestamp('2023-10-13 10:05:00+0000', tz='UTC'))":67.0,"('AAPL', Timestamp('2023-10-13 10:10:00+0000', tz='UTC'))":19.0,"('AAPL', Timestamp('2023-10-13 10:15:00+0000', tz='UTC'))":41.0,"('AAPL', Timestamp('2023-10-13 10:20:00+0000', tz='UTC'))":41.0,"('AAPL', Timestamp('2023-10-13 10:25:00+0000', tz='UTC'))":82.0,"('AAPL', Timestamp('2023-10-13 10:30:00+0000', tz='UTC'))":65.0,"('AAPL', Timestamp('2023-10-13 10:35:00+0000', tz='UTC'))":24.0,"('AAPL', Timestamp('2023-10-13 10:40:00+0000', tz='UTC'))":7.0,"('AAPL', Timestamp('2023-10-13 10:45:00+0000', tz='UTC'))":46.0,"('AAPL', Timestamp('2023-10-13 10:50:00+0000', tz='UTC'))":92.0,"('AAPL', Timestamp('2023-10-13 10:55:00+0000', tz='UTC'))":9.0,"('AAPL', Timestamp('2023-10-13 11:00:00+0000', tz='UTC'))":141.0,"('AAPL', Timestamp('2023-10-13 11:05:00+0000', tz='UTC'))":79.0,"('AAPL', Timestamp('2023-10-13 11:10:00+0000', tz='UTC'))":38.0,"('AAPL', Timestamp('2023-10-13 11:15:00+0000', tz='UTC'))":65.0,"('AAPL', Timestamp('2023-10-13 11:20:00+0000', tz='UTC'))":36.0,"('AAPL', Timestamp('2023-10-13 11:25:00+0000', tz='UTC'))":9.0,"('AAPL', Timestamp('2023-10-13 11:30:00+0000', tz='UTC'))":27.0,"('AAPL', Timestamp('2023-10-13 11:35:00+0000', tz='UTC'))":260.0,"('AAPL', Timestamp('2023-10-13 11:40:00+0000', tz='UTC'))":177.0,"('AAPL', Timestamp('2023-10-13 11:45:00+0000', tz='UTC'))":61.0,"('AAPL', Timestamp('2023-10-13 11:50:00+0000', tz='UTC'))":82.0,"('AAPL', Timestamp('2023-10-13 11:55:00+0000', tz='UTC'))":16.0,"('AAPL', Timestamp('2023-10-13 12:00:00+0000', tz='UTC'))":1403.0,"('AAPL', Timestamp('2023-10-13 12:05:00+0000', tz='UTC'))":161.0,"('AAPL', Timestamp('2023-10-13 12:10:00+0000', tz='UTC'))":66.0,"('AAPL', Timestamp('2023-10-13 12:15:00+0000', tz='UTC'))":227.0,"('AAPL', Timestamp('2023-10-13 12:20:00+0000', tz='UTC'))":149.0,"('AAPL', Timestamp('2023-10-13 12:25:00+0000', tz='UTC'))":146.0,"('AAPL', Timestamp('2023-10-13 12:30:00+0000', tz='UTC'))":248.0,"('AAPL', Timestamp('2023-10-13 12:35:00+0000', tz='UTC'))":432.0,"('AAPL', Timestamp('2023-10-13 12:40:00+0000', tz='UTC'))":307.0,"('AAPL', Timestamp('2023-10-13 12:45:00+0000', tz='UTC'))":179.0,"('AAPL', Timestamp('2023-10-13 12:50:00+0000', tz='UTC'))":275.0,"('AAPL', Timestamp('2023-10-13 12:55:00+0000', tz='UTC'))":408.0,"('AAPL', Timestamp('2023-10-13 13:00:00+0000', tz='UTC'))":276.0,"('AAPL', Timestamp('2023-10-13 13:05:00+0000', tz='UTC'))":347.0,"('AAPL', Timestamp('2023-10-13 13:10:00+0000', tz='UTC'))":437.0,"('AAPL', Timestamp('2023-10-13 13:15:00+0000', tz='UTC'))":265.0,"('AAPL', Timestamp('2023-10-13 13:20:00+0000', tz='UTC'))":504.0,"('AAPL', Timestamp('2023-10-13 13:25:00+0000', tz='UTC'))":518.0,"('AAPL', Timestamp('2023-10-13 13:30:00+0000', tz='UTC'))":14225.0,"('AAPL', Timestamp('2023-10-13 13:35:00+0000', tz='UTC'))":8585.0,"('AAPL', Timestamp('2023-10-13 13:40:00+0000', tz='UTC'))":6076.0,"('AAPL', Timestamp('2023-10-13 13:45:00+0000', tz='UTC'))":9412.0,"('AAPL', Timestamp('2023-10-13 13:50:00+0000', tz='UTC'))":11408.0,"('AAPL', Timestamp('2023-10-13 13:55:00+0000', tz='UTC'))":11450.0,"('AAPL', Timestamp('2023-10-13 14:00:00+0000', tz='UTC'))":16635.0,"('AAPL', Timestamp('2023-10-13 14:05:00+0000', tz='UTC'))":12384.0,"('AAPL', Timestamp('2023-10-13 14:10:00+0000', tz='UTC'))":11231.0,"('AAPL', Timestamp('2023-10-13 14:15:00+0000', tz='UTC'))":10390.0,"('AAPL', Timestamp('2023-10-13 14:20:00+0000', tz='UTC'))":10373.0,"('AAPL', Timestamp('2023-10-13 14:25:00+0000', tz='UTC'))":9537.0,"('AAPL', Timestamp('2023-10-13 14:30:00+0000', tz='UTC'))":8827.0,"('AAPL', Timestamp('2023-10-13 14:35:00+0000', tz='UTC'))":8337.0,"('AAPL', Timestamp('2023-10-13 14:40:00+0000', tz='UTC'))":8357.0,"('AAPL', Timestamp('2023-10-13 14:45:00+0000', tz='UTC'))":10752.0,"('AAPL', Timestamp('2023-10-13 14:50:00+0000', tz='UTC'))":11693.0,"('AAPL', Timestamp('2023-10-13 14:55:00+0000', tz='UTC'))":10575.0,"('AAPL', Timestamp('2023-10-13 15:00:00+0000', tz='UTC'))":9834.0,"('AAPL', Timestamp('2023-10-13 15:05:00+0000', tz='UTC'))":9484.0,"('AAPL', Timestamp('2023-10-13 15:10:00+0000', tz='UTC'))":9597.0,"('AAPL', Timestamp('2023-10-13 15:15:00+0000', tz='UTC'))":12069.0,"('AAPL', Timestamp('2023-10-13 15:20:00+0000', tz='UTC'))":13247.0,"('AAPL', Timestamp('2023-10-13 15:25:00+0000', tz='UTC'))":10883.0,"('AAPL', Timestamp('2023-10-13 15:30:00+0000', tz='UTC'))":9286.0,"('AAPL', Timestamp('2023-10-13 15:35:00+0000', tz='UTC'))":4973.0,"('AAPL', Timestamp('2023-10-13 15:40:00+0000', tz='UTC'))":4214.0,"('AAPL', Timestamp('2023-10-13 15:45:00+0000', tz='UTC'))":3628.0,"('AAPL', Timestamp('2023-10-13 15:50:00+0000', tz='UTC'))":6120.0,"('AAPL', Timestamp('2023-10-13 15:55:00+0000', tz='UTC'))":5017.0,"('AAPL', Timestamp('2023-10-13 16:00:00+0000', tz='UTC'))":4782.0,"('AAPL', Timestamp('2023-10-13 16:05:00+0000', tz='UTC'))":3701.0,"('AAPL', Timestamp('2023-10-13 16:10:00+0000', tz='UTC'))":4130.0,"('AAPL', Timestamp('2023-10-13 16:15:00+0000', tz='UTC'))":4118.0,"('AAPL', Timestamp('2023-10-13 16:20:00+0000', tz='UTC'))":3760.0,"('AAPL', Timestamp('2023-10-13 16:25:00+0000', tz='UTC'))":3187.0,"('AAPL', Timestamp('2023-10-13 16:30:00+0000', tz='UTC'))":3728.0,"('AAPL', Timestamp('2023-10-13 16:35:00+0000', tz='UTC'))":3248.0,"('AAPL', Timestamp('2023-10-13 16:40:00+0000', tz='UTC'))":2599.0,"('AAPL', Timestamp('2023-10-13 16:45:00+0000', tz='UTC'))":2635.0,"('AAPL', Timestamp('2023-10-13 16:50:00+0000', tz='UTC'))":4043.0,"('AAPL', Timestamp('2023-10-13 16:55:00+0000', tz='UTC'))":2678.0,"('AAPL', Timestamp('2023-10-13 17:00:00+0000', tz='UTC'))":2910.0,"('AAPL', Timestamp('2023-10-13 17:05:00+0000', tz='UTC'))":4753.0,"('AAPL', Timestamp('2023-10-13 17:10:00+0000', tz='UTC'))":4827.0,"('AAPL', Timestamp('2023-10-13 17:15:00+0000', tz='UTC'))":3384.0,"('AAPL', Timestamp('2023-10-13 17:20:00+0000', tz='UTC'))":3568.0,"('AAPL', Timestamp('2023-10-13 17:25:00+0000', tz='UTC'))":6060.0,"('AAPL', Timestamp('2023-10-13 17:30:00+0000', tz='UTC'))":5385.0,"('AAPL', Timestamp('2023-10-13 17:35:00+0000', tz='UTC'))":4627.0,"('AAPL', Timestamp('2023-10-13 17:40:00+0000', tz='UTC'))":6309.0,"('AAPL', Timestamp('2023-10-13 17:45:00+0000', tz='UTC'))":4161.0,"('AAPL', Timestamp('2023-10-13 17:50:00+0000', tz='UTC'))":3534.0,"('AAPL', Timestamp('2023-10-13 17:55:00+0000', tz='UTC'))":3337.0,"('AAPL', Timestamp('2023-10-13 18:00:00+0000', tz='UTC'))":3825.0,"('AAPL', Timestamp('2023-10-13 18:05:00+0000', tz='UTC'))":4613.0,"('AAPL', Timestamp('2023-10-13 18:10:00+0000', tz='UTC'))":2982.0,"('AAPL', Timestamp('2023-10-13 18:15:00+0000', tz='UTC'))":4493.0,"('AAPL', Timestamp('2023-10-13 18:20:00+0000', tz='UTC'))":4050.0,"('AAPL', Timestamp('2023-10-13 18:25:00+0000', tz='UTC'))":3769.0,"('AAPL', Timestamp('2023-10-13 18:30:00+0000', tz='UTC'))":6892.0,"('AAPL', Timestamp('2023-10-13 18:35:00+0000', tz='UTC'))":4658.0,"('AAPL', Timestamp('2023-10-13 18:40:00+0000', tz='UTC'))":3517.0,"('AAPL', Timestamp('2023-10-13 18:45:00+0000', tz='UTC'))":4093.0,"('AAPL', Timestamp('2023-10-13 18:50:00+0000', tz='UTC'))":4156.0,"('AAPL', Timestamp('2023-10-13 18:55:00+0000', tz='UTC'))":3756.0,"('AAPL', Timestamp('2023-10-13 19:00:00+0000', tz='UTC'))":4224.0,"('AAPL', Timestamp('2023-10-13 19:05:00+0000', tz='UTC'))":4099.0,"('AAPL', Timestamp('2023-10-13 19:10:00+0000', tz='UTC'))":5400.0,"('AAPL', Timestamp('2023-10-13 19:15:00+0000', tz='UTC'))":5158.0,"('AAPL', Timestamp('2023-10-13 19:20:00+0000', tz='UTC'))":4298.0,"('AAPL', Timestamp('2023-10-13 19:25:00+0000', tz='UTC'))":4853.0,"('AAPL', Timestamp('2023-10-13 19:30:00+0000', tz='UTC'))":5512.0,"('AAPL', Timestamp('2023-10-13 19:35:00+0000', tz='UTC'))":5457.0,"('AAPL', Timestamp('2023-10-13 19:40:00+0000', tz='UTC'))":7043.0,"('AAPL', Timestamp('2023-10-13 19:45:00+0000', tz='UTC'))":7832.0,"('AAPL', Timestamp('2023-10-13 19:50:00+0000', tz='UTC'))":12006.0,"('AAPL', Timestamp('2023-10-13 19:55:00+0000', tz='UTC'))":17201.0,"('AAPL', Timestamp('2023-10-13 20:00:00+0000', tz='UTC'))":369.0,"('AAPL', Timestamp('2023-10-13 20:05:00+0000', tz='UTC'))":212.0,"('AAPL', Timestamp('2023-10-13 20:10:00+0000', tz='UTC'))":119.0,"('AAPL', Timestamp('2023-10-13 20:15:00+0000', tz='UTC'))":101.0,"('AAPL', Timestamp('2023-10-13 20:20:00+0000', tz='UTC'))":103.0,"('AAPL', Timestamp('2023-10-13 20:25:00+0000', tz='UTC'))":47.0,"('AAPL', Timestamp('2023-10-13 20:30:00+0000', tz='UTC'))":94.0,"('AAPL', Timestamp('2023-10-13 20:35:00+0000', tz='UTC'))":53.0,"('AAPL', Timestamp('2023-10-13 20:40:00+0000', tz='UTC'))":77.0,"('AAPL', Timestamp('2023-10-13 20:45:00+0000', tz='UTC'))":9.0,"('AAPL', Timestamp('2023-10-13 20:50:00+0000', tz='UTC'))":97.0,"('AAPL', Timestamp('2023-10-13 20:55:00+0000', tz='UTC'))":60.0,"('AAPL', Timestamp('2023-10-13 21:05:00+0000', tz='UTC'))":55.0,"('AAPL', Timestamp('2023-10-13 21:10:00+0000', tz='UTC'))":52.0,"('AAPL', Timestamp('2023-10-13 21:15:00+0000', tz='UTC'))":59.0,"('AAPL', Timestamp('2023-10-13 21:20:00+0000', tz='UTC'))":17.0,"('AAPL', Timestamp('2023-10-13 21:25:00+0000', tz='UTC'))":19.0,"('AAPL', Timestamp('2023-10-13 21:30:00+0000', tz='UTC'))":66.0,"('AAPL', Timestamp('2023-10-13 21:35:00+0000', tz='UTC'))":8.0,"('AAPL', Timestamp('2023-10-13 21:40:00+0000', tz='UTC'))":12.0,"('AAPL', Timestamp('2023-10-13 21:45:00+0000', tz='UTC'))":73.0,"('AAPL', Timestamp('2023-10-13 21:50:00+0000', tz='UTC'))":35.0,"('AAPL', Timestamp('2023-10-13 21:55:00+0000', tz='UTC'))":13.0,"('AAPL', Timestamp('2023-10-13 22:00:00+0000', tz='UTC'))":36.0,"('AAPL', Timestamp('2023-10-13 22:05:00+0000', tz='UTC'))":11.0,"('AAPL', Timestamp('2023-10-13 22:10:00+0000', tz='UTC'))":45.0,"('AAPL', Timestamp('2023-10-13 22:15:00+0000', tz='UTC'))":12.0,"('AAPL', Timestamp('2023-10-13 22:20:00+0000', tz='UTC'))":23.0,"('AAPL', Timestamp('2023-10-13 22:35:00+0000', tz='UTC'))":50.0,"('AAPL', Timestamp('2023-10-13 22:40:00+0000', tz='UTC'))":41.0,"('AAPL', Timestamp('2023-10-13 22:45:00+0000', tz='UTC'))":11.0,"('AAPL', Timestamp('2023-10-13 22:50:00+0000', tz='UTC'))":20.0,"('AAPL', Timestamp('2023-10-13 22:55:00+0000', tz='UTC'))":9.0,"('AAPL', Timestamp('2023-10-13 23:00:00+0000', tz='UTC'))":15.0,"('AAPL', Timestamp('2023-10-13 23:05:00+0000', tz='UTC'))":15.0,"('AAPL', Timestamp('2023-10-13 23:10:00+0000', tz='UTC'))":17.0,"('AAPL', Timestamp('2023-10-13 23:15:00+0000', tz='UTC'))":10.0,"('AAPL', Timestamp('2023-10-13 23:20:00+0000', tz='UTC'))":23.0,"('AAPL', Timestamp('2023-10-13 23:25:00+0000', tz='UTC'))":19.0,"('AAPL', Timestamp('2023-10-13 23:30:00+0000', tz='UTC'))":16.0,"('AAPL', Timestamp('2023-10-13 23:35:00+0000', tz='UTC'))":25.0,"('AAPL', Timestamp('2023-10-13 23:40:00+0000', tz='UTC'))":29.0,"('AAPL', Timestamp('2023-10-13 23:45:00+0000', tz='UTC'))":74.0,"('AAPL', Timestamp('2023-10-13 23:50:00+0000', tz='UTC'))":39.0},"vwap":{"('AAPL', Timestamp('2023-10-13 08:00:00+0000', tz='UTC'))":181.026301,"('AAPL', Timestamp('2023-10-13 08:05:00+0000', tz='UTC'))":181.098758,"('AAPL', Timestamp('2023-10-13 08:10:00+0000', tz='UTC'))":181.09716,"('AAPL', Timestamp('2023-10-13 08:15:00+0000', tz='UTC'))":181.064876,"('AAPL', Timestamp('2023-10-13 08:25:00+0000', tz='UTC'))":181.010531,"('AAPL', Timestamp('2023-10-13 08:30:00+0000', tz='UTC'))":180.929702,"('AAPL', Timestamp('2023-10-13 08:40:00+0000', tz='UTC'))":180.717881,"('AAPL', Timestamp('2023-10-13 08:45:00+0000', tz='UTC'))":180.750281,"('AAPL', Timestamp('2023-10-13 08:50:00+0000', tz='UTC'))":180.74463,"('AAPL', Timestamp('2023-10-13 08:55:00+0000', tz='UTC'))":180.806905,"('AAPL', Timestamp('2023-10-13 09:00:00+0000', tz='UTC'))":180.704686,"('AAPL', Timestamp('2023-10-13 09:05:00+0000', tz='UTC'))":180.587464,"('AAPL', Timestamp('2023-10-13 09:10:00+0000', tz='UTC'))":180.646617,"('AAPL', Timestamp('2023-10-13 09:15:00+0000', tz='UTC'))":180.591203,"('AAPL', Timestamp('2023-10-13 09:20:00+0000', tz='UTC'))":180.605235,"('AAPL', Timestamp('2023-10-13 09:25:00+0000', tz='UTC'))":180.670622,"('AAPL', Timestamp('2023-10-13 09:30:00+0000', tz='UTC'))":180.671052,"('AAPL', Timestamp('2023-10-13 09:35:00+0000', tz='UTC'))":180.628627,"('AAPL', Timestamp('2023-10-13 09:40:00+0000', tz='UTC'))":180.574784,"('AAPL', Timestamp('2023-10-13 09:45:00+0000', tz='UTC'))":180.512458,"('AAPL', Timestamp('2023-10-13 09:50:00+0000', tz='UTC'))":180.404894,"('AAPL', Timestamp('2023-10-13 09:55:00+0000', tz='UTC'))":180.250217,"('AAPL', Timestamp('2023-10-13 10:00:00+0000', tz='UTC'))":180.27787,"('AAPL', Timestamp('2023-10-13 10:05:00+0000', tz='UTC'))":180.233341,"('AAPL', Timestamp('2023-10-13 10:10:00+0000', tz='UTC'))":180.105494,"('AAPL', Timestamp('2023-10-13 10:15:00+0000', tz='UTC'))":180.1292,"('AAPL', Timestamp('2023-10-13 10:20:00+0000', tz='UTC'))":180.103296,"('AAPL', Timestamp('2023-10-13 10:25:00+0000', tz='UTC'))":180.098143,"('AAPL', Timestamp('2023-10-13 10:30:00+0000', tz='UTC'))":180.101557,"('AAPL', Timestamp('2023-10-13 10:35:00+0000', tz='UTC'))":180.095515,"('AAPL', Timestamp('2023-10-13 10:40:00+0000', tz='UTC'))":180.092596,"('AAPL', Timestamp('2023-10-13 10:45:00+0000', tz='UTC'))":180.200199,"('AAPL', Timestamp('2023-10-13 10:50:00+0000', tz='UTC'))":180.306277,"('AAPL', Timestamp('2023-10-13 10:55:00+0000', tz='UTC'))":180.250912,"('AAPL', Timestamp('2023-10-13 11:00:00+0000', tz='UTC'))":180.276583,"('AAPL', Timestamp('2023-10-13 11:05:00+0000', tz='UTC'))":180.396911,"('AAPL', Timestamp('2023-10-13 11:10:00+0000', tz='UTC'))":180.43095,"('AAPL', Timestamp('2023-10-13 11:15:00+0000', tz='UTC'))":180.358671,"('AAPL', Timestamp('2023-10-13 11:20:00+0000', tz='UTC'))":180.256724,"('AAPL', Timestamp('2023-10-13 11:25:00+0000', tz='UTC'))":180.292404,"('AAPL', Timestamp('2023-10-13 11:30:00+0000', tz='UTC'))":180.325476,"('AAPL', Timestamp('2023-10-13 11:35:00+0000', tz='UTC'))":180.300025,"('AAPL', Timestamp('2023-10-13 11:40:00+0000', tz='UTC'))":180.233715,"('AAPL', Timestamp('2023-10-13 11:45:00+0000', tz='UTC'))":180.155202,"('AAPL', Timestamp('2023-10-13 11:50:00+0000', tz='UTC'))":180.242873,"('AAPL', Timestamp('2023-10-13 11:55:00+0000', tz='UTC'))":180.251054,"('AAPL', Timestamp('2023-10-13 12:00:00+0000', tz='UTC'))":180.489714,"('AAPL', Timestamp('2023-10-13 12:05:00+0000', tz='UTC'))":180.179796,"('AAPL', Timestamp('2023-10-13 12:10:00+0000', tz='UTC'))":180.173219,"('AAPL', Timestamp('2023-10-13 12:15:00+0000', tz='UTC'))":180.14977,"('AAPL', Timestamp('2023-10-13 12:20:00+0000', tz='UTC'))":180.201404,"('AAPL', Timestamp('2023-10-13 12:25:00+0000', tz='UTC'))":180.365343,"('AAPL', Timestamp('2023-10-13 12:30:00+0000', tz='UTC'))":180.434723,"('AAPL', Timestamp('2023-10-13 12:35:00+0000', tz='UTC'))":180.741299,"('AAPL', Timestamp('2023-10-13 12:40:00+0000', tz='UTC'))":180.84307,"('AAPL', Timestamp('2023-10-13 12:45:00+0000', tz='UTC'))":180.775146,"('AAPL', Timestamp('2023-10-13 12:50:00+0000', tz='UTC'))":180.891035,"('AAPL', Timestamp('2023-10-13 12:55:00+0000', tz='UTC'))":181.005756,"('AAPL', Timestamp('2023-10-13 13:00:00+0000', tz='UTC'))":181.031864,"('AAPL', Timestamp('2023-10-13 13:05:00+0000', tz='UTC'))":181.089996,"('AAPL', Timestamp('2023-10-13 13:10:00+0000', tz='UTC'))":181.205731,"('AAPL', Timestamp('2023-10-13 13:15:00+0000', tz='UTC'))":181.205837,"('AAPL', Timestamp('2023-10-13 13:20:00+0000', tz='UTC'))":181.1725,"('AAPL', Timestamp('2023-10-13 13:25:00+0000', tz='UTC'))":181.248243,"('AAPL', Timestamp('2023-10-13 13:30:00+0000', tz='UTC'))":181.531083,"('AAPL', Timestamp('2023-10-13 13:35:00+0000', tz='UTC'))":181.165002,"('AAPL', Timestamp('2023-10-13 13:40:00+0000', tz='UTC'))":181.221408,"('AAPL', Timestamp('2023-10-13 13:45:00+0000', tz='UTC'))":181.192657,"('AAPL', Timestamp('2023-10-13 13:50:00+0000', tz='UTC'))":181.249072,"('AAPL', Timestamp('2023-10-13 13:55:00+0000', tz='UTC'))":181.240483,"('AAPL', Timestamp('2023-10-13 14:00:00+0000', tz='UTC'))":180.951073,"('AAPL', Timestamp('2023-10-13 14:05:00+0000', tz='UTC'))":180.927989,"('AAPL', Timestamp('2023-10-13 14:10:00+0000', tz='UTC'))":180.822146,"('AAPL', Timestamp('2023-10-13 14:15:00+0000', tz='UTC'))":180.606711,"('AAPL', Timestamp('2023-10-13 14:20:00+0000', tz='UTC'))":180.602904,"('AAPL', Timestamp('2023-10-13 14:25:00+0000', tz='UTC'))":180.523961,"('AAPL', Timestamp('2023-10-13 14:30:00+0000', tz='UTC'))":180.535447,"('AAPL', Timestamp('2023-10-13 14:35:00+0000', tz='UTC'))":180.574705,"('AAPL', Timestamp('2023-10-13 14:40:00+0000', tz='UTC'))":180.317686,"('AAPL', Timestamp('2023-10-13 14:45:00+0000', tz='UTC'))":180.122667,"('AAPL', Timestamp('2023-10-13 14:50:00+0000', tz='UTC'))":179.66187,"('AAPL', Timestamp('2023-10-13 14:55:00+0000', tz='UTC'))":179.622483,"('AAPL', Timestamp('2023-10-13 15:00:00+0000', tz='UTC'))":179.608638,"('AAPL', Timestamp('2023-10-13 15:05:00+0000', tz='UTC'))":179.416179,"('AAPL', Timestamp('2023-10-13 15:10:00+0000', tz='UTC'))":179.531261,"('AAPL', Timestamp('2023-10-13 15:15:00+0000', tz='UTC'))":179.318411,"('AAPL', Timestamp('2023-10-13 15:20:00+0000', tz='UTC'))":179.182192,"('AAPL', Timestamp('2023-10-13 15:25:00+0000', tz='UTC'))":179.085371,"('AAPL', Timestamp('2023-10-13 15:30:00+0000', tz='UTC'))":179.150194,"('AAPL', Timestamp('2023-10-13 15:35:00+0000', tz='UTC'))":179.142429,"('AAPL', Timestamp('2023-10-13 15:40:00+0000', tz='UTC'))":179.236838,"('AAPL', Timestamp('2023-10-13 15:45:00+0000', tz='UTC'))":179.055651,"('AAPL', Timestamp('2023-10-13 15:50:00+0000', tz='UTC'))":178.741422,"('AAPL', Timestamp('2023-10-13 15:55:00+0000', tz='UTC'))":178.561314,"('AAPL', Timestamp('2023-10-13 16:00:00+0000', tz='UTC'))":178.689579,"('AAPL', Timestamp('2023-10-13 16:05:00+0000', tz='UTC'))":178.832206,"('AAPL', Timestamp('2023-10-13 16:10:00+0000', tz='UTC'))":178.919148,"('AAPL', Timestamp('2023-10-13 16:15:00+0000', tz='UTC'))":178.950487,"('AAPL', Timestamp('2023-10-13 16:20:00+0000', tz='UTC'))":179.167911,"('AAPL', Timestamp('2023-10-13 16:25:00+0000', tz='UTC'))":179.200647,"('AAPL', Timestamp('2023-10-13 16:30:00+0000', tz='UTC'))":179.342249,"('AAPL', Timestamp('2023-10-13 16:35:00+0000', tz='UTC'))":179.275229,"('AAPL', Timestamp('2023-10-13 16:40:00+0000', tz='UTC'))":179.32235,"('AAPL', Timestamp('2023-10-13 16:45:00+0000', tz='UTC'))":179.263771,"('AAPL', Timestamp('2023-10-13 16:50:00+0000', tz='UTC'))":179.011389,"('AAPL', Timestamp('2023-10-13 16:55:00+0000', tz='UTC'))":179.083006,"('AAPL', Timestamp('2023-10-13 17:00:00+0000', tz='UTC'))":179.03424,"('AAPL', Timestamp('2023-10-13 17:05:00+0000', tz='UTC'))":178.780252,"('AAPL', Timestamp('2023-10-13 17:10:00+0000', tz='UTC'))":178.717591,"('AAPL', Timestamp('2023-10-13 17:15:00+0000', tz='UTC'))":178.58699,"('AAPL', Timestamp('2023-10-13 17:20:00+0000', tz='UTC'))":178.628724,"('AAPL', Timestamp('2023-10-13 17:25:00+0000', tz='UTC'))":178.3539,"('AAPL', Timestamp('2023-10-13 17:30:00+0000', tz='UTC'))":178.246444,"('AAPL', Timestamp('2023-10-13 17:35:00+0000', tz='UTC'))":178.228118,"('AAPL', Timestamp('2023-10-13 17:40:00+0000', tz='UTC'))":178.706353,"('AAPL', Timestamp('2023-10-13 17:45:00+0000', tz='UTC'))":178.821522,"('AAPL', Timestamp('2023-10-13 17:50:00+0000', tz='UTC'))":178.797187,"('AAPL', Timestamp('2023-10-13 17:55:00+0000', tz='UTC'))":178.851286,"('AAPL', Timestamp('2023-10-13 18:00:00+0000', tz='UTC'))":178.830918,"('AAPL', Timestamp('2023-10-13 18:05:00+0000', tz='UTC'))":178.935996,"('AAPL', Timestamp('2023-10-13 18:10:00+0000', tz='UTC'))":178.924533,"('AAPL', Timestamp('2023-10-13 18:15:00+0000', tz='UTC'))":179.017199,"('AAPL', Timestamp('2023-10-13 18:20:00+0000', tz='UTC'))":179.192609,"('AAPL', Timestamp('2023-10-13 18:25:00+0000', tz='UTC'))":179.132773,"('AAPL', Timestamp('2023-10-13 18:30:00+0000', tz='UTC'))":179.405281,"('AAPL', Timestamp('2023-10-13 18:35:00+0000', tz='UTC'))":179.2502,"('AAPL', Timestamp('2023-10-13 18:40:00+0000', tz='UTC'))":179.207294,"('AAPL', Timestamp('2023-10-13 18:45:00+0000', tz='UTC'))":179.062688,"('AAPL', Timestamp('2023-10-13 18:50:00+0000', tz='UTC'))":179.172658,"('AAPL', Timestamp('2023-10-13 18:55:00+0000', tz='UTC'))":179.290991,"('AAPL', Timestamp('2023-10-13 19:00:00+0000', tz='UTC'))":179.391868,"('AAPL', Timestamp('2023-10-13 19:05:00+0000', tz='UTC'))":179.315758,"('AAPL', Timestamp('2023-10-13 19:10:00+0000', tz='UTC'))":179.51775,"('AAPL', Timestamp('2023-10-13 19:15:00+0000', tz='UTC'))":179.286082,"('AAPL', Timestamp('2023-10-13 19:20:00+0000', tz='UTC'))":179.095685,"('AAPL', Timestamp('2023-10-13 19:25:00+0000', tz='UTC'))":179.001731,"('AAPL', Timestamp('2023-10-13 19:30:00+0000', tz='UTC'))":178.982064,"('AAPL', Timestamp('2023-10-13 19:35:00+0000', tz='UTC'))":178.942374,"('AAPL', Timestamp('2023-10-13 19:40:00+0000', tz='UTC'))":178.726148,"('AAPL', Timestamp('2023-10-13 19:45:00+0000', tz='UTC'))":178.737459,"('AAPL', Timestamp('2023-10-13 19:50:00+0000', tz='UTC'))":178.94173,"('AAPL', Timestamp('2023-10-13 19:55:00+0000', tz='UTC'))":178.823611,"('AAPL', Timestamp('2023-10-13 20:00:00+0000', tz='UTC'))":178.849995,"('AAPL', Timestamp('2023-10-13 20:05:00+0000', tz='UTC'))":178.843811,"('AAPL', Timestamp('2023-10-13 20:10:00+0000', tz='UTC'))":178.84261,"('AAPL', Timestamp('2023-10-13 20:15:00+0000', tz='UTC'))":178.820369,"('AAPL', Timestamp('2023-10-13 20:20:00+0000', tz='UTC'))":178.672405,"('AAPL', Timestamp('2023-10-13 20:25:00+0000', tz='UTC'))":178.639282,"('AAPL', Timestamp('2023-10-13 20:30:00+0000', tz='UTC'))":178.661533,"('AAPL', Timestamp('2023-10-13 20:35:00+0000', tz='UTC'))":178.616187,"('AAPL', Timestamp('2023-10-13 20:40:00+0000', tz='UTC'))":178.586398,"('AAPL', Timestamp('2023-10-13 20:45:00+0000', tz='UTC'))":178.792139,"('AAPL', Timestamp('2023-10-13 20:50:00+0000', tz='UTC'))":178.843273,"('AAPL', Timestamp('2023-10-13 20:55:00+0000', tz='UTC'))":178.652636,"('AAPL', Timestamp('2023-10-13 21:05:00+0000', tz='UTC'))":178.653941,"('AAPL', Timestamp('2023-10-13 21:10:00+0000', tz='UTC'))":178.656602,"('AAPL', Timestamp('2023-10-13 21:15:00+0000', tz='UTC'))":178.846234,"('AAPL', Timestamp('2023-10-13 21:20:00+0000', tz='UTC'))":178.60269,"('AAPL', Timestamp('2023-10-13 21:25:00+0000', tz='UTC'))":178.627662,"('AAPL', Timestamp('2023-10-13 21:30:00+0000', tz='UTC'))":178.601276,"('AAPL', Timestamp('2023-10-13 21:35:00+0000', tz='UTC'))":178.543274,"('AAPL', Timestamp('2023-10-13 21:40:00+0000', tz='UTC'))":178.623193,"('AAPL', Timestamp('2023-10-13 21:45:00+0000', tz='UTC'))":178.630964,"('AAPL', Timestamp('2023-10-13 21:50:00+0000', tz='UTC'))":178.910803,"('AAPL', Timestamp('2023-10-13 21:55:00+0000', tz='UTC'))":178.586095,"('AAPL', Timestamp('2023-10-13 22:00:00+0000', tz='UTC'))":178.628652,"('AAPL', Timestamp('2023-10-13 22:05:00+0000', tz='UTC'))":178.599233,"('AAPL', Timestamp('2023-10-13 22:10:00+0000', tz='UTC'))":178.566403,"('AAPL', Timestamp('2023-10-13 22:15:00+0000', tz='UTC'))":178.587083,"('AAPL', Timestamp('2023-10-13 22:20:00+0000', tz='UTC'))":178.581776,"('AAPL', Timestamp('2023-10-13 22:35:00+0000', tz='UTC'))":178.589505,"('AAPL', Timestamp('2023-10-13 22:40:00+0000', tz='UTC'))":178.590599,"('AAPL', Timestamp('2023-10-13 22:45:00+0000', tz='UTC'))":178.63336,"('AAPL', Timestamp('2023-10-13 22:50:00+0000', tz='UTC'))":178.604045,"('AAPL', Timestamp('2023-10-13 22:55:00+0000', tz='UTC'))":178.638648,"('AAPL', Timestamp('2023-10-13 23:00:00+0000', tz='UTC'))":178.612663,"('AAPL', Timestamp('2023-10-13 23:05:00+0000', tz='UTC'))":178.616811,"('AAPL', Timestamp('2023-10-13 23:10:00+0000', tz='UTC'))":178.598643,"('AAPL', Timestamp('2023-10-13 23:15:00+0000', tz='UTC'))":178.596667,"('AAPL', Timestamp('2023-10-13 23:20:00+0000', tz='UTC'))":178.539068,"('AAPL', Timestamp('2023-10-13 23:25:00+0000', tz='UTC'))":178.524413,"('AAPL', Timestamp('2023-10-13 23:30:00+0000', tz='UTC'))":178.533663,"('AAPL', Timestamp('2023-10-13 23:35:00+0000', tz='UTC'))":178.527099,"('AAPL', Timestamp('2023-10-13 23:40:00+0000', tz='UTC'))":178.518837,"('AAPL', Timestamp('2023-10-13 23:45:00+0000', tz='UTC'))":178.503236,"('AAPL', Timestamp('2023-10-13 23:50:00+0000', tz='UTC'))":178.498621}}