{"open":{"('AAPL', Timestamp('2023-10-30 08:00:00+0000', tz='UTC'))":168.98,"('AAPL', Timestamp('2023-10-30 08:05:00+0000', tz='UTC'))":168.92,"('AAPL', Timestamp('2023-10-30 08:10:00+0000', tz='UTC'))":168.97,"('AAPL', Timestamp('2023-10-30 08:15:00+0000', tz='UTC'))":168.99,"('AAPL', Timestamp('2023-10-30 08:20:00+0000', tz='UTC'))":169.0,"('AAPL', Timestamp('2023-10-30 08:25:00+0000', tz='UTC'))":168.91,"('AAPL', Timestamp('2023-10-30 08:35:00+0000', tz='UTC'))":168.85,"('AAPL', Timestamp('2023-10-30 08:40:00+0000', tz='UTC'))":168.85,"('AAPL', Timestamp('2023-10-30 08:45:00+0000', tz='UTC'))":168.86,"('AAPL', Timestamp('2023-10-30 08:50:00+0000', tz='UTC'))":168.8,"('AAPL', Timestamp('2023-10-30 09:00:00+0000', tz='UTC'))":168.97,"('AAPL', Timestamp('2023-10-30 09:05:00+0000', tz='UTC'))":169.1,"('AAPL', Timestamp('2023-10-30 09:10:00+0000', tz='UTC'))":169.2,"('AAPL', Timestamp('2023-10-30 09:15:00+0000', tz='UTC'))":169.43,"('AAPL', Timestamp('2023-10-30 09:20:00+0000', tz='UTC'))":169.37,"('AAPL', Timestamp('2023-10-30 09:25:00+0000', tz='UTC'))":169.22,"('AAPL', Timestamp('2023-10-30 09:30:00+0000', tz='UTC'))":169.25,"('AAPL', Timestamp('2023-10-30 09:35:00+0000', tz='UTC'))":169.16,"('AAPL', Timestamp('2023-10-30 09:40:00+0000', tz='UTC'))":169.1,"('AAPL', Timestamp('2023-10-30 09:45:00+0000', tz='UTC'))":169.11,"('AAPL', Timestamp('2023-10-30 09:50:00+0000', tz='UTC'))":169.14,"('AAPL', Timestamp('2023-10-30 09:55:00+0000', tz='UTC'))":169.16,"('AAPL', Timestamp('2023-10-30 10:05:00+0000', tz='UTC'))":169.17,"('AAPL', Timestamp('2023-10-30 10:10:00+0000', tz='UTC'))":169.12,"('AAPL', Timestamp('2023-10-30 10:15:00+0000', tz='UTC'))":169.12,"('AAPL', Timestamp('2023-10-30 10:20:00+0000', tz='UTC'))":169.0,"('AAPL', Timestamp('2023-10-30 10:25:00+0000', tz='UTC'))":169.0,"('AAPL', Timestamp('2023-10-30 10:30:00+0000', tz='UTC'))":169.05,"('AAPL', Timestamp('2023-10-30 10:35:00+0000', tz='UTC'))":169.04,"('AAPL', Timestamp('2023-10-30 10:45:00+0000', tz='UTC'))":169.09,"('AAPL', Timestamp('2023-10-30 10:50:00+0000', tz='UTC'))":169.0,"('AAPL', Timestamp('2023-10-30 10:55:00+0000', tz='UTC'))":169.22,"('AAPL', Timestamp('2023-10-30 11:00:00+0000', tz='UTC'))":169.14,"('AAPL', Timestamp('2023-10-30 11:05:00+0000', tz='UTC'))":169.27,"('AAPL', Timestamp('2023-10-30 11:10:00+0000', tz='UTC'))":169.14,"('AAPL', Timestamp('2023-10-30 11:15:00+0000', tz='UTC'))":169.2,"('AAPL', Timestamp('2023-10-30 11:20:00+0000', tz='UTC'))":169.21,"('AAPL', Timestamp('2023-10-30 11:25:00+0000', tz='UTC'))":169.16,"('AAPL', Timestamp('2023-10-30 11:30:00+0000', tz='UTC'))":169.13,"('AAPL', Timestamp('2023-10-30 11:35:00+0000', tz='UTC'))":169.21,"('AAPL', Timestamp('2023-10-30 11:40:00+0000', tz='UTC'))":169.2,"('AAPL', Timestamp('2023-10-30 11:45:00+0000', tz='UTC'))":169.24,"('AAPL', Timestamp('2023-10-30 11:50:00+0000', tz='UTC'))":169.25,"('AAPL', Timestamp('2023-10-30 11:55:00+0000', tz='UTC'))":169.13,"('AAPL', Timestamp('2023-10-30 12:00:00+0000', tz='UTC'))":169.16,"('AAPL', Timestamp('2023-10-30 12:05:00+0000', tz='UTC'))":169.0,"('AAPL', Timestamp('2023-10-30 12:10:00+0000', tz='UTC'))":168.92,"('AAPL', Timestamp('2023-10-30 12:15:00+0000', tz='UTC'))":168.93,"('AAPL', Timestamp('2023-10-30 12:20:00+0000', tz='UTC'))":168.7799,"('AAPL', Timestamp('2023-10-30 12:25:00+0000', tz='UTC'))":168.6994,"('AAPL', Timestamp('2023-10-30 12:30:00+0000', tz='UTC'))":168.75,"('AAPL', Timestamp('2023-10-30 12:35:00+0000', tz='UTC'))":168.87,"('AAPL', Timestamp('2023-10-30 12:40:00+0000', tz='UTC'))":168.61,"('AAPL', Timestamp('2023-10-30 12:45:00+0000', tz='UTC'))":168.85,"('AAPL', Timestamp('2023-10-30 12:50:00+0000', tz='UTC'))":168.39,"('AAPL', Timestamp('2023-10-30 12:55:00+0000', tz='UTC'))":168.44,"('AAPL', Timestamp('2023-10-30 13:00:00+0000', tz='UTC'))":168.56,"('AAPL', Timestamp('2023-10-30 13:05:00+0000', tz='UTC'))":168.67,"('AAPL', Timestamp('2023-10-30 13:10:00+0000', tz='UTC'))":168.71,"('AAPL', Timestamp('2023-10-30 13:15:00+0000', tz='UTC'))":168.5,"('AAPL', Timestamp('2023-10-30 13:20:00+0000', tz='UTC'))":168.65,"('AAPL', Timestamp('2023-10-30 13:25:00+0000', tz='UTC'))":168.63,"('AAPL', Timestamp('2023-10-30 13:30:00+0000', tz='UTC'))":169.02,"('AAPL', Timestamp('2023-10-30 13:35:00+0000', tz='UTC'))":170.02,"('AAPL', Timestamp('2023-10-30 13:40:00+0000', tz='UTC'))":170.74,"('AAPL', Timestamp('2023-10-30 13:45:00+0000', tz='UTC'))":170.9015,"('AAPL', Timestamp('2023-10-30 13:50:00+0000', tz='UTC'))":170.98,"('AAPL', Timestamp('2023-10-30 13:55:00+0000', tz='UTC'))":170.67,"('AAPL', Timestamp('2023-10-30 14:00:00+0000', tz='UTC'))":170.63,"('AAPL', Timestamp('2023-10-30 14:05:00+0000', tz='UTC'))":170.4099,"('AAPL', Timestamp('2023-10-30 14:10:00+0000', tz='UTC'))":170.71,"('AAPL', Timestamp('2023-10-30 14:15:00+0000', tz='UTC'))":170.375,"('AAPL', Timestamp('2023-10-30 14:20:00+0000', tz='UTC'))":169.8,"('AAPL', Timestamp('2023-10-30 14:25:00+0000', tz='UTC'))":169.54,"('AAPL', Timestamp('2023-10-30 14:30:00+0000', tz='UTC'))":169.37,"('AAPL', Timestamp('2023-10-30 14:35:00+0000', tz='UTC'))":169.58,"('AAPL', Timestamp('2023-10-30 14:40:00+0000', tz='UTC'))":169.77,"('AAPL', Timestamp('2023-10-30 14:45:00+0000', tz='UTC'))":169.53,"('AAPL', Timestamp('2023-10-30 14:50:00+0000', tz='UTC'))":169.67,"('AAPL', Timestamp('2023-10-30 14:55:00+0000', tz='UTC'))":170.0,"('AAPL', Timestamp('2023-10-30 15:00:00+0000', tz='UTC'))":169.44,"('AAPL', Timestamp('2023-10-30 15:05:00+0000', tz='UTC'))":169.95,"('AAPL', Timestamp('2023-10-30 15:10:00+0000', tz='UTC'))":169.96,"('AAPL', Timestamp('2023-10-30 15:15:00+0000', tz='UTC'))":169.88,"('AAPL', Timestamp('2023-10-30 15:20:00+0000', tz='UTC'))":170.08,"('AAPL', Timestamp('2023-10-30 15:25:00+0000', tz='UTC'))":169.59,"('AAPL', Timestamp('2023-10-30 15:30:00+0000', tz='UTC'))":169.67,"('AAPL', Timestamp('2023-10-30 15:35:00+0000', tz='UTC'))":170.061,"('AAPL', Timestamp('2023-10-30 15:40:00+0000', tz='UTC'))":169.7,"('AAPL', Timestamp('2023-10-30 15:45:00+0000', tz='UTC'))":169.78,"('AAPL', Timestamp('2023-10-30 15:50:00+0000', tz='UTC'))":169.74,"('AAPL', Timestamp('2023-10-30 15:55:00+0000', tz='UTC'))":169.88,"('AAPL', Timestamp('2023-10-30 16:00:00+0000', tz='UTC'))":169.91,"('AAPL', Timestamp('2023-10-30 16:05:00+0000', tz='UTC'))":169.855,"('AAPL', Timestamp('2023-10-30 16:10:00+0000', tz='UTC'))":169.695,"('AAPL', Timestamp('2023-10-30 16:15:00+0000', tz='UTC'))":169.86,"('AAPL', Timestamp('2023-10-30 16:20:00+0000', tz='UTC'))":169.53,"('AAPL', Timestamp('2023-10-30 16:25:00+0000', tz='UTC'))":169.47,"('AAPL', Timestamp('2023-10-30 16:30:00+0000', tz='UTC'))":169.465,"('AAPL', Timestamp('2023-10-30 16:35:00+0000', tz='UTC'))":169.57,"('AAPL', Timestamp('2023-10-30 16:40:00+0000', tz='UTC'))":169.4368,"('AAPL', Timestamp('2023-10-30 16:45:00+0000', tz='UTC'))":169.2,"('AAPL', Timestamp('2023-10-30 16:50:00+0000', tz='UTC'))":169.335,"('AAPL', Timestamp('2023-10-30 16:55:00+0000', tz='UTC'))":169.145,"('AAPL', Timestamp('2023-10-30 17:00:00+0000', tz='UTC'))":169.37,"('AAPL', Timestamp('2023-10-30 17:05:00+0000', tz='UTC'))":169.39,"('AAPL', Timestamp('2023-10-30 17:10:00+0000', tz='UTC'))":169.54,"('AAPL', Timestamp('2023-10-30 17:15:00+0000', tz='UTC'))":169.37,"('AAPL', Timestamp('2023-10-30 17:20:00+0000', tz='UTC'))":169.32,"('AAPL', Timestamp('2023-10-30 17:25:00+0000', tz='UTC'))":169.675,"('AAPL', Timestamp('2023-10-30 17:30:00+0000', tz='UTC'))":169.92,"('AAPL', Timestamp('2023-10-30 17:35:00+0000', tz='UTC'))":170.04,"('AAPL', Timestamp('2023-10-30 17:40:00+0000', tz='UTC'))":169.97,"('AAPL', Timestamp('2023-10-30 17:45:00+0000', tz='UTC'))":170.05,"('AAPL', Timestamp('2023-10-30 17:50:00+0000', tz='UTC'))":170.28,"('AAPL', Timestamp('2023-10-30 17:55:00+0000', tz='UTC'))":170.255,"('AAPL', Timestamp('2023-10-30 18:00:00+0000', tz='UTC'))":170.28,"('AAPL', Timestamp('2023-10-30 18:05:00+0000', tz='UTC'))":170.43,"('AAPL', Timestamp('2023-10-30 18:10:00+0000', tz='UTC'))":170.4,"('AAPL', Timestamp('2023-10-30 18:15:00+0000', tz='UTC'))":170.27,"('AAPL', Timestamp('2023-10-30 18:20:00+0000', tz='UTC'))":170.28,"('AAPL', Timestamp('2023-10-30 18:25:00+0000', tz='UTC'))":170.32,"('AAPL', Timestamp('2023-10-30 18:30:00+0000', tz='UTC'))":170.35,"('AAPL', Timestamp('2023-10-30 18:35:00+0000', tz='UTC'))":170.43,"('AAPL', Timestamp('2023-10-30 18:40:00+0000', tz='UTC'))":170.53,"('AAPL', Timestamp('2023-10-30 18:45:00+0000', tz='UTC'))":170.7437,"('AAPL', Timestamp('2023-10-30 18:50:00+0000', tz='UTC'))":170.71,"('AAPL', Timestamp('2023-10-30 18:55:00+0000', tz='UTC'))":170.65,"('AAPL', Timestamp('2023-10-30 19:00:00+0000', tz='UTC'))":170.5,"('AAPL', Timestamp('2023-10-30 19:05:00+0000', tz='UTC'))":170.34,"('AAPL', Timestamp('2023-10-30 19:10:00+0000', tz='UTC'))":170.24,"('AAPL', Timestamp('2023-10-30 19:15:00+0000', tz='UTC'))":170.12,"('AAPL', Timestamp('2023-10-30 19:20:00+0000', tz='UTC'))":170.1199,"('AAPL', Timestamp('2023-10-30 19:25:00+0000', tz='UTC'))":170.19,"('AAPL', Timestamp('2023-10-30 19:30:00+0000', tz='UTC'))":169.85,"('AAPL', Timestamp('2023-10-30 19:35:00+0000', tz='UTC'))":169.94,"('AAPL', Timestamp('2023-10-30 19:40:00+0000', tz='UTC'))":170.155,"('AAPL', Timestamp('2023-10-30 19:45:00+0000', tz='UTC'))":170.195,"('AAPL', Timestamp('2023-10-30 19:50:00+0000', tz='UTC'))":170.32,"('AAPL', Timestamp('2023-10-30 19:55:00+0000', tz='UTC'))":170.33,"('AAPL', Timestamp('2023-10-30 20:00:00+0000', tz='UTC'))":170.24,"('AAPL', Timestamp('2023-10-30 20:05:00+0000', tz='UTC'))":170.06,"('AAPL', Timestamp('2023-10-30 20:10:00+0000', tz='UTC'))":170.08,"('AAPL', Timestamp('2023-10-30 20:15:00+0000', tz='UTC'))":170.02,"('AAPL', Timestamp('2023-10-30 20:20:00+0000', tz='UTC'))":170.29,"('AAPL', Timestamp('2023-10-30 20:25:00+0000', tz='UTC'))":170.04,"('AAPL', Timestamp('2023-10-30 20:30:00+0000', tz='UTC'))":170.06,"('AAPL', Timestamp('2023-10-30 20:35:00+0000', tz='UTC'))":169.97,"('AAPL', Timestamp('2023-10-30 20:40:00+0000', tz='UTC'))":169.9632,"('AAPL', Timestamp('2023-10-30 20:45:00+0000', tz='UTC'))":169.93,"('AAPL', Timestamp('2023-10-30 20:50:00+0000', tz='UTC'))":170.02,"('AAPL', Timestamp('2023-10-30 20:55:00+0000', tz='UTC'))":169.96,"('AAPL', Timestamp('2023-10-30 21:00:00+0000', tz='UTC'))":170.0,"('AAPL', Timestamp('2023-10-30 21:05:00+0000', tz='UTC'))":170.03,"('AAPL', Timestamp('2023-10-30 21:10:00+0000', tz='UTC'))":169.99,"('AAPL', Timestamp('2023-10-30 21:15:00+0000', tz='UTC'))":169.95,"('AAPL', Timestamp('2023-10-30 21:20:00+0000', tz='UTC'))":169.94,"('AAPL', Timestamp('2023-10-30 21:25:00+0000', tz='UTC'))":170.0,"('AAPL', Timestamp('2023-10-30 21:30:00+0000', tz='UTC'))":170.03,"('AAPL', Timestamp('2023-10-30 21:35:00+0000', tz='UTC'))":170.0,"('AAPL', Timestamp('2023-10-30 21:40:00+0000', tz='UTC'))":169.9852,"('AAPL', Timestamp('2023-10-30 21:45:00+0000', tz='UTC'))":170.04,"('AAPL', Timestamp('2023-10-30 21:50:00+0000', tz='UTC'))":170.0,"('AAPL', Timestamp('2023-10-30 21:55:00+0000', tz='UTC'))":169.9808,"('AAPL', Timestamp('2023-10-30 22:00:00+0000', tz='UTC'))":169.94,"('AAPL', Timestamp('2023-10-30 22:05:00+0000', tz='UTC'))":169.95,"('AAPL', Timestamp('2023-10-30 22:10:00+0000', tz='UTC'))":169.8601,"('AAPL', Timestamp('2023-10-30 22:15:00+0000', tz='UTC'))":169.92,"('AAPL', Timestamp('2023-10-30 22:20:00+0000', tz='UTC'))":169.85,"('AAPL', Timestamp('2023-10-30 22:25:00+0000', tz='UTC'))":169.81,"('AAPL', Timestamp('2023-10-30 22:30:00+0000', tz='UTC'))":169.85,"('AAPL', Timestamp('2023-10-30 22:35:00+0000', tz='UTC'))":169.83,"('AAPL', Timestamp('2023-10-30 22:40:00+0000', tz='UTC'))":169.8611,"('AAPL', Timestamp('2023-10-30 22:50:00+0000', tz='UTC'))":169.82,"('AAPL', Timestamp('2023-10-30 22:55:00+0000', tz='UTC'))":169.8699,"('AAPL', Timestamp('2023-10-30 23:00:00+0000', tz='UTC'))":169.87,"('AAPL', Timestamp('2023-10-30 23:05:00+0000', tz='UTC'))":169.85,"('AAPL', Timestamp('2023-10-30 23:10:00+0000', tz='UTC'))":169.89,"('AAPL', Timestamp('2023-10-30 23:15:00+0000', tz='UTC'))":169.85,"('AAPL', Timestamp('2023-10-30 23:20:00+0000', tz='UTC'))":169.8699,"('AAPL', Timestamp('2023-10-30 23:25:00+0000', tz='UTC'))":169.85,"('AAPL', Timestamp('2023-10-30 23:30:00+0000', tz='UTC'))":169.85,"('AAPL', Timestamp('2023-10-30 23:35:00+0000', tz='UTC'))":169.86,"('AAPL', Timestamp('2023-10-30 23:40:00+0000', tz='UTC'))":169.85,"('AAPL', Timestamp('2023-10-30 23:45:00+0000', tz='UTC'))":169.81,"('AAPL', Timestamp('2023-10-30 23:50:00+0000', tz='UTC'))":169.73},"high":{"('AAPL', Timestamp('2023-10-30 08:00:00+0000', tz='UTC'))":168.98,"('AAPL', Timestamp('2023-10-30 08:05:00+0000', tz='UTC'))":169.0,"('AAPL', Timestamp('2023-10-30 08:10:00+0000', tz='UTC'))":168.97,"('AAPL', Timestamp('2023-10-30 08:15:00+0000', tz='UTC'))":169.0,"('AAPL', Timestamp('2023-10-30 08:20:00+0000', tz='UTC'))":169.0,"('AAPL', Timestamp('2023-10-30 08:25:00+0000', tz='UTC'))":168.91,"('AAPL', Timestamp('2023-10-30 08:35:00+0000', tz='UTC'))":168.85,"('AAPL', Timestamp('2023-10-30 08:40:00+0000', tz='UTC'))":168.92,"('AAPL', Timestamp('2023-10-30 08:45:00+0000', tz='UTC'))":168.86,"('AAPL', Timestamp('2023-10-30 08:50:00+0000', tz='UTC'))":168.99,"('AAPL', Timestamp('2023-10-30 09:00:00+0000', tz='UTC'))":169.09,"('AAPL', Timestamp('2023-10-30 09:05:00+0000', tz='UTC'))":169.2,"('AAPL', Timestamp('2023-10-30 09:10:00+0000', tz='UTC'))":169.23,"('AAPL', Timestamp('2023-10-30 09:15:00+0000', tz='UTC'))":169.47,"('AAPL', Timestamp('2023-10-30 09:20:00+0000', tz='UTC'))":169.37,"('AAPL', Timestamp('2023-10-30 09:25:00+0000', tz='UTC'))":169.22,"('AAPL', Timestamp('2023-10-30 09:30:00+0000', tz='UTC'))":169.25,"('AAPL', Timestamp('2023-10-30 09:35:00+0000', tz='UTC'))":169.16,"('AAPL', Timestamp('2023-10-30 09:40:00+0000', tz='UTC'))":169.1,"('AAPL', Timestamp('2023-10-30 09:45:00+0000', tz='UTC'))":169.11,"('AAPL', Timestamp('2023-10-30 09:50:00+0000', tz='UTC'))":169.14,"('AAPL', Timestamp('2023-10-30 09:55:00+0000', tz='UTC'))":169.16,"('AAPL', Timestamp('2023-10-30 10:05:00+0000', tz='UTC'))":169.17,"('AAPL', Timestamp('2023-10-30 10:10:00+0000', tz='UTC'))":169.13,"('AAPL', Timestamp('2023-10-30 10:15:00+0000', tz='UTC'))":169.12,"('AAPL', Timestamp('2023-10-30 10:20:00+0000', tz='UTC'))":169.02,"('AAPL', Timestamp('2023-10-30 10:25:00+0000', tz='UTC'))":169.01,"('AAPL', Timestamp('2023-10-30 10:30:00+0000', tz='UTC'))":169.05,"('AAPL', Timestamp('2023-10-30 10:35:00+0000', tz='UTC'))":169.04,"('AAPL', Timestamp('2023-10-30 10:45:00+0000', tz='UTC'))":169.09,"('AAPL', Timestamp('2023-10-30 10:50:00+0000', tz='UTC'))":169.11,"('AAPL', Timestamp('2023-10-30 10:55:00+0000', tz='UTC'))":169.22,"('AAPL', Timestamp('2023-10-30 11:00:00+0000', tz='UTC'))":169.3,"('AAPL', Timestamp('2023-10-30 11:05:00+0000', tz='UTC'))":169.27,"('AAPL', Timestamp('2023-10-30 11:10:00+0000', tz='UTC'))":169.2,"('AAPL', Timestamp('2023-10-30 11:15:00+0000', tz='UTC'))":169.23,"('AAPL', Timestamp('2023-10-30 11:20:00+0000', tz='UTC'))":169.21,"('AAPL', Timestamp('2023-10-30 11:25:00+0000', tz='UTC'))":169.16,"('AAPL', Timestamp('2023-10-30 11:30:00+0000', tz='UTC'))":169.21,"('AAPL', Timestamp('2023-10-30 11:35:00+0000', tz='UTC'))":169.21,"('AAPL', Timestamp('2023-10-30 11:40:00+0000', tz='UTC'))":169.2,"('AAPL', Timestamp('2023-10-30 11:45:00+0000', tz='UTC'))":169.28,"('AAPL', Timestamp('2023-10-30 11:50:00+0000', tz='UTC'))":169.25,"('AAPL', Timestamp('2023-10-30 11:55:00+0000', tz='UTC'))":169.16,"('AAPL', Timestamp('2023-10-30 12:00:00+0000', tz='UTC'))":169.28,"('AAPL', Timestamp('2023-10-30 12:05:00+0000', tz='UTC'))":169.05,"('AAPL', Timestamp('2023-10-30 12:10:00+0000', tz='UTC'))":169.0,"('AAPL', Timestamp('2023-10-30 12:15:00+0000', tz='UTC'))":168.95,"('AAPL', Timestamp('2023-10-30 12:20:00+0000', tz='UTC'))":168.78,"('AAPL', Timestamp('2023-10-30 12:25:00+0000', tz='UTC'))":168.75,"('AAPL', Timestamp('2023-10-30 12:30:00+0000', tz='UTC'))":168.97,"('AAPL', Timestamp('2023-10-30 12:35:00+0000', tz='UTC'))":168.87,"('AAPL', Timestamp('2023-10-30 12:40:00+0000', tz='UTC'))":168.69,"('AAPL', Timestamp('2023-10-30 12:45:00+0000', tz='UTC'))":168.85,"('AAPL', Timestamp('2023-10-30 12:50:00+0000', tz='UTC'))":168.44,"('AAPL', Timestamp('2023-10-30 12:55:00+0000', tz='UTC'))":168.6996,"('AAPL', Timestamp('2023-10-30 13:00:00+0000', tz='UTC'))":168.72,"('AAPL', Timestamp('2023-10-30 13:05:00+0000', tz='UTC'))":168.75,"('AAPL', Timestamp('2023-10-30 13:10:00+0000', tz='UTC'))":168.79,"('AAPL', Timestamp('2023-10-30 13:15:00+0000', tz='UTC'))":168.67,"('AAPL', Timestamp('2023-10-30 13:20:00+0000', tz='UTC'))":168.7,"('AAPL', Timestamp('2023-10-30 13:25:00+0000', tz='UTC'))":169.06,"('AAPL', Timestamp('2023-10-30 13:30:00+0000', tz='UTC'))":170.1,"('AAPL', Timestamp('2023-10-30 13:35:00+0000', tz='UTC'))":171.04,"('AAPL', Timestamp('2023-10-30 13:40:00+0000', tz='UTC'))":170.9,"('AAPL', Timestamp('2023-10-30 13:45:00+0000', tz='UTC'))":171.11,"('AAPL', Timestamp('2023-10-30 13:50:00+0000', tz='UTC'))":171.17,"('AAPL', Timestamp('2023-10-30 13:55:00+0000', tz='UTC'))":170.87,"('AAPL', Timestamp('2023-10-30 14:00:00+0000', tz='UTC'))":170.9,"('AAPL', Timestamp('2023-10-30 14:05:00+0000', tz='UTC'))":170.83,"('AAPL', Timestamp('2023-10-30 14:10:00+0000', tz='UTC'))":170.805,"('AAPL', Timestamp('2023-10-30 14:15:00+0000', tz='UTC'))":170.45,"('AAPL', Timestamp('2023-10-30 14:20:00+0000', tz='UTC'))":169.825,"('AAPL', Timestamp('2023-10-30 14:25:00+0000', tz='UTC'))":169.68,"('AAPL', Timestamp('2023-10-30 14:30:00+0000', tz='UTC'))":169.62,"('AAPL', Timestamp('2023-10-30 14:35:00+0000', tz='UTC'))":169.92,"('AAPL', Timestamp('2023-10-30 14:40:00+0000', tz='UTC'))":169.985,"('AAPL', Timestamp('2023-10-30 14:45:00+0000', tz='UTC'))":169.91,"('AAPL', Timestamp('2023-10-30 14:50:00+0000', tz='UTC'))":170.13,"('AAPL', Timestamp('2023-10-30 14:55:00+0000', tz='UTC'))":170.0,"('AAPL', Timestamp('2023-10-30 15:00:00+0000', tz='UTC'))":170.0531,"('AAPL', Timestamp('2023-10-30 15:05:00+0000', tz='UTC'))":170.1103,"('AAPL', Timestamp('2023-10-30 15:10:00+0000', tz='UTC'))":170.2,"('AAPL', Timestamp('2023-10-30 15:15:00+0000', tz='UTC'))":170.19,"('AAPL', Timestamp('2023-10-30 15:20:00+0000', tz='UTC'))":170.18,"('AAPL', Timestamp('2023-10-30 15:25:00+0000', tz='UTC'))":169.67,"('AAPL', Timestamp('2023-10-30 15:30:00+0000', tz='UTC'))":170.0602,"('AAPL', Timestamp('2023-10-30 15:35:00+0000', tz='UTC'))":170.16,"('AAPL', Timestamp('2023-10-30 15:40:00+0000', tz='UTC'))":169.79,"('AAPL', Timestamp('2023-10-30 15:45:00+0000', tz='UTC'))":169.84,"('AAPL', Timestamp('2023-10-30 15:50:00+0000', tz='UTC'))":169.95,"('AAPL', Timestamp('2023-10-30 15:55:00+0000', tz='UTC'))":169.97,"('AAPL', Timestamp('2023-10-30 16:00:00+0000', tz='UTC'))":170.0,"('AAPL', Timestamp('2023-10-30 16:05:00+0000', tz='UTC'))":169.86,"('AAPL', Timestamp('2023-10-30 16:10:00+0000', tz='UTC'))":169.93,"('AAPL', Timestamp('2023-10-30 16:15:00+0000', tz='UTC'))":169.97,"('AAPL', Timestamp('2023-10-30 16:20:00+0000', tz='UTC'))":169.58,"('AAPL', Timestamp('2023-10-30 16:25:00+0000', tz='UTC'))":169.59,"('AAPL', Timestamp('2023-10-30 16:30:00+0000', tz='UTC'))":169.59,"('AAPL', Timestamp('2023-10-30 16:35:00+0000', tz='UTC'))":169.7,"('AAPL', Timestamp('2023-10-30 16:40:00+0000', tz='UTC'))":169.46,"('AAPL', Timestamp('2023-10-30 16:45:00+0000', tz='UTC'))":169.375,"('AAPL', Timestamp('2023-10-30 16:50:00+0000', tz='UTC'))":169.44,"('AAPL', Timestamp('2023-10-30 16:55:00+0000', tz='UTC'))":169.39,"('AAPL', Timestamp('2023-10-30 17:00:00+0000', tz='UTC'))":169.43,"('AAPL', Timestamp('2023-10-30 17:05:00+0000', tz='UTC'))":169.58,"('AAPL', Timestamp('2023-10-30 17:10:00+0000', tz='UTC'))":169.625,"('AAPL', Timestamp('2023-10-30 17:15:00+0000', tz='UTC'))":169.54,"('AAPL', Timestamp('2023-10-30 17:20:00+0000', tz='UTC'))":169.68,"('AAPL', Timestamp('2023-10-30 17:25:00+0000', tz='UTC'))":170.05,"('AAPL', Timestamp('2023-10-30 17:30:00+0000', tz='UTC'))":170.19,"('AAPL', Timestamp('2023-10-30 17:35:00+0000', tz='UTC'))":170.04,"('AAPL', Timestamp('2023-10-30 17:40:00+0000', tz='UTC'))":170.1,"('AAPL', Timestamp('2023-10-30 17:45:00+0000', tz='UTC'))":170.32,"('AAPL', Timestamp('2023-10-30 17:50:00+0000', tz='UTC'))":170.4,"('AAPL', Timestamp('2023-10-30 17:55:00+0000', tz='UTC'))":170.3371,"('AAPL', Timestamp('2023-10-30 18:00:00+0000', tz='UTC'))":170.43,"('AAPL', Timestamp('2023-10-30 18:05:00+0000', tz='UTC'))":170.4376,"('AAPL', Timestamp('2023-10-30 18:10:00+0000', tz='UTC'))":170.49,"('AAPL', Timestamp('2023-10-30 18:15:00+0000', tz='UTC'))":170.33,"('AAPL', Timestamp('2023-10-30 18:20:00+0000', tz='UTC'))":170.44,"('AAPL', Timestamp('2023-10-30 18:25:00+0000', tz='UTC'))":170.49,"('AAPL', Timestamp('2023-10-30 18:30:00+0000', tz='UTC'))":170.455,"('AAPL', Timestamp('2023-10-30 18:35:00+0000', tz='UTC'))":170.65,"('AAPL', Timestamp('2023-10-30 18:40:00+0000', tz='UTC'))":170.77,"('AAPL', Timestamp('2023-10-30 18:45:00+0000', tz='UTC'))":170.82,"('AAPL', Timestamp('2023-10-30 18:50:00+0000', tz='UTC'))":170.8,"('AAPL', Timestamp('2023-10-30 18:55:00+0000', tz='UTC'))":170.6599,"('AAPL', Timestamp('2023-10-30 19:00:00+0000', tz='UTC'))":170.67,"('AAPL', Timestamp('2023-10-30 19:05:00+0000', tz='UTC'))":170.485,"('AAPL', Timestamp('2023-10-30 19:10:00+0000', tz='UTC'))":170.24,"('AAPL', Timestamp('2023-10-30 19:15:00+0000', tz='UTC'))":170.25,"('AAPL', Timestamp('2023-10-30 19:20:00+0000', tz='UTC'))":170.22,"('AAPL', Timestamp('2023-10-30 19:25:00+0000', tz='UTC'))":170.2,"('AAPL', Timestamp('2023-10-30 19:30:00+0000', tz='UTC'))":170.0,"('AAPL', Timestamp('2023-10-30 19:35:00+0000', tz='UTC'))":170.2,"('AAPL', Timestamp('2023-10-30 19:40:00+0000', tz='UTC'))":170.28,"('AAPL', Timestamp('2023-10-30 19:45:00+0000', tz='UTC'))":170.45,"('AAPL', Timestamp('2023-10-30 19:50:00+0000', tz='UTC'))":170.48,"('AAPL', Timestamp('2023-10-30 19:55:00+0000', tz='UTC'))":170.45,"('AAPL', Timestamp('2023-10-30 20:00:00+0000', tz='UTC'))":170.29,"('AAPL', Timestamp('2023-10-30 20:05:00+0000', tz='UTC'))":170.29,"('AAPL', Timestamp('2023-10-30 20:10:00+0000', tz='UTC'))":170.08,"('AAPL', Timestamp('2023-10-30 20:15:00+0000', tz='UTC'))":170.29,"('AAPL', Timestamp('2023-10-30 20:20:00+0000', tz='UTC'))":170.29,"('AAPL', Timestamp('2023-10-30 20:25:00+0000', tz='UTC'))":170.08,"('AAPL', Timestamp('2023-10-30 20:30:00+0000', tz='UTC'))":170.06,"('AAPL', Timestamp('2023-10-30 20:35:00+0000', tz='UTC'))":170.29,"('AAPL', Timestamp('2023-10-30 20:40:00+0000', tz='UTC'))":169.9632,"('AAPL', Timestamp('2023-10-30 20:45:00+0000', tz='UTC'))":170.0,"('AAPL', Timestamp('2023-10-30 20:50:00+0000', tz='UTC'))":170.02,"('AAPL', Timestamp('2023-10-30 20:55:00+0000', tz='UTC'))":169.96,"('AAPL', Timestamp('2023-10-30 21:00:00+0000', tz='UTC'))":170.06,"('AAPL', Timestamp('2023-10-30 21:05:00+0000', tz='UTC'))":170.03,"('AAPL', Timestamp('2023-10-30 21:10:00+0000', tz='UTC'))":170.01,"('AAPL', Timestamp('2023-10-30 21:15:00+0000', tz='UTC'))":169.96,"('AAPL', Timestamp('2023-10-30 21:20:00+0000', tz='UTC'))":170.02,"('AAPL', Timestamp('2023-10-30 21:25:00+0000', tz='UTC'))":170.05,"('AAPL', Timestamp('2023-10-30 21:30:00+0000', tz='UTC'))":170.03,"('AAPL', Timestamp('2023-10-30 21:35:00+0000', tz='UTC'))":170.05,"('AAPL', Timestamp('2023-10-30 21:40:00+0000', tz='UTC'))":169.9852,"('AAPL', Timestamp('2023-10-30 21:45:00+0000', tz='UTC'))":170.04,"('AAPL', Timestamp('2023-10-30 21:50:00+0000', tz='UTC'))":170.0,"('AAPL', Timestamp('2023-10-30 21:55:00+0000', tz='UTC'))":170.0,"('AAPL', Timestamp('2023-10-30 22:00:00+0000', tz='UTC'))":169.99,"('AAPL', Timestamp('2023-10-30 22:05:00+0000', tz='UTC'))":169.95,"('AAPL', Timestamp('2023-10-30 22:10:00+0000', tz='UTC'))":169.95,"('AAPL', Timestamp('2023-10-30 22:15:00+0000', tz='UTC'))":169.92,"('AAPL', Timestamp('2023-10-30 22:20:00+0000', tz='UTC'))":169.85,"('AAPL', Timestamp('2023-10-30 22:25:00+0000', tz='UTC'))":169.81,"('AAPL', Timestamp('2023-10-30 22:30:00+0000', tz='UTC'))":169.88,"('AAPL', Timestamp('2023-10-30 22:35:00+0000', tz='UTC'))":169.85,"('AAPL', Timestamp('2023-10-30 22:40:00+0000', tz='UTC'))":169.9,"('AAPL', Timestamp('2023-10-30 22:50:00+0000', tz='UTC'))":169.9,"('AAPL', Timestamp('2023-10-30 22:55:00+0000', tz='UTC'))":169.8699,"('AAPL', Timestamp('2023-10-30 23:00:00+0000', tz='UTC'))":169.91,"('AAPL', Timestamp('2023-10-30 23:05:00+0000', tz='UTC'))":169.89,"('AAPL', Timestamp('2023-10-30 23:10:00+0000', tz='UTC'))":169.89,"('AAPL', Timestamp('2023-10-30 23:15:00+0000', tz='UTC'))":169.87,"('AAPL', Timestamp('2023-10-30 23:20:00+0000', tz='UTC'))":169.87,"('AAPL', Timestamp('2023-10-30 23:25:00+0000', tz='UTC'))":169.85,"('AAPL', Timestamp('2023-10-30 23:30:00+0000', tz='UTC'))":169.86,"('AAPL', Timestamp('2023-10-30 23:35:00+0000', tz='UTC'))":169.86,"('AAPL', Timestamp('2023-10-30 23:40:00+0000', tz='UTC'))":169.85,"('AAPL', Timestamp('2023-10-30 23:45:00+0000', tz='UTC'))":169.81,"('AAPL', Timestamp('2023-10-30 23:50:00+0000', tz='UTC'))":169.84},"low":{"('AAPL', Timestamp('2023-10-30 08:00:00+0000', tz='UTC'))":168.6,"('AAPL', Timestamp('2023-10-30 08:05:00+0000', tz='UTC'))":168.92,"('AAPL', Timestamp('2023-10-30 08:10:00+0000', tz='UTC'))":168.9,"('AAPL', Timestamp('2023-10-30 08:15:00+0000', tz='UTC'))":168.99,"('AAPL', Timestamp('2023-10-30 08:20:00+0000', tz='UTC'))":168.92,"('AAPL', Timestamp('2023-10-30 08:25:00+0000', tz='UTC'))":168.85,"('AAPL', Timestamp('2023-10-30 08:35:00+0000', tz='UTC'))":168.85,"('AAPL', Timestamp('2023-10-30 08:40:00+0000', tz='UTC'))":168.85,"('AAPL', Timestamp('2023-10-30 08:45:00+0000', tz='UTC'))":168.71,"('AAPL', Timestamp('2023-10-30 08:50:00+0000', tz='UTC'))":168.8,"('AAPL', Timestamp('2023-10-30 09:00:00+0000', tz='UTC'))":168.97,"('AAPL', Timestamp('2023-10-30 09:05:00+0000', tz='UTC'))":169.1,"('AAPL', Timestamp('2023-10-30 09:10:00+0000', tz='UTC'))":169.2,"('AAPL', Timestamp('2023-10-30 09:15:00+0000', tz='UTC'))":169.43,"('AAPL', Timestamp('2023-10-30 09:20:00+0000', tz='UTC'))":169.22,"('AAPL', Timestamp('2023-10-30 09:25:00+0000', tz='UTC'))":169.2,"('AAPL', Timestamp('2023-10-30 09:30:00+0000', tz='UTC'))":169.25,"('AAPL', Timestamp('2023-10-30 09:35:00+0000', tz='UTC'))":168.96,"('AAPL', Timestamp('2023-10-30 09:40:00+0000', tz='UTC'))":169.1,"('AAPL', Timestamp('2023-10-30 09:45:00+0000', tz='UTC'))":169.11,"('AAPL', Timestamp('2023-10-30 09:50:00+0000', tz='UTC'))":169.14,"('AAPL', Timestamp('2023-10-30 09:55:00+0000', tz='UTC'))":169.16,"('AAPL', Timestamp('2023-10-30 10:05:00+0000', tz='UTC'))":169.12,"('AAPL', Timestamp('2023-10-30 10:10:00+0000', tz='UTC'))":169.12,"('AAPL', Timestamp('2023-10-30 10:15:00+0000', tz='UTC'))":168.96,"('AAPL', Timestamp('2023-10-30 10:20:00+0000', tz='UTC'))":169.0,"('AAPL', Timestamp('2023-10-30 10:25:00+0000', tz='UTC'))":168.98,"('AAPL', Timestamp('2023-10-30 10:30:00+0000', tz='UTC'))":169.0,"('AAPL', Timestamp('2023-10-30 10:35:00+0000', tz='UTC'))":169.0,"('AAPL', Timestamp('2023-10-30 10:45:00+0000', tz='UTC'))":169.0,"('AAPL', Timestamp('2023-10-30 10:50:00+0000', tz='UTC'))":169.0,"('AAPL', Timestamp('2023-10-30 10:55:00+0000', tz='UTC'))":169.13,"('AAPL', Timestamp('2023-10-30 11:00:00+0000', tz='UTC'))":169.13,"('AAPL', Timestamp('2023-10-30 11:05:00+0000', tz='UTC'))":169.24,"('AAPL', Timestamp('2023-10-30 11:10:00+0000', tz='UTC'))":169.14,"('AAPL', Timestamp('2023-10-30 11:15:00+0000', tz='UTC'))":169.2,"('AAPL', Timestamp('2023-10-30 11:20:00+0000', tz='UTC'))":169.13,"('AAPL', Timestamp('2023-10-30 11:25:00+0000', tz='UTC'))":169.1,"('AAPL', Timestamp('2023-10-30 11:30:00+0000', tz='UTC'))":169.13,"('AAPL', Timestamp('2023-10-30 11:35:00+0000', tz='UTC'))":169.21,"('AAPL', Timestamp('2023-10-30 11:40:00+0000', tz='UTC'))":169.2,"('AAPL', Timestamp('2023-10-30 11:45:00+0000', tz='UTC'))":169.24,"('AAPL', Timestamp('2023-10-30 11:50:00+0000', tz='UTC'))":169.18,"('AAPL', Timestamp('2023-10-30 11:55:00+0000', tz='UTC'))":169.1,"('AAPL', Timestamp('2023-10-30 12:00:00+0000', tz='UTC'))":168.57,"('AAPL', Timestamp('2023-10-30 12:05:00+0000', tz='UTC'))":168.91,"('AAPL', Timestamp('2023-10-30 12:10:00+0000', tz='UTC'))":168.89,"('AAPL', Timestamp('2023-10-30 12:15:00+0000', tz='UTC'))":168.76,"('AAPL', Timestamp('2023-10-30 12:20:00+0000', tz='UTC'))":168.47,"('AAPL', Timestamp('2023-10-30 12:25:00+0000', tz='UTC'))":168.617,"('AAPL', Timestamp('2023-10-30 12:30:00+0000', tz='UTC'))":168.75,"('AAPL', Timestamp('2023-10-30 12:35:00+0000', tz='UTC'))":168.65,"('AAPL', Timestamp('2023-10-30 12:40:00+0000', tz='UTC'))":168.55,"('AAPL', Timestamp('2023-10-30 12:45:00+0000', tz='UTC'))":168.49,"('AAPL', Timestamp('2023-10-30 12:50:00+0000', tz='UTC'))":168.35,"('AAPL', Timestamp('2023-10-30 12:55:00+0000', tz='UTC'))":168.395,"('AAPL', Timestamp('2023-10-30 13:00:00+0000', tz='UTC'))":168.56,"('AAPL', Timestamp('2023-10-30 13:05:00+0000', tz='UTC'))":168.65,"('AAPL', Timestamp('2023-10-30 13:10:00+0000', tz='UTC'))":168.45,"('AAPL', Timestamp('2023-10-30 13:15:00+0000', tz='UTC'))":168.4,"('AAPL', Timestamp('2023-10-30 13:20:00+0000', tz='UTC'))":168.57,"('AAPL', Timestamp('2023-10-30 13:25:00+0000', tz='UTC'))":168.37,"('AAPL', Timestamp('2023-10-30 13:30:00+0000', tz='UTC'))":168.87,"('AAPL', Timestamp('2023-10-30 13:35:00+0000', tz='UTC'))":169.85,"('AAPL', Timestamp('2023-10-30 13:40:00+0000', tz='UTC'))":170.4,"('AAPL', Timestamp('2023-10-30 13:45:00+0000', tz='UTC'))":170.76,"('AAPL', Timestamp('2023-10-30 13:50:00+0000', tz='UTC'))":170.605,"('AAPL', Timestamp('2023-10-30 13:55:00+0000', tz='UTC'))":170.53,"('AAPL', Timestamp('2023-10-30 14:00:00+0000', tz='UTC'))":170.33,"('AAPL', Timestamp('2023-10-30 14:05:00+0000', tz='UTC'))":170.33,"('AAPL', Timestamp('2023-10-30 14:10:00+0000', tz='UTC'))":170.27,"('AAPL', Timestamp('2023-10-30 14:15:00+0000', tz='UTC'))":169.64,"('AAPL', Timestamp('2023-10-30 14:20:00+0000', tz='UTC'))":169.33,"('AAPL', Timestamp('2023-10-30 14:25:00+0000', tz='UTC'))":169.35,"('AAPL', Timestamp('2023-10-30 14:30:00+0000', tz='UTC'))":169.21,"('AAPL', Timestamp('2023-10-30 14:35:00+0000', tz='UTC'))":169.495,"('AAPL', Timestamp('2023-10-30 14:40:00+0000', tz='UTC'))":169.53,"('AAPL', Timestamp('2023-10-30 14:45:00+0000', tz='UTC'))":169.495,"('AAPL', Timestamp('2023-10-30 14:50:00+0000', tz='UTC'))":169.58,"('AAPL', Timestamp('2023-10-30 14:55:00+0000', tz='UTC'))":169.37,"('AAPL', Timestamp('2023-10-30 15:00:00+0000', tz='UTC'))":169.425,"('AAPL', Timestamp('2023-10-30 15:05:00+0000', tz='UTC'))":169.885,"('AAPL', Timestamp('2023-10-30 15:10:00+0000', tz='UTC'))":169.75,"('AAPL', Timestamp('2023-10-30 15:15:00+0000', tz='UTC'))":169.8,"('AAPL', Timestamp('2023-10-30 15:20:00+0000', tz='UTC'))":169.45,"('AAPL', Timestamp('2023-10-30 15:25:00+0000', tz='UTC'))":169.43,"('AAPL', Timestamp('2023-10-30 15:30:00+0000', tz='UTC'))":169.65,"('AAPL', Timestamp('2023-10-30 15:35:00+0000', tz='UTC'))":169.71,"('AAPL', Timestamp('2023-10-30 15:40:00+0000', tz='UTC'))":169.54,"('AAPL', Timestamp('2023-10-30 15:45:00+0000', tz='UTC'))":169.594,"('AAPL', Timestamp('2023-10-30 15:50:00+0000', tz='UTC'))":169.6901,"('AAPL', Timestamp('2023-10-30 15:55:00+0000', tz='UTC'))":169.77,"('AAPL', Timestamp('2023-10-30 16:00:00+0000', tz='UTC'))":169.77,"('AAPL', Timestamp('2023-10-30 16:05:00+0000', tz='UTC'))":169.605,"('AAPL', Timestamp('2023-10-30 16:10:00+0000', tz='UTC'))":169.695,"('AAPL', Timestamp('2023-10-30 16:15:00+0000', tz='UTC'))":169.48,"('AAPL', Timestamp('2023-10-30 16:20:00+0000', tz='UTC'))":169.41,"('AAPL', Timestamp('2023-10-30 16:25:00+0000', tz='UTC'))":169.44,"('AAPL', Timestamp('2023-10-30 16:30:00+0000', tz='UTC'))":169.35,"('AAPL', Timestamp('2023-10-30 16:35:00+0000', tz='UTC'))":169.41,"('AAPL', Timestamp('2023-10-30 16:40:00+0000', tz='UTC'))":169.16,"('AAPL', Timestamp('2023-10-30 16:45:00+0000', tz='UTC'))":169.1015,"('AAPL', Timestamp('2023-10-30 16:50:00+0000', tz='UTC'))":169.1399,"('AAPL', Timestamp('2023-10-30 16:55:00+0000', tz='UTC'))":169.05,"('AAPL', Timestamp('2023-10-30 17:00:00+0000', tz='UTC'))":169.1834,"('AAPL', Timestamp('2023-10-30 17:05:00+0000', tz='UTC'))":169.3502,"('AAPL', Timestamp('2023-10-30 17:10:00+0000', tz='UTC'))":169.295,"('AAPL', Timestamp('2023-10-30 17:15:00+0000', tz='UTC'))":169.2687,"('AAPL', Timestamp('2023-10-30 17:20:00+0000', tz='UTC'))":169.21,"('AAPL', Timestamp('2023-10-30 17:25:00+0000', tz='UTC'))":169.62,"('AAPL', Timestamp('2023-10-30 17:30:00+0000', tz='UTC'))":169.92,"('AAPL', Timestamp('2023-10-30 17:35:00+0000', tz='UTC'))":169.88,"('AAPL', Timestamp('2023-10-30 17:40:00+0000', tz='UTC'))":169.93,"('AAPL', Timestamp('2023-10-30 17:45:00+0000', tz='UTC'))":169.99,"('AAPL', Timestamp('2023-10-30 17:50:00+0000', tz='UTC'))":170.21,"('AAPL', Timestamp('2023-10-30 17:55:00+0000', tz='UTC'))":170.14,"('AAPL', Timestamp('2023-10-30 18:00:00+0000', tz='UTC'))":170.1801,"('AAPL', Timestamp('2023-10-30 18:05:00+0000', tz='UTC'))":170.2101,"('AAPL', Timestamp('2023-10-30 18:10:00+0000', tz='UTC'))":170.26,"('AAPL', Timestamp('2023-10-30 18:15:00+0000', tz='UTC'))":170.135,"('AAPL', Timestamp('2023-10-30 18:20:00+0000', tz='UTC'))":170.21,"('AAPL', Timestamp('2023-10-30 18:25:00+0000', tz='UTC'))":170.225,"('AAPL', Timestamp('2023-10-30 18:30:00+0000', tz='UTC'))":170.302,"('AAPL', Timestamp('2023-10-30 18:35:00+0000', tz='UTC'))":170.395,"('AAPL', Timestamp('2023-10-30 18:40:00+0000', tz='UTC'))":170.5,"('AAPL', Timestamp('2023-10-30 18:45:00+0000', tz='UTC'))":170.64,"('AAPL', Timestamp('2023-10-30 18:50:00+0000', tz='UTC'))":170.57,"('AAPL', Timestamp('2023-10-30 18:55:00+0000', tz='UTC'))":170.4401,"('AAPL', Timestamp('2023-10-30 19:00:00+0000', tz='UTC'))":170.325,"('AAPL', Timestamp('2023-10-30 19:05:00+0000', tz='UTC'))":170.215,"('AAPL', Timestamp('2023-10-30 19:10:00+0000', tz='UTC'))":170.01,"('AAPL', Timestamp('2023-10-30 19:15:00+0000', tz='UTC'))":170.01,"('AAPL', Timestamp('2023-10-30 19:20:00+0000', tz='UTC'))":170.01,"('AAPL', Timestamp('2023-10-30 19:25:00+0000', tz='UTC'))":169.8402,"('AAPL', Timestamp('2023-10-30 19:30:00+0000', tz='UTC'))":169.845,"('AAPL', Timestamp('2023-10-30 19:35:00+0000', tz='UTC'))":169.93,"('AAPL', Timestamp('2023-10-30 19:40:00+0000', tz='UTC'))":170.06,"('AAPL', Timestamp('2023-10-30 19:45:00+0000', tz='UTC'))":170.035,"('AAPL', Timestamp('2023-10-30 19:50:00+0000', tz='UTC'))":170.16,"('AAPL', Timestamp('2023-10-30 19:55:00+0000', tz='UTC'))":170.1,"('AAPL', Timestamp('2023-10-30 20:00:00+0000', tz='UTC'))":170.0,"('AAPL', Timestamp('2023-10-30 20:05:00+0000', tz='UTC'))":170.04,"('AAPL', Timestamp('2023-10-30 20:10:00+0000', tz='UTC'))":169.99,"('AAPL', Timestamp('2023-10-30 20:15:00+0000', tz='UTC'))":169.91,"('AAPL', Timestamp('2023-10-30 20:20:00+0000', tz='UTC'))":169.97,"('AAPL', Timestamp('2023-10-30 20:25:00+0000', tz='UTC'))":170.04,"('AAPL', Timestamp('2023-10-30 20:30:00+0000', tz='UTC'))":170.0,"('AAPL', Timestamp('2023-10-30 20:35:00+0000', tz='UTC'))":169.96,"('AAPL', Timestamp('2023-10-30 20:40:00+0000', tz='UTC'))":169.92,"('AAPL', Timestamp('2023-10-30 20:45:00+0000', tz='UTC'))":169.92,"('AAPL', Timestamp('2023-10-30 20:50:00+0000', tz='UTC'))":169.95,"('AAPL', Timestamp('2023-10-30 20:55:00+0000', tz='UTC'))":169.96,"('AAPL', Timestamp('2023-10-30 21:00:00+0000', tz='UTC'))":170.0,"('AAPL', Timestamp('2023-10-30 21:05:00+0000', tz='UTC'))":169.98,"('AAPL', Timestamp('2023-10-30 21:10:00+0000', tz='UTC'))":169.9492,"('AAPL', Timestamp('2023-10-30 21:15:00+0000', tz='UTC'))":169.95,"('AAPL', Timestamp('2023-10-30 21:20:00+0000', tz='UTC'))":169.94,"('AAPL', Timestamp('2023-10-30 21:25:00+0000', tz='UTC'))":170.0,"('AAPL', Timestamp('2023-10-30 21:30:00+0000', tz='UTC'))":170.0,"('AAPL', Timestamp('2023-10-30 21:35:00+0000', tz='UTC'))":170.0,"('AAPL', Timestamp('2023-10-30 21:40:00+0000', tz='UTC'))":169.9852,"('AAPL', Timestamp('2023-10-30 21:45:00+0000', tz='UTC'))":170.0,"('AAPL', Timestamp('2023-10-30 21:50:00+0000', tz='UTC'))":170.0,"('AAPL', Timestamp('2023-10-30 21:55:00+0000', tz='UTC'))":169.92,"('AAPL', Timestamp('2023-10-30 22:00:00+0000', tz='UTC'))":169.93,"('AAPL', Timestamp('2023-10-30 22:05:00+0000', tz='UTC'))":169.9,"('AAPL', Timestamp('2023-10-30 22:10:00+0000', tz='UTC'))":169.8506,"('AAPL', Timestamp('2023-10-30 22:15:00+0000', tz='UTC'))":169.86,"('AAPL', Timestamp('2023-10-30 22:20:00+0000', tz='UTC'))":169.8,"('AAPL', Timestamp('2023-10-30 22:25:00+0000', tz='UTC'))":169.81,"('AAPL', Timestamp('2023-10-30 22:30:00+0000', tz='UTC'))":169.84,"('AAPL', Timestamp('2023-10-30 22:35:00+0000', tz='UTC'))":169.83,"('AAPL', Timestamp('2023-10-30 22:40:00+0000', tz='UTC'))":169.86,"('AAPL', Timestamp('2023-10-30 22:50:00+0000', tz='UTC'))":169.82,"('AAPL', Timestamp('2023-10-30 22:55:00+0000', tz='UTC'))":169.8699,"('AAPL', Timestamp('2023-10-30 23:00:00+0000', tz='UTC'))":169.87,"('AAPL', Timestamp('2023-10-30 23:05:00+0000', tz='UTC'))":169.85,"('AAPL', Timestamp('2023-10-30 23:10:00+0000', tz='UTC'))":169.82,"('AAPL', Timestamp('2023-10-30 23:15:00+0000', tz='UTC'))":169.85,"('AAPL', Timestamp('2023-10-30 23:20:00+0000', tz='UTC'))":169.86,"('AAPL', Timestamp('2023-10-30 23:25:00+0000', tz='UTC'))":169.85,"('AAPL', Timestamp('2023-10-30 23:30:00+0000', tz='UTC'))":169.82,"('AAPL', Timestamp('2023-10-30 23:35:00+0000', tz='UTC'))":169.83,"('AAPL', Timestamp('2023-10-30 23:40:00+0000', tz='UTC'))":169.8199,"('AAPL', Timestamp('2023-10-30 23:45:00+0000', tz='UTC'))":169.71,"('AAPL', Timestamp('2023-10-30 23:50:00+0000', tz='UTC'))":169.72},"close":{"('AAPL', Timestamp('2023-10-30 08:00:00+0000', tz='UTC'))":168.88,"('AAPL', Timestamp('2023-10-30 08:05:00+0000', tz='UTC'))":169.0,"('AAPL', Timestamp('2023-10-30 08:10:00+0000', tz='UTC'))":168.9,"('AAPL', Timestamp('2023-10-30 08:15:00+0000', tz='UTC'))":169.0,"('AAPL', Timestamp('2023-10-30 08:20:00+0000', tz='UTC'))":168.92,"('AAPL', Timestamp('2023-10-30 08:25:00+0000', tz='UTC'))":168.85,"('AAPL', Timestamp('2023-10-30 08:35:00+0000', tz='UTC'))":168.85,"('AAPL', Timestamp('2023-10-30 08:40:00+0000', tz='UTC'))":168.85,"('AAPL', Timestamp('2023-10-30 08:45:00+0000', tz='UTC'))":168.71,"('AAPL', Timestamp('2023-10-30 08:50:00+0000', tz='UTC'))":168.99,"('AAPL', Timestamp('2023-10-30 09:00:00+0000', tz='UTC'))":169.09,"('AAPL', Timestamp('2023-10-30 09:05:00+0000', tz='UTC'))":169.2,"('AAPL', Timestamp('2023-10-30 09:10:00+0000', tz='UTC'))":169.23,"('AAPL', Timestamp('2023-10-30 09:15:00+0000', tz='UTC'))":169.47,"('AAPL', Timestamp('2023-10-30 09:20:00+0000', tz='UTC'))":169.25,"('AAPL', Timestamp('2023-10-30 09:25:00+0000', tz='UTC'))":169.2,"('AAPL', Timestamp('2023-10-30 09:30:00+0000', tz='UTC'))":169.25,"('AAPL', Timestamp('2023-10-30 09:35:00+0000', tz='UTC'))":168.96,"('AAPL', Timestamp('2023-10-30 09:40:00+0000', tz='UTC'))":169.1,"('AAPL', Timestamp('2023-10-30 09:45:00+0000', tz='UTC'))":169.11,"('AAPL', Timestamp('2023-10-30 09:50:00+0000', tz='UTC'))":169.14,"('AAPL', Timestamp('2023-10-30 09:55:00+0000', tz='UTC'))":169.16,"('AAPL', Timestamp('2023-10-30 10:05:00+0000', tz='UTC'))":169.13,"('AAPL', Timestamp('2023-10-30 10:10:00+0000', tz='UTC'))":169.12,"('AAPL', Timestamp('2023-10-30 10:15:00+0000', tz='UTC'))":169.02,"('AAPL', Timestamp('2023-10-30 10:20:00+0000', tz='UTC'))":169.0,"('AAPL', Timestamp('2023-10-30 10:25:00+0000', tz='UTC'))":169.01,"('AAPL', Timestamp('2023-10-30 10:30:00+0000', tz='UTC'))":169.0,"('AAPL', Timestamp('2023-10-30 10:35:00+0000', tz='UTC'))":169.01,"('AAPL', Timestamp('2023-10-30 10:45:00+0000', tz='UTC'))":169.0,"('AAPL', Timestamp('2023-10-30 10:50:00+0000', tz='UTC'))":169.06,"('AAPL', Timestamp('2023-10-30 10:55:00+0000', tz='UTC'))":169.19,"('AAPL', Timestamp('2023-10-30 11:00:00+0000', tz='UTC'))":169.3,"('AAPL', Timestamp('2023-10-30 11:05:00+0000', tz='UTC'))":169.25,"('AAPL', Timestamp('2023-10-30 11:10:00+0000', tz='UTC'))":169.2,"('AAPL', Timestamp('2023-10-30 11:15:00+0000', tz='UTC'))":169.23,"('AAPL', Timestamp('2023-10-30 11:20:00+0000', tz='UTC'))":169.18,"('AAPL', Timestamp('2023-10-30 11:25:00+0000', tz='UTC'))":169.1,"('AAPL', Timestamp('2023-10-30 11:30:00+0000', tz='UTC'))":169.21,"('AAPL', Timestamp('2023-10-30 11:35:00+0000', tz='UTC'))":169.21,"('AAPL', Timestamp('2023-10-30 11:40:00+0000', tz='UTC'))":169.2,"('AAPL', Timestamp('2023-10-30 11:45:00+0000', tz='UTC'))":169.28,"('AAPL', Timestamp('2023-10-30 11:50:00+0000', tz='UTC'))":169.18,"('AAPL', Timestamp('2023-10-30 11:55:00+0000', tz='UTC'))":169.16,"('AAPL', Timestamp('2023-10-30 12:00:00+0000', tz='UTC'))":169.02,"('AAPL', Timestamp('2023-10-30 12:05:00+0000', tz='UTC'))":169.0,"('AAPL', Timestamp('2023-10-30 12:10:00+0000', tz='UTC'))":168.93,"('AAPL', Timestamp('2023-10-30 12:15:00+0000', tz='UTC'))":168.76,"('AAPL', Timestamp('2023-10-30 12:20:00+0000', tz='UTC'))":168.5,"('AAPL', Timestamp('2023-10-30 12:25:00+0000', tz='UTC'))":168.73,"('AAPL', Timestamp('2023-10-30 12:30:00+0000', tz='UTC'))":168.97,"('AAPL', Timestamp('2023-10-30 12:35:00+0000', tz='UTC'))":168.65,"('AAPL', Timestamp('2023-10-30 12:40:00+0000', tz='UTC'))":168.55,"('AAPL', Timestamp('2023-10-30 12:45:00+0000', tz='UTC'))":168.5,"('AAPL', Timestamp('2023-10-30 12:50:00+0000', tz='UTC'))":168.35,"('AAPL', Timestamp('2023-10-30 12:55:00+0000', tz='UTC'))":168.58,"('AAPL', Timestamp('2023-10-30 13:00:00+0000', tz='UTC'))":168.7,"('AAPL', Timestamp('2023-10-30 13:05:00+0000', tz='UTC'))":168.75,"('AAPL', Timestamp('2023-10-30 13:10:00+0000', tz='UTC'))":168.53,"('AAPL', Timestamp('2023-10-30 13:15:00+0000', tz='UTC'))":168.65,"('AAPL', Timestamp('2023-10-30 13:20:00+0000', tz='UTC'))":168.7,"('AAPL', Timestamp('2023-10-30 13:25:00+0000', tz='UTC'))":169.06,"('AAPL', Timestamp('2023-10-30 13:30:00+0000', tz='UTC'))":170.01,"('AAPL', Timestamp('2023-10-30 13:35:00+0000', tz='UTC'))":170.738,"('AAPL', Timestamp('2023-10-30 13:40:00+0000', tz='UTC'))":170.8939,"('AAPL', Timestamp('2023-10-30 13:45:00+0000', tz='UTC'))":170.98,"('AAPL', Timestamp('2023-10-30 13:50:00+0000', tz='UTC'))":170.65,"('AAPL', Timestamp('2023-10-30 13:55:00+0000', tz='UTC'))":170.615,"('AAPL', Timestamp('2023-10-30 14:00:00+0000', tz='UTC'))":170.3969,"('AAPL', Timestamp('2023-10-30 14:05:00+0000', tz='UTC'))":170.71,"('AAPL', Timestamp('2023-10-30 14:10:00+0000', tz='UTC'))":170.365,"('AAPL', Timestamp('2023-10-30 14:15:00+0000', tz='UTC'))":169.81,"('AAPL', Timestamp('2023-10-30 14:20:00+0000', tz='UTC'))":169.56,"('AAPL', Timestamp('2023-10-30 14:25:00+0000', tz='UTC'))":169.4,"('AAPL', Timestamp('2023-10-30 14:30:00+0000', tz='UTC'))":169.57,"('AAPL', Timestamp('2023-10-30 14:35:00+0000', tz='UTC'))":169.7488,"('AAPL', Timestamp('2023-10-30 14:40:00+0000', tz='UTC'))":169.53,"('AAPL', Timestamp('2023-10-30 14:45:00+0000', tz='UTC'))":169.68,"('AAPL', Timestamp('2023-10-30 14:50:00+0000', tz='UTC'))":169.99,"('AAPL', Timestamp('2023-10-30 14:55:00+0000', tz='UTC'))":169.4414,"('AAPL', Timestamp('2023-10-30 15:00:00+0000', tz='UTC'))":169.94,"('AAPL', Timestamp('2023-10-30 15:05:00+0000', tz='UTC'))":169.9634,"('AAPL', Timestamp('2023-10-30 15:10:00+0000', tz='UTC'))":169.88,"('AAPL', Timestamp('2023-10-30 15:15:00+0000', tz='UTC'))":170.065,"('AAPL', Timestamp('2023-10-30 15:20:00+0000', tz='UTC'))":169.6,"('AAPL', Timestamp('2023-10-30 15:25:00+0000', tz='UTC'))":169.67,"('AAPL', Timestamp('2023-10-30 15:30:00+0000', tz='UTC'))":170.05,"('AAPL', Timestamp('2023-10-30 15:35:00+0000', tz='UTC'))":169.71,"('AAPL', Timestamp('2023-10-30 15:40:00+0000', tz='UTC'))":169.77,"('AAPL', Timestamp('2023-10-30 15:45:00+0000', tz='UTC'))":169.722,"('AAPL', Timestamp('2023-10-30 15:50:00+0000', tz='UTC'))":169.8812,"('AAPL', Timestamp('2023-10-30 15:55:00+0000', tz='UTC'))":169.92,"('AAPL', Timestamp('2023-10-30 16:00:00+0000', tz='UTC'))":169.86,"('AAPL', Timestamp('2023-10-30 16:05:00+0000', tz='UTC'))":169.69,"('AAPL', Timestamp('2023-10-30 16:10:00+0000', tz='UTC'))":169.85,"('AAPL', Timestamp('2023-10-30 16:15:00+0000', tz='UTC'))":169.52,"('AAPL', Timestamp('2023-10-30 16:20:00+0000', tz='UTC'))":169.46,"('AAPL', Timestamp('2023-10-30 16:25:00+0000', tz='UTC'))":169.4661,"('AAPL', Timestamp('2023-10-30 16:30:00+0000', tz='UTC'))":169.535,"('AAPL', Timestamp('2023-10-30 16:35:00+0000', tz='UTC'))":169.44,"('AAPL', Timestamp('2023-10-30 16:40:00+0000', tz='UTC'))":169.18,"('AAPL', Timestamp('2023-10-30 16:45:00+0000', tz='UTC'))":169.34,"('AAPL', Timestamp('2023-10-30 16:50:00+0000', tz='UTC'))":169.14,"('AAPL', Timestamp('2023-10-30 16:55:00+0000', tz='UTC'))":169.37,"('AAPL', Timestamp('2023-10-30 17:00:00+0000', tz='UTC'))":169.39,"('AAPL', Timestamp('2023-10-30 17:05:00+0000', tz='UTC'))":169.54,"('AAPL', Timestamp('2023-10-30 17:10:00+0000', tz='UTC'))":169.37,"('AAPL', Timestamp('2023-10-30 17:15:00+0000', tz='UTC'))":169.325,"('AAPL', Timestamp('2023-10-30 17:20:00+0000', tz='UTC'))":169.676,"('AAPL', Timestamp('2023-10-30 17:25:00+0000', tz='UTC'))":169.9199,"('AAPL', Timestamp('2023-10-30 17:30:00+0000', tz='UTC'))":170.05,"('AAPL', Timestamp('2023-10-30 17:35:00+0000', tz='UTC'))":169.965,"('AAPL', Timestamp('2023-10-30 17:40:00+0000', tz='UTC'))":170.05,"('AAPL', Timestamp('2023-10-30 17:45:00+0000', tz='UTC'))":170.28,"('AAPL', Timestamp('2023-10-30 17:50:00+0000', tz='UTC'))":170.28,"('AAPL', Timestamp('2023-10-30 17:55:00+0000', tz='UTC'))":170.2801,"('AAPL', Timestamp('2023-10-30 18:00:00+0000', tz='UTC'))":170.43,"('AAPL', Timestamp('2023-10-30 18:05:00+0000', tz='UTC'))":170.4002,"('AAPL', Timestamp('2023-10-30 18:10:00+0000', tz='UTC'))":170.27,"('AAPL', Timestamp('2023-10-30 18:15:00+0000', tz='UTC'))":170.2814,"('AAPL', Timestamp('2023-10-30 18:20:00+0000', tz='UTC'))":170.32,"('AAPL', Timestamp('2023-10-30 18:25:00+0000', tz='UTC'))":170.36,"('AAPL', Timestamp('2023-10-30 18:30:00+0000', tz='UTC'))":170.44,"('AAPL', Timestamp('2023-10-30 18:35:00+0000', tz='UTC'))":170.535,"('AAPL', Timestamp('2023-10-30 18:40:00+0000', tz='UTC'))":170.7499,"('AAPL', Timestamp('2023-10-30 18:45:00+0000', tz='UTC'))":170.72,"('AAPL', Timestamp('2023-10-30 18:50:00+0000', tz='UTC'))":170.66,"('AAPL', Timestamp('2023-10-30 18:55:00+0000', tz='UTC'))":170.5,"('AAPL', Timestamp('2023-10-30 19:00:00+0000', tz='UTC'))":170.35,"('AAPL', Timestamp('2023-10-30 19:05:00+0000', tz='UTC'))":170.25,"('AAPL', Timestamp('2023-10-30 19:10:00+0000', tz='UTC'))":170.12,"('AAPL', Timestamp('2023-10-30 19:15:00+0000', tz='UTC'))":170.115,"('AAPL', Timestamp('2023-10-30 19:20:00+0000', tz='UTC'))":170.2,"('AAPL', Timestamp('2023-10-30 19:25:00+0000', tz='UTC'))":169.855,"('AAPL', Timestamp('2023-10-30 19:30:00+0000', tz='UTC'))":169.9336,"('AAPL', Timestamp('2023-10-30 19:35:00+0000', tz='UTC'))":170.15,"('AAPL', Timestamp('2023-10-30 19:40:00+0000', tz='UTC'))":170.2,"('AAPL', Timestamp('2023-10-30 19:45:00+0000', tz='UTC'))":170.315,"('AAPL', Timestamp('2023-10-30 19:50:00+0000', tz='UTC'))":170.335,"('AAPL', Timestamp('2023-10-30 19:55:00+0000', tz='UTC'))":170.23,"('AAPL', Timestamp('2023-10-30 20:00:00+0000', tz='UTC'))":170.04,"('AAPL', Timestamp('2023-10-30 20:05:00+0000', tz='UTC'))":170.08,"('AAPL', Timestamp('2023-10-30 20:10:00+0000', tz='UTC'))":170.02,"('AAPL', Timestamp('2023-10-30 20:15:00+0000', tz='UTC'))":169.95,"('AAPL', Timestamp('2023-10-30 20:20:00+0000', tz='UTC'))":170.08,"('AAPL', Timestamp('2023-10-30 20:25:00+0000', tz='UTC'))":170.07,"('AAPL', Timestamp('2023-10-30 20:30:00+0000', tz='UTC'))":170.0,"('AAPL', Timestamp('2023-10-30 20:35:00+0000', tz='UTC'))":170.29,"('AAPL', Timestamp('2023-10-30 20:40:00+0000', tz='UTC'))":169.93,"('AAPL', Timestamp('2023-10-30 20:45:00+0000', tz='UTC'))":169.99,"('AAPL', Timestamp('2023-10-30 20:50:00+0000', tz='UTC'))":169.97,"('AAPL', Timestamp('2023-10-30 20:55:00+0000', tz='UTC'))":169.96,"('AAPL', Timestamp('2023-10-30 21:00:00+0000', tz='UTC'))":170.0299,"('AAPL', Timestamp('2023-10-30 21:05:00+0000', tz='UTC'))":169.98,"('AAPL', Timestamp('2023-10-30 21:10:00+0000', tz='UTC'))":169.95,"('AAPL', Timestamp('2023-10-30 21:15:00+0000', tz='UTC'))":169.96,"('AAPL', Timestamp('2023-10-30 21:20:00+0000', tz='UTC'))":170.0182,"('AAPL', Timestamp('2023-10-30 21:25:00+0000', tz='UTC'))":170.05,"('AAPL', Timestamp('2023-10-30 21:30:00+0000', tz='UTC'))":170.0,"('AAPL', Timestamp('2023-10-30 21:35:00+0000', tz='UTC'))":170.02,"('AAPL', Timestamp('2023-10-30 21:40:00+0000', tz='UTC'))":169.9852,"('AAPL', Timestamp('2023-10-30 21:45:00+0000', tz='UTC'))":170.0,"('AAPL', Timestamp('2023-10-30 21:50:00+0000', tz='UTC'))":170.0,"('AAPL', Timestamp('2023-10-30 21:55:00+0000', tz='UTC'))":169.92,"('AAPL', Timestamp('2023-10-30 22:00:00+0000', tz='UTC'))":169.93,"('AAPL', Timestamp('2023-10-30 22:05:00+0000', tz='UTC'))":169.9,"('AAPL', Timestamp('2023-10-30 22:10:00+0000', tz='UTC'))":169.95,"('AAPL', Timestamp('2023-10-30 22:15:00+0000', tz='UTC'))":169.9,"('AAPL', Timestamp('2023-10-30 22:20:00+0000', tz='UTC'))":169.8,"('AAPL', Timestamp('2023-10-30 22:25:00+0000', tz='UTC'))":169.81,"('AAPL', Timestamp('2023-10-30 22:30:00+0000', tz='UTC'))":169.87,"('AAPL', Timestamp('2023-10-30 22:35:00+0000', tz='UTC'))":169.85,"('AAPL', Timestamp('2023-10-30 22:40:00+0000', tz='UTC'))":169.9,"('AAPL', Timestamp('2023-10-30 22:50:00+0000', tz='UTC'))":169.9,"('AAPL', Timestamp('2023-10-30 22:55:00+0000', tz='UTC'))":169.8699,"('AAPL', Timestamp('2023-10-30 23:00:00+0000', tz='UTC'))":169.91,"('AAPL', Timestamp('2023-10-30 23:05:00+0000', tz='UTC'))":169.89,"('AAPL', Timestamp('2023-10-30 23:10:00+0000', tz='UTC'))":169.82,"('AAPL', Timestamp('2023-10-30 23:15:00+0000', tz='UTC'))":169.87,"('AAPL', Timestamp('2023-10-30 23:20:00+0000', tz='UTC'))":169.86,"('AAPL', Timestamp('2023-10-30 23:25:00+0000', tz='UTC'))":169.85,"('AAPL', Timestamp('2023-10-30 23:30:00+0000', tz='UTC'))":169.86,"('AAPL', Timestamp('2023-10-30 23:35:00+0000', tz='UTC'))":169.83,"('AAPL', Timestamp('2023-10-30 23:40:00+0000', tz='UTC'))":169.8199,"('AAPL', Timestamp('2023-10-30 23:45:00+0000', tz='UTC'))":169.76,"('AAPL', Timestamp('2023-10-30 23:50:00+0000', tz='UTC'))":169.84},"volume":{"('AAPL', Timestamp('2023-10-30 08:00:00+0000', tz='UTC'))":7357.0,"('AAPL', Timestamp('2023-10-30 08:05:00+0000', tz='UTC'))":6812.0,"('AAPL', Timestamp('2023-10-30 08:10:00+0000', tz='UTC'))":1134.0,"('AAPL', Timestamp('2023-10-30 08:15:00+0000', tz='UTC'))":1423.0,"('AAPL', Timestamp('2023-10-30 08:20:00+0000', tz='UTC'))":2556.0,"('AAPL', Timestamp('2023-10-30 08:25:00+0000', tz='UTC'))":1270.0,"('AAPL', Timestamp('2023-10-30 08:35:00+0000', tz='UTC'))":688.0,"('AAPL', Timestamp('2023-10-30 08:40:00+0000', tz='UTC'))":3223.0,"('AAPL', Timestamp('2023-10-30 08:45:00+0000', tz='UTC'))":1350.0,"('AAPL', Timestamp('2023-10-30 08:50:00+0000', tz='UTC'))":2834.0,"('AAPL', Timestamp('2023-10-30 09:00:00+0000', tz='UTC'))":1346.0,"('AAPL', Timestamp('2023-10-30 09:05:00+0000', tz='UTC'))":3089.0,"('AAPL', Timestamp('2023-10-30 09:10:00+0000', tz='UTC'))":806.0,"('AAPL', Timestamp('2023-10-30 09:15:00+0000', tz='UTC'))":947.0,"('AAPL', Timestamp('2023-10-30 09:20:00+0000', tz='UTC'))":3091.0,"('AAPL', Timestamp('2023-10-30 09:25:00+0000', tz='UTC'))":2164.0,"('AAPL', Timestamp('2023-10-30 09:30:00+0000', tz='UTC'))":433.0,"('AAPL', Timestamp('2023-10-30 09:35:00+0000', tz='UTC'))":3842.0,"('AAPL', Timestamp('2023-10-30 09:40:00+0000', tz='UTC'))":947.0,"('AAPL', Timestamp('2023-10-30 09:45:00+0000', tz='UTC'))":273.0,"('AAPL', Timestamp('2023-10-30 09:50:00+0000', tz='UTC'))":325.0,"('AAPL', Timestamp('2023-10-30 09:55:00+0000', tz='UTC'))":240.0,"('AAPL', Timestamp('2023-10-30 10:05:00+0000', tz='UTC'))":2183.0,"('AAPL', Timestamp('2023-10-30 10:10:00+0000', tz='UTC'))":3008.0,"('AAPL', Timestamp('2023-10-30 10:15:00+0000', tz='UTC'))":5492.0,"('AAPL', Timestamp('2023-10-30 10:20:00+0000', tz='UTC'))":3081.0,"('AAPL', Timestamp('2023-10-30 10:25:00+0000', tz='UTC'))":4778.0,"('AAPL', Timestamp('2023-10-30 10:30:00+0000', tz='UTC'))":3629.0,"('AAPL', Timestamp('2023-10-30 10:35:00+0000', tz='UTC'))":621.0,"('AAPL', Timestamp('2023-10-30 10:45:00+0000', tz='UTC'))":4133.0,"('AAPL', Timestamp('2023-10-30 10:50:00+0000', tz='UTC'))":7639.0,"('AAPL', Timestamp('2023-10-30 10:55:00+0000', tz='UTC'))":12847.0,"('AAPL', Timestamp('2023-10-30 11:00:00+0000', tz='UTC'))":7432.0,"('AAPL', Timestamp('2023-10-30 11:05:00+0000', tz='UTC'))":3606.0,"('AAPL', Timestamp('2023-10-30 11:10:00+0000', tz='UTC'))":2284.0,"('AAPL', Timestamp('2023-10-30 11:15:00+0000', tz='UTC'))":894.0,"('AAPL', Timestamp('2023-10-30 11:20:00+0000', tz='UTC'))":8185.0,"('AAPL', Timestamp('2023-10-30 11:25:00+0000', tz='UTC'))":3376.0,"('AAPL', Timestamp('2023-10-30 11:30:00+0000', tz='UTC'))":3614.0,"('AAPL', Timestamp('2023-10-30 11:35:00+0000', tz='UTC'))":584.0,"('AAPL', Timestamp('2023-10-30 11:40:00+0000', tz='UTC'))":362.0,"('AAPL', Timestamp('2023-10-30 11:45:00+0000', tz='UTC'))":5041.0,"('AAPL', Timestamp('2023-10-30 11:50:00+0000', tz='UTC'))":4928.0,"('AAPL', Timestamp('2023-10-30 11:55:00+0000', tz='UTC'))":3663.0,"('AAPL', Timestamp('2023-10-30 12:00:00+0000', tz='UTC'))":52038.0,"('AAPL', Timestamp('2023-10-30 12:05:00+0000', tz='UTC'))":9042.0,"('AAPL', Timestamp('2023-10-30 12:10:00+0000', tz='UTC'))":12127.0,"('AAPL', Timestamp('2023-10-30 12:15:00+0000', tz='UTC'))":14406.0,"('AAPL', Timestamp('2023-10-30 12:20:00+0000', tz='UTC'))":21829.0,"('AAPL', Timestamp('2023-10-30 12:25:00+0000', tz='UTC'))":8306.0,"('AAPL', Timestamp('2023-10-30 12:30:00+0000', tz='UTC'))":7265.0,"('AAPL', Timestamp('2023-10-30 12:35:00+0000', tz='UTC'))":18404.0,"('AAPL', Timestamp('2023-10-30 12:40:00+0000', tz='UTC'))":10891.0,"('AAPL', Timestamp('2023-10-30 12:45:00+0000', tz='UTC'))":11454.0,"('AAPL', Timestamp('2023-10-30 12:50:00+0000', tz='UTC'))":10858.0,"('AAPL', Timestamp('2023-10-30 12:55:00+0000', tz='UTC'))":77248.0,"('AAPL', Timestamp('2023-10-30 13:00:00+0000', tz='UTC'))":4583.0,"('AAPL', Timestamp('2023-10-30 13:05:00+0000', tz='UTC'))":9926.0,"('AAPL', Timestamp('2023-10-30 13:10:00+0000', tz='UTC'))":17709.0,"('AAPL', Timestamp('2023-10-30 13:15:00+0000', tz='UTC'))":9501.0,"('AAPL', Timestamp('2023-10-30 13:20:00+0000', tz='UTC'))":10738.0,"('AAPL', Timestamp('2023-10-30 13:25:00+0000', tz='UTC'))":63142.0,"('AAPL', Timestamp('2023-10-30 13:30:00+0000', tz='UTC'))":2051778.0,"('AAPL', Timestamp('2023-10-30 13:35:00+0000', tz='UTC'))":1505247.0,"('AAPL', Timestamp('2023-10-30 13:40:00+0000', tz='UTC'))":1066279.0,"('AAPL', Timestamp('2023-10-30 13:45:00+0000', tz='UTC'))":1116241.0,"('AAPL', Timestamp('2023-10-30 13:50:00+0000', tz='UTC'))":951494.0,"('AAPL', Timestamp('2023-10-30 13:55:00+0000', tz='UTC'))":739139.0,"('AAPL', Timestamp('2023-10-30 14:00:00+0000', tz='UTC'))":928302.0,"('AAPL', Timestamp('2023-10-30 14:05:00+0000', tz='UTC'))":534738.0,"('AAPL', Timestamp('2023-10-30 14:10:00+0000', tz='UTC'))":717865.0,"('AAPL', Timestamp('2023-10-30 14:15:00+0000', tz='UTC'))":964758.0,"('AAPL', Timestamp('2023-10-30 14:20:00+0000', tz='UTC'))":911973.0,"('AAPL', Timestamp('2023-10-30 14:25:00+0000', tz='UTC'))":641947.0,"('AAPL', Timestamp('2023-10-30 14:30:00+0000', tz='UTC'))":631672.0,"('AAPL', Timestamp('2023-10-30 14:35:00+0000', tz='UTC'))":731892.0,"('AAPL', Timestamp('2023-10-30 14:40:00+0000', tz='UTC'))":591377.0,"('AAPL', Timestamp('2023-10-30 14:45:00+0000', tz='UTC'))":762752.0,"('AAPL', Timestamp('2023-10-30 14:50:00+0000', tz='UTC'))":551528.0,"('AAPL', Timestamp('2023-10-30 14:55:00+0000', tz='UTC'))":726218.0,"('AAPL', Timestamp('2023-10-30 15:00:00+0000', tz='UTC'))":489051.0,"('AAPL', Timestamp('2023-10-30 15:05:00+0000', tz='UTC'))":424960.0,"('AAPL', Timestamp('2023-10-30 15:10:00+0000', tz='UTC'))":403512.0,"('AAPL', Timestamp('2023-10-30 15:15:00+0000', tz='UTC'))":370344.0,"('AAPL', Timestamp('2023-10-30 15:20:00+0000', tz='UTC'))":558091.0,"('AAPL', Timestamp('2023-10-30 15:25:00+0000', tz='UTC'))":454690.0,"('AAPL', Timestamp('2023-10-30 15:30:00+0000', tz='UTC'))":437045.0,"('AAPL', Timestamp('2023-10-30 15:35:00+0000', tz='UTC'))":492705.0,"('AAPL', Timestamp('2023-10-30 15:40:00+0000', tz='UTC'))":336730.0,"('AAPL', Timestamp('2023-10-30 15:45:00+0000', tz='UTC'))":261119.0,"('AAPL', Timestamp('2023-10-30 15:50:00+0000', tz='UTC'))":292475.0,"('AAPL', Timestamp('2023-10-30 15:55:00+0000', tz='UTC'))":194156.0,"('AAPL', Timestamp('2023-10-30 16:00:00+0000', tz='UTC'))":263662.0,"('AAPL', Timestamp('2023-10-30 16:05:00+0000', tz='UTC'))":236552.0,"('AAPL', Timestamp('2023-10-30 16:10:00+0000', tz='UTC'))":303658.0,"('AAPL', Timestamp('2023-10-30 16:15:00+0000', tz='UTC'))":312541.0,"('AAPL', Timestamp('2023-10-30 16:20:00+0000', tz='UTC'))":303444.0,"('AAPL', Timestamp('2023-10-30 16:25:00+0000', tz='UTC'))":273235.0,"('AAPL', Timestamp('2023-10-30 16:30:00+0000', tz='UTC'))":378543.0,"('AAPL', Timestamp('2023-10-30 16:35:00+0000', tz='UTC'))":225054.0,"('AAPL', Timestamp('2023-10-30 16:40:00+0000', tz='UTC'))":418782.0,"('AAPL', Timestamp('2023-10-30 16:45:00+0000', tz='UTC'))":282983.0,"('AAPL', Timestamp('2023-10-30 16:50:00+0000', tz='UTC'))":289407.0,"('AAPL', Timestamp('2023-10-30 16:55:00+0000', tz='UTC'))":452454.0,"('AAPL', Timestamp('2023-10-30 17:00:00+0000', tz='UTC'))":328790.0,"('AAPL', Timestamp('2023-10-30 17:05:00+0000', tz='UTC'))":368294.0,"('AAPL', Timestamp('2023-10-30 17:10:00+0000', tz='UTC'))":349788.0,"('AAPL', Timestamp('2023-10-30 17:15:00+0000', tz='UTC'))":292732.0,"('AAPL', Timestamp('2023-10-30 17:20:00+0000', tz='UTC'))":318730.0,"('AAPL', Timestamp('2023-10-30 17:25:00+0000', tz='UTC'))":772823.0,"('AAPL', Timestamp('2023-10-30 17:30:00+0000', tz='UTC'))":430780.0,"('AAPL', Timestamp('2023-10-30 17:35:00+0000', tz='UTC'))":294822.0,"('AAPL', Timestamp('2023-10-30 17:40:00+0000', tz='UTC'))":252192.0,"('AAPL', Timestamp('2023-10-30 17:45:00+0000', tz='UTC'))":364142.0,"('AAPL', Timestamp('2023-10-30 17:50:00+0000', tz='UTC'))":343967.0,"('AAPL', Timestamp('2023-10-30 17:55:00+0000', tz='UTC'))":332781.0,"('AAPL', Timestamp('2023-10-30 18:00:00+0000', tz='UTC'))":387053.0,"('AAPL', Timestamp('2023-10-30 18:05:00+0000', tz='UTC'))":475226.0,"('AAPL', Timestamp('2023-10-30 18:10:00+0000', tz='UTC'))":354875.0,"('AAPL', Timestamp('2023-10-30 18:15:00+0000', tz='UTC'))":365327.0,"('AAPL', Timestamp('2023-10-30 18:20:00+0000', tz='UTC'))":267851.0,"('AAPL', Timestamp('2023-10-30 18:25:00+0000', tz='UTC'))":363140.0,"('AAPL', Timestamp('2023-10-30 18:30:00+0000', tz='UTC'))":349127.0,"('AAPL', Timestamp('2023-10-30 18:35:00+0000', tz='UTC'))":454732.0,"('AAPL', Timestamp('2023-10-30 18:40:00+0000', tz='UTC'))":404466.0,"('AAPL', Timestamp('2023-10-30 18:45:00+0000', tz='UTC'))":421677.0,"('AAPL', Timestamp('2023-10-30 18:50:00+0000', tz='UTC'))":348299.0,"('AAPL', Timestamp('2023-10-30 18:55:00+0000', tz='UTC'))":408009.0,"('AAPL', Timestamp('2023-10-30 19:00:00+0000', tz='UTC'))":530212.0,"('AAPL', Timestamp('2023-10-30 19:05:00+0000', tz='UTC'))":573574.0,"('AAPL', Timestamp('2023-10-30 19:10:00+0000', tz='UTC'))":794446.0,"('AAPL', Timestamp('2023-10-30 19:15:00+0000', tz='UTC'))":532061.0,"('AAPL', Timestamp('2023-10-30 19:20:00+0000', tz='UTC'))":709892.0,"('AAPL', Timestamp('2023-10-30 19:25:00+0000', tz='UTC'))":581623.0,"('AAPL', Timestamp('2023-10-30 19:30:00+0000', tz='UTC'))":582443.0,"('AAPL', Timestamp('2023-10-30 19:35:00+0000', tz='UTC'))":654303.0,"('AAPL', Timestamp('2023-10-30 19:40:00+0000', tz='UTC'))":960704.0,"('AAPL', Timestamp('2023-10-30 19:45:00+0000', tz='UTC'))":845141.0,"('AAPL', Timestamp('2023-10-30 19:50:00+0000', tz='UTC'))":1195392.0,"('AAPL', Timestamp('2023-10-30 19:55:00+0000', tz='UTC'))":1756589.0,"('AAPL', Timestamp('2023-10-30 20:00:00+0000', tz='UTC'))":6466492.0,"('AAPL', Timestamp('2023-10-30 20:05:00+0000', tz='UTC'))":17379.0,"('AAPL', Timestamp('2023-10-30 20:10:00+0000', tz='UTC'))":27472.0,"('AAPL', Timestamp('2023-10-30 20:15:00+0000', tz='UTC'))":38697.0,"('AAPL', Timestamp('2023-10-30 20:20:00+0000', tz='UTC'))":47227.0,"('AAPL', Timestamp('2023-10-30 20:25:00+0000', tz='UTC'))":5031.0,"('AAPL', Timestamp('2023-10-30 20:30:00+0000', tz='UTC'))":6729.0,"('AAPL', Timestamp('2023-10-30 20:35:00+0000', tz='UTC'))":40479.0,"('AAPL', Timestamp('2023-10-30 20:40:00+0000', tz='UTC'))":2612.0,"('AAPL', Timestamp('2023-10-30 20:45:00+0000', tz='UTC'))":10731.0,"('AAPL', Timestamp('2023-10-30 20:50:00+0000', tz='UTC'))":3921.0,"('AAPL', Timestamp('2023-10-30 20:55:00+0000', tz='UTC'))":290.0,"('AAPL', Timestamp('2023-10-30 21:00:00+0000', tz='UTC'))":5287.0,"('AAPL', Timestamp('2023-10-30 21:05:00+0000', tz='UTC'))":1673.0,"('AAPL', Timestamp('2023-10-30 21:10:00+0000', tz='UTC'))":5266.0,"('AAPL', Timestamp('2023-10-30 21:15:00+0000', tz='UTC'))":888.0,"('AAPL', Timestamp('2023-10-30 21:20:00+0000', tz='UTC'))":2728.0,"('AAPL', Timestamp('2023-10-30 21:25:00+0000', tz='UTC'))":255609.0,"('AAPL', Timestamp('2023-10-30 21:30:00+0000', tz='UTC'))":609.0,"('AAPL', Timestamp('2023-10-30 21:35:00+0000', tz='UTC'))":1520.0,"('AAPL', Timestamp('2023-10-30 21:40:00+0000', tz='UTC'))":163.0,"('AAPL', Timestamp('2023-10-30 21:45:00+0000', tz='UTC'))":379.0,"('AAPL', Timestamp('2023-10-30 21:50:00+0000', tz='UTC'))":443.0,"('AAPL', Timestamp('2023-10-30 21:55:00+0000', tz='UTC'))":4241.0,"('AAPL', Timestamp('2023-10-30 22:00:00+0000', tz='UTC'))":1036.0,"('AAPL', Timestamp('2023-10-30 22:05:00+0000', tz='UTC'))":2300.0,"('AAPL', Timestamp('2023-10-30 22:10:00+0000', tz='UTC'))":3111.0,"('AAPL', Timestamp('2023-10-30 22:15:00+0000', tz='UTC'))":1488.0,"('AAPL', Timestamp('2023-10-30 22:20:00+0000', tz='UTC'))":2728.0,"('AAPL', Timestamp('2023-10-30 22:25:00+0000', tz='UTC'))":252.0,"('AAPL', Timestamp('2023-10-30 22:30:00+0000', tz='UTC'))":3084.0,"('AAPL', Timestamp('2023-10-30 22:35:00+0000', tz='UTC'))":911.0,"('AAPL', Timestamp('2023-10-30 22:40:00+0000', tz='UTC'))":2718.0,"('AAPL', Timestamp('2023-10-30 22:50:00+0000', tz='UTC'))":921.0,"('AAPL', Timestamp('2023-10-30 22:55:00+0000', tz='UTC'))":3139.0,"('AAPL', Timestamp('2023-10-30 23:00:00+0000', tz='UTC'))":1760.0,"('AAPL', Timestamp('2023-10-30 23:05:00+0000', tz='UTC'))":2114.0,"('AAPL', Timestamp('2023-10-30 23:10:00+0000', tz='UTC'))":1411.0,"('AAPL', Timestamp('2023-10-30 23:15:00+0000', tz='UTC'))":1274.0,"('AAPL', Timestamp('2023-10-30 23:20:00+0000', tz='UTC'))":1760.0,"('AAPL', Timestamp('2023-10-30 23:25:00+0000', tz='UTC'))":416.0,"('AAPL', Timestamp('2023-10-30 23:30:00+0000', tz='UTC'))":2900.0,"('AAPL', Timestamp('2023-10-30 23:35:00+0000', tz='UTC'))":2730.0,"('AAPL', Timestamp('2023-10-30 23:40:00+0000', tz='UTC'))":3033.0,"('AAPL', Timestamp('2023-10-30 23:45:00+0000', tz='UTC'))":6174.0,"('AAPL', Timestamp('2023-10-30 23:50:00+0000', tz='UTC'))":3478.0},"trade_count":{"('AAPL', Timestamp('2023-10-30 08:00:00+0000', tz='UTC'))":209.0,"('AAPL', Timestamp('2023-10-30 08:05:00+0000', tz='UTC'))":143.0,"('AAPL', Timestamp('2023-10-30 08:10:00+0000', tz='UTC'))":39.0,"('AAPL', Timestamp('2023-10-30 08:15:00+0000', tz='UTC'))":38.0,"('AAPL', Timestamp('2023-10-30 08:20:00+0000', tz='UTC'))":31.0,"('AAPL', Timestamp('2023-10-30 08:25:00+0000', tz='UTC'))":36.0,"('AAPL', Timestamp('2023-10-30 08:35:00+0000', tz='UTC'))":11.0,"('AAPL', Timestamp('2023-10-30 08:40:00+0000', tz='UTC'))":61.0,"('AAPL', Timestamp('2023-10-30 08:45:00+0000', tz='UTC'))":28.0,"('AAPL', Timestamp('2023-10-30 08:50:00+0000', tz='UTC'))":53.0,"('AAPL', Timestamp('2023-10-30 09:00:00+0000', tz='UTC'))":48.0,"('AAPL', Timestamp('2023-10-30 09:05:00+0000', tz='UTC'))":49.0,"('AAPL', Timestamp('2023-10-30 09:10:00+0000', tz='UTC'))":14.0,"('AAPL', Timestamp('2023-10-30 09:15:00+0000', tz='UTC'))":24.0,"('AAPL', Timestamp('2023-10-30 09:20:00+0000', tz='UTC'))":80.0,"('AAPL', Timestamp('2023-10-30 09:25:00+0000', tz='UTC'))":30.0,"('AAPL', Timestamp('2023-10-30 09:30:00+0000', tz='UTC'))":9.0,"('AAPL', Timestamp('2023-10-30 09:35:00+0000', tz='UTC'))":88.0,"('AAPL', Timestamp('2023-10-30 09:40:00+0000', tz='UTC'))":13.0,"('AAPL', Timestamp('2023-10-30 09:45:00+0000', tz='UTC'))":6.0,"('AAPL', Timestamp('2023-10-30 09:50:00+0000', tz='UTC'))":10.0,"('AAPL', Timestamp('2023-10-30 09:55:00+0000', tz='UTC'))":9.0,"('AAPL', Timestamp('2023-10-30 10:05:00+0000', tz='UTC'))":32.0,"('AAPL', Timestamp('2023-10-30 10:10:00+0000', tz='UTC'))":37.0,"('AAPL', Timestamp('2023-10-30 10:15:00+0000', tz='UTC'))":130.0,"('AAPL', Timestamp('2023-10-30 10:20:00+0000', tz='UTC'))":25.0,"('AAPL', Timestamp('2023-10-30 10:25:00+0000', tz='UTC'))":75.0,"('AAPL', Timestamp('2023-10-30 10:30:00+0000', tz='UTC'))":32.0,"('AAPL', Timestamp('2023-10-30 10:35:00+0000', tz='UTC'))":16.0,"('AAPL', Timestamp('2023-10-30 10:45:00+0000', tz='UTC'))":105.0,"('AAPL', Timestamp('2023-10-30 10:50:00+0000', tz='UTC'))":116.0,"('AAPL', Timestamp('2023-10-30 10:55:00+0000', tz='UTC'))":53.0,"('AAPL', Timestamp('2023-10-30 11:00:00+0000', tz='UTC'))":191.0,"('AAPL', Timestamp('2023-10-30 11:05:00+0000', tz='UTC'))":80.0,"('AAPL', Timestamp('2023-10-30 11:10:00+0000', tz='UTC'))":58.0,"('AAPL', Timestamp('2023-10-30 11:15:00+0000', tz='UTC'))":29.0,"('AAPL', Timestamp('2023-10-30 11:20:00+0000', tz='UTC'))":129.0,"('AAPL', Timestamp('2023-10-30 11:25:00+0000', tz='UTC'))":82.0,"('AAPL', Timestamp('2023-10-30 11:30:00+0000', tz='UTC'))":76.0,"('AAPL', Timestamp('2023-10-30 11:35:00+0000', tz='UTC'))":17.0,"('AAPL', Timestamp('2023-10-30 11:40:00+0000', tz='UTC'))":11.0,"('AAPL', Timestamp('2023-10-30 11:45:00+0000', tz='UTC'))":135.0,"('AAPL', Timestamp('2023-10-30 11:50:00+0000', tz='UTC'))":59.0,"('AAPL', Timestamp('2023-10-30 11:55:00+0000', tz='UTC'))":96.0,"('AAPL', Timestamp('2023-10-30 12:00:00+0000', tz='UTC'))":1492.0,"('AAPL', Timestamp('2023-10-30 12:05:00+0000', tz='UTC'))":244.0,"('AAPL', Timestamp('2023-10-30 12:10:00+0000', tz='UTC'))":208.0,"('AAPL', Timestamp('2023-10-30 12:15:00+0000', tz='UTC'))":384.0,"('AAPL', Timestamp('2023-10-30 12:20:00+0000', tz='UTC'))":560.0,"('AAPL', Timestamp('2023-10-30 12:25:00+0000', tz='UTC'))":197.0,"('AAPL', Timestamp('2023-10-30 12:30:00+0000', tz='UTC'))":201.0,"('AAPL', Timestamp('2023-10-30 12:35:00+0000', tz='UTC'))":406.0,"('AAPL', Timestamp('2023-10-30 12:40:00+0000', tz='UTC'))":272.0,"('AAPL', Timestamp('2023-10-30 12:45:00+0000', tz='UTC'))":244.0,"('AAPL', Timestamp('2023-10-30 12:50:00+0000', tz='UTC'))":261.0,"('AAPL', Timestamp('2023-10-30 12:55:00+0000', tz='UTC'))":528.0,"('AAPL', Timestamp('2023-10-30 13:00:00+0000', tz='UTC'))":179.0,"('AAPL', Timestamp('2023-10-30 13:05:00+0000', tz='UTC'))":231.0,"('AAPL', Timestamp('2023-10-30 13:10:00+0000', tz='UTC'))":544.0,"('AAPL', Timestamp('2023-10-30 13:15:00+0000', tz='UTC'))":328.0,"('AAPL', Timestamp('2023-10-30 13:20:00+0000', tz='UTC'))":293.0,"('AAPL', Timestamp('2023-10-30 13:25:00+0000', tz='UTC'))":1115.0,"('AAPL', Timestamp('2023-10-30 13:30:00+0000', tz='UTC'))":21036.0,"('AAPL', Timestamp('2023-10-30 13:35:00+0000', tz='UTC'))":15448.0,"('AAPL', Timestamp('2023-10-30 13:40:00+0000', tz='UTC'))":11315.0,"('AAPL', Timestamp('2023-10-30 13:45:00+0000', tz='UTC'))":21239.0,"('AAPL', Timestamp('2023-10-30 13:50:00+0000', tz='UTC'))":24655.0,"('AAPL', Timestamp('2023-10-30 13:55:00+0000', tz='UTC'))":20786.0,"('AAPL', Timestamp('2023-10-30 14:00:00+0000', tz='UTC'))":21641.0,"('AAPL', Timestamp('2023-10-30 14:05:00+0000', tz='UTC'))":16401.0,"('AAPL', Timestamp('2023-10-30 14:10:00+0000', tz='UTC'))":19155.0,"('AAPL', Timestamp('2023-10-30 14:15:00+0000', tz='UTC'))":19835.0,"('AAPL', Timestamp('2023-10-30 14:20:00+0000', tz='UTC'))":21468.0,"('AAPL', Timestamp('2023-10-30 14:25:00+0000', tz='UTC'))":17311.0,"('AAPL', Timestamp('2023-10-30 14:30:00+0000', tz='UTC'))":18251.0,"('AAPL', Timestamp('2023-10-30 14:35:00+0000', tz='UTC'))":19229.0,"('AAPL', Timestamp('2023-10-30 14:40:00+0000', tz='UTC'))":18312.0,"('AAPL', Timestamp('2023-10-30 14:45:00+0000', tz='UTC'))":17348.0,"('AAPL', Timestamp('2023-10-30 14:50:00+0000', tz='UTC'))":6427.0,"('AAPL', Timestamp('2023-10-30 14:55:00+0000', tz='UTC'))":6023.0,"('AAPL', Timestamp('2023-10-30 15:00:00+0000', tz='UTC'))":5670.0,"('AAPL', Timestamp('2023-10-30 15:05:00+0000', tz='UTC'))":4547.0,"('AAPL', Timestamp('2023-10-30 15:10:00+0000', tz='UTC'))":4990.0,"('AAPL', Timestamp('2023-10-30 15:15:00+0000', tz='UTC'))":5066.0,"('AAPL', Timestamp('2023-10-30 15:20:00+0000', tz='UTC'))":6031.0,"('AAPL', Timestamp('2023-10-30 15:25:00+0000', tz='UTC'))":4920.0,"('AAPL', Timestamp('2023-10-30 15:30:00+0000', tz='UTC'))":4983.0,"('AAPL', Timestamp('2023-10-30 15:35:00+0000', tz='UTC'))":4883.0,"('AAPL', Timestamp('2023-10-30 15:40:00+0000', tz='UTC'))":3986.0,"('AAPL', Timestamp('2023-10-30 15:45:00+0000', tz='UTC'))":3564.0,"('AAPL', Timestamp('2023-10-30 15:50:00+0000', tz='UTC'))":3555.0,"('AAPL', Timestamp('2023-10-30 15:55:00+0000', tz='UTC'))":3220.0,"('AAPL', Timestamp('2023-10-30 16:00:00+0000', tz='UTC'))":4113.0,"('AAPL', Timestamp('2023-10-30 16:05:00+0000', tz='UTC'))":3091.0,"('AAPL', Timestamp('2023-10-30 16:10:00+0000', tz='UTC'))":3606.0,"('AAPL', Timestamp('2023-10-30 16:15:00+0000', tz='UTC'))":4113.0,"('AAPL', Timestamp('2023-10-30 16:20:00+0000', tz='UTC'))":3369.0,"('AAPL', Timestamp('2023-10-30 16:25:00+0000', tz='UTC'))":3307.0,"('AAPL', Timestamp('2023-10-30 16:30:00+0000', tz='UTC'))":4175.0,"('AAPL', Timestamp('2023-10-30 16:35:00+0000', tz='UTC'))":3151.0,"('AAPL', Timestamp('2023-10-30 16:40:00+0000', tz='UTC'))":4456.0,"('AAPL', Timestamp('2023-10-30 16:45:00+0000', tz='UTC'))":3578.0,"('AAPL', Timestamp('2023-10-30 16:50:00+0000', tz='UTC'))":3496.0,"('AAPL', Timestamp('2023-10-30 16:55:00+0000', tz='UTC'))":4634.0,"('AAPL', Timestamp('2023-10-30 17:00:00+0000', tz='UTC'))":3979.0,"('AAPL', Timestamp('2023-10-30 17:05:00+0000', tz='UTC'))":4165.0,"('AAPL', Timestamp('2023-10-30 17:10:00+0000', tz='UTC'))":3983.0,"('AAPL', Timestamp('2023-10-30 17:15:00+0000', tz='UTC'))":3812.0,"('AAPL', Timestamp('2023-10-30 17:20:00+0000', tz='UTC'))":4200.0,"('AAPL', Timestamp('2023-10-30 17:25:00+0000', tz='UTC'))":7552.0,"('AAPL', Timestamp('2023-10-30 17:30:00+0000', tz='UTC'))":5011.0,"('AAPL', Timestamp('2023-10-30 17:35:00+0000', tz='UTC'))":3814.0,"('AAPL', Timestamp('2023-10-30 17:40:00+0000', tz='UTC'))":3276.0,"('AAPL', Timestamp('2023-10-30 17:45:00+0000', tz='UTC'))":4143.0,"('AAPL', Timestamp('2023-10-30 17:50:00+0000', tz='UTC'))":3860.0,"('AAPL', Timestamp('2023-10-30 17:55:00+0000', tz='UTC'))":3495.0,"('AAPL', Timestamp('2023-10-30 18:00:00+0000', tz='UTC'))":4399.0,"('AAPL', Timestamp('2023-10-30 18:05:00+0000', tz='UTC'))":5113.0,"('AAPL', Timestamp('2023-10-30 18:10:00+0000', tz='UTC'))":4045.0,"('AAPL', Timestamp('2023-10-30 18:15:00+0000', tz='UTC'))":3941.0,"('AAPL', Timestamp('2023-10-30 18:20:00+0000', tz='UTC'))":3505.0,"('AAPL', Timestamp('2023-10-30 18:25:00+0000', tz='UTC'))":4591.0,"('AAPL', Timestamp('2023-10-30 18:30:00+0000', tz='UTC'))":3795.0,"('AAPL', Timestamp('2023-10-30 18:35:00+0000', tz='UTC'))":5029.0,"('AAPL', Timestamp('2023-10-30 18:40:00+0000', tz='UTC'))":4178.0,"('AAPL', Timestamp('2023-10-30 18:45:00+0000', tz='UTC'))":4434.0,"('AAPL', Timestamp('2023-10-30 18:50:00+0000', tz='UTC'))":3646.0,"('AAPL', Timestamp('2023-10-30 18:55:00+0000', tz='UTC'))":4636.0,"('AAPL', Timestamp('2023-10-30 19:00:00+0000', tz='UTC'))":6354.0,"('AAPL', Timestamp('2023-10-30 19:05:00+0000', tz='UTC'))":5880.0,"('AAPL', Timestamp('2023-10-30 19:10:00+0000', tz='UTC'))":6980.0,"('AAPL', Timestamp('2023-10-30 19:15:00+0000', tz='UTC'))":5238.0,"('AAPL', Timestamp('2023-10-30 19:20:00+0000', tz='UTC'))":5921.0,"('AAPL', Timestamp('2023-10-30 19:25:00+0000', tz='UTC'))":6009.0,"('AAPL', Timestamp('2023-10-30 19:30:00+0000', tz='UTC'))":6521.0,"('AAPL', Timestamp('2023-10-30 19:35:00+0000', tz='UTC'))":6032.0,"('AAPL', Timestamp('2023-10-30 19:40:00+0000', tz='UTC'))":7703.0,"('AAPL', Timestamp('2023-10-30 19:45:00+0000', tz='UTC'))":8970.0,"('AAPL', Timestamp('2023-10-30 19:50:00+0000', tz='UTC'))":11227.0,"('AAPL', Timestamp('2023-10-30 19:55:00+0000', tz='UTC'))":16427.0,"('AAPL', Timestamp('2023-10-30 20:00:00+0000', tz='UTC'))":545.0,"('AAPL', Timestamp('2023-10-30 20:05:00+0000', tz='UTC'))":172.0,"('AAPL', Timestamp('2023-10-30 20:10:00+0000', tz='UTC'))":226.0,"('AAPL', Timestamp('2023-10-30 20:15:00+0000', tz='UTC'))":213.0,"('AAPL', Timestamp('2023-10-30 20:20:00+0000', tz='UTC'))":184.0,"('AAPL', Timestamp('2023-10-30 20:25:00+0000', tz='UTC'))":133.0,"('AAPL', Timestamp('2023-10-30 20:30:00+0000', tz='UTC'))":103.0,"('AAPL', Timestamp('2023-10-30 20:35:00+0000', tz='UTC'))":75.0,"('AAPL', Timestamp('2023-10-30 20:40:00+0000', tz='UTC'))":80.0,"('AAPL', Timestamp('2023-10-30 20:45:00+0000', tz='UTC'))":119.0,"('AAPL', Timestamp('2023-10-30 20:50:00+0000', tz='UTC'))":95.0,"('AAPL', Timestamp('2023-10-30 20:55:00+0000', tz='UTC'))":13.0,"('AAPL', Timestamp('2023-10-30 21:00:00+0000', tz='UTC'))":96.0,"('AAPL', Timestamp('2023-10-30 21:05:00+0000', tz='UTC'))":48.0,"('AAPL', Timestamp('2023-10-30 21:10:00+0000', tz='UTC'))":92.0,"('AAPL', Timestamp('2023-10-30 21:15:00+0000', tz='UTC'))":40.0,"('AAPL', Timestamp('2023-10-30 21:20:00+0000', tz='UTC'))":56.0,"('AAPL', Timestamp('2023-10-30 21:25:00+0000', tz='UTC'))":26.0,"('AAPL', Timestamp('2023-10-30 21:30:00+0000', tz='UTC'))":30.0,"('AAPL', Timestamp('2023-10-30 21:35:00+0000', tz='UTC'))":54.0,"('AAPL', Timestamp('2023-10-30 21:40:00+0000', tz='UTC'))":11.0,"('AAPL', Timestamp('2023-10-30 21:45:00+0000', tz='UTC'))":22.0,"('AAPL', Timestamp('2023-10-30 21:50:00+0000', tz='UTC'))":20.0,"('AAPL', Timestamp('2023-10-30 21:55:00+0000', tz='UTC'))":115.0,"('AAPL', Timestamp('2023-10-30 22:00:00+0000', tz='UTC'))":37.0,"('AAPL', Timestamp('2023-10-30 22:05:00+0000', tz='UTC'))":64.0,"('AAPL', Timestamp('2023-10-30 22:10:00+0000', tz='UTC'))":68.0,"('AAPL', Timestamp('2023-10-30 22:15:00+0000', tz='UTC'))":52.0,"('AAPL', Timestamp('2023-10-30 22:20:00+0000', tz='UTC'))":56.0,"('AAPL', Timestamp('2023-10-30 22:25:00+0000', tz='UTC'))":13.0,"('AAPL', Timestamp('2023-10-30 22:30:00+0000', tz='UTC'))":52.0,"('AAPL', Timestamp('2023-10-30 22:35:00+0000', tz='UTC'))":27.0,"('AAPL', Timestamp('2023-10-30 22:40:00+0000', tz='UTC'))":45.0,"('AAPL', Timestamp('2023-10-30 22:50:00+0000', tz='UTC'))":29.0,"('AAPL', Timestamp('2023-10-30 22:55:00+0000', tz='UTC'))":12.0,"('AAPL', Timestamp('2023-10-30 23:00:00+0000', tz='UTC'))":49.0,"('AAPL', Timestamp('2023-10-30 23:05:00+0000', tz='UTC'))":39.0,"('AAPL', Timestamp('2023-10-30 23:10:00+0000', tz='UTC'))":24.0,"('AAPL', Timestamp('2023-10-30 23:15:00+0000', tz='UTC'))":46.0,"('AAPL', Timestamp('2023-10-30 23:20:00+0000', tz='UTC'))":40.0,"('AAPL', Timestamp('2023-10-30 23:25:00+0000', tz='UTC'))":11.0,"('AAPL', Timestamp('2023-10-30 23:30:00+0000', tz='UTC'))":75.0,"('AAPL', Timestamp('2023-10-30 23:35:00+0000', tz='UTC'))":74.0,"('AAPL', Timestamp('2023-10-30 23:40:00+0000', tz='UTC'))":60.0,"('AAPL', Timestamp('2023-10-30 23:45:00+0000', tz='UTC'))":110.0,"('AAPL', Timestamp('2023-10-30 23:50:00+0000', tz='UTC'))":77.0},"vwap":{"('AAPL', Timestamp('2023-10-30 08:00:00+0000', tz='UTC'))":168.764265,"('AAPL', Timestamp('2023-10-30 08:05:00+0000', tz='UTC'))":168.975884,"('AAPL', Timestamp('2023-10-30 08:10:00+0000', tz='UTC'))":168.938395,"('AAPL', Timestamp('2023-10-30 08:15:00+0000', tz='UTC'))":168.992235,"('AAPL', Timestamp('2023-10-30 08:20:00+0000', tz='UTC'))":168.991862,"('AAPL', Timestamp('2023-10-30 08:25:00+0000', tz='UTC'))":168.84211,"('AAPL', Timestamp('2023-10-30 08:35:00+0000', tz='UTC'))":168.846657,"('AAPL', Timestamp('2023-10-30 08:40:00+0000', tz='UTC'))":168.867149,"('AAPL', Timestamp('2023-10-30 08:45:00+0000', tz='UTC'))":168.753845,"('AAPL', Timestamp('2023-10-30 08:50:00+0000', tz='UTC'))":168.924689,"('AAPL', Timestamp('2023-10-30 09:00:00+0000', tz='UTC'))":169.036531,"('AAPL', Timestamp('2023-10-30 09:05:00+0000', tz='UTC'))":169.163037,"('AAPL', Timestamp('2023-10-30 09:10:00+0000', tz='UTC'))":169.206526,"('AAPL', Timestamp('2023-10-30 09:15:00+0000', tz='UTC'))":169.449894,"('AAPL', Timestamp('2023-10-30 09:20:00+0000', tz='UTC'))":169.268114,"('AAPL', Timestamp('2023-10-30 09:25:00+0000', tz='UTC'))":169.203443,"('AAPL', Timestamp('2023-10-30 09:30:00+0000', tz='UTC'))":169.249977,"('AAPL', Timestamp('2023-10-30 09:35:00+0000', tz='UTC'))":169.073108,"('AAPL', Timestamp('2023-10-30 09:40:00+0000', tz='UTC'))":169.091573,"('AAPL', Timestamp('2023-10-30 09:45:00+0000', tz='UTC'))":169.111648,"('AAPL', Timestamp('2023-10-30 09:50:00+0000', tz='UTC'))":169.138646,"('AAPL', Timestamp('2023-10-30 09:55:00+0000', tz='UTC'))":169.166625,"('AAPL', Timestamp('2023-10-30 10:05:00+0000', tz='UTC'))":169.147677,"('AAPL', Timestamp('2023-10-30 10:10:00+0000', tz='UTC'))":169.120888,"('AAPL', Timestamp('2023-10-30 10:15:00+0000', tz='UTC'))":169.049472,"('AAPL', Timestamp('2023-10-30 10:20:00+0000', tz='UTC'))":169.0042,"('AAPL', Timestamp('2023-10-30 10:25:00+0000', tz='UTC'))":169.000934,"('AAPL', Timestamp('2023-10-30 10:30:00+0000', tz='UTC'))":169.004398,"('AAPL', Timestamp('2023-10-30 10:35:00+0000', tz='UTC'))":169.016699,"('AAPL', Timestamp('2023-10-30 10:45:00+0000', tz='UTC'))":169.024958,"('AAPL', Timestamp('2023-10-30 10:50:00+0000', tz='UTC'))":169.039764,"('AAPL', Timestamp('2023-10-30 10:55:00+0000', tz='UTC'))":169.215081,"('AAPL', Timestamp('2023-10-30 11:00:00+0000', tz='UTC'))":169.188976,"('AAPL', Timestamp('2023-10-30 11:05:00+0000', tz='UTC'))":169.212521,"('AAPL', Timestamp('2023-10-30 11:10:00+0000', tz='UTC'))":169.161173,"('AAPL', Timestamp('2023-10-30 11:15:00+0000', tz='UTC'))":169.200414,"('AAPL', Timestamp('2023-10-30 11:20:00+0000', tz='UTC'))":169.183938,"('AAPL', Timestamp('2023-10-30 11:25:00+0000', tz='UTC'))":169.128768,"('AAPL', Timestamp('2023-10-30 11:30:00+0000', tz='UTC'))":169.165805,"('AAPL', Timestamp('2023-10-30 11:35:00+0000', tz='UTC'))":169.219264,"('AAPL', Timestamp('2023-10-30 11:40:00+0000', tz='UTC'))":169.193011,"('AAPL', Timestamp('2023-10-30 11:45:00+0000', tz='UTC'))":169.262842,"('AAPL', Timestamp('2023-10-30 11:50:00+0000', tz='UTC'))":169.191684,"('AAPL', Timestamp('2023-10-30 11:55:00+0000', tz='UTC'))":169.113196,"('AAPL', Timestamp('2023-10-30 12:00:00+0000', tz='UTC'))":169.103724,"('AAPL', Timestamp('2023-10-30 12:05:00+0000', tz='UTC'))":168.95696,"('AAPL', Timestamp('2023-10-30 12:10:00+0000', tz='UTC'))":168.936872,"('AAPL', Timestamp('2023-10-30 12:15:00+0000', tz='UTC'))":168.882981,"('AAPL', Timestamp('2023-10-30 12:20:00+0000', tz='UTC'))":168.656236,"('AAPL', Timestamp('2023-10-30 12:25:00+0000', tz='UTC'))":168.695936,"('AAPL', Timestamp('2023-10-30 12:30:00+0000', tz='UTC'))":168.866129,"('AAPL', Timestamp('2023-10-30 12:35:00+0000', tz='UTC'))":168.744829,"('AAPL', Timestamp('2023-10-30 12:40:00+0000', tz='UTC'))":168.619415,"('AAPL', Timestamp('2023-10-30 12:45:00+0000', tz='UTC'))":168.555301,"('AAPL', Timestamp('2023-10-30 12:50:00+0000', tz='UTC'))":168.392509,"('AAPL', Timestamp('2023-10-30 12:55:00+0000', tz='UTC'))":168.562685,"('AAPL', Timestamp('2023-10-30 13:00:00+0000', tz='UTC'))":168.639308,"('AAPL', Timestamp('2023-10-30 13:05:00+0000', tz='UTC'))":168.703654,"('AAPL', Timestamp('2023-10-30 13:10:00+0000', tz='UTC'))":168.572664,"('AAPL', Timestamp('2023-10-30 13:15:00+0000', tz='UTC'))":168.520918,"('AAPL', Timestamp('2023-10-30 13:20:00+0000', tz='UTC'))":168.645756,"('AAPL', Timestamp('2023-10-30 13:25:00+0000', tz='UTC'))":168.7157,"('AAPL', Timestamp('2023-10-30 13:30:00+0000', tz='UTC'))":169.401658,"('AAPL', Timestamp('2023-10-30 13:35:00+0000', tz='UTC'))":170.511955,"('AAPL', Timestamp('2023-10-30 13:40:00+0000', tz='UTC'))":170.639105,"('AAPL', Timestamp('2023-10-30 13:45:00+0000', tz='UTC'))":170.955515,"('AAPL', Timestamp('2023-10-30 13:50:00+0000', tz='UTC'))":170.885458,"('AAPL', Timestamp('2023-10-30 13:55:00+0000', tz='UTC'))":170.697875,"('AAPL', Timestamp('2023-10-30 14:00:00+0000', tz='UTC'))":170.592348,"('AAPL', Timestamp('2023-10-30 14:05:00+0000', tz='UTC'))":170.587258,"('AAPL', Timestamp('2023-10-30 14:10:00+0000', tz='UTC'))":170.476593,"('AAPL', Timestamp('2023-10-30 14:15:00+0000', tz='UTC'))":170.021303,"('AAPL', Timestamp('2023-10-30 14:20:00+0000', tz='UTC'))":169.496869,"('AAPL', Timestamp('2023-10-30 14:25:00+0000', tz='UTC'))":169.497414,"('AAPL', Timestamp('2023-10-30 14:30:00+0000', tz='UTC'))":169.418448,"('AAPL', Timestamp('2023-10-30 14:35:00+0000', tz='UTC'))":169.680136,"('AAPL', Timestamp('2023-10-30 14:40:00+0000', tz='UTC'))":169.815192,"('AAPL', Timestamp('2023-10-30 14:45:00+0000', tz='UTC'))":169.72903,"('AAPL', Timestamp('2023-10-30 14:50:00+0000', tz='UTC'))":169.928938,"('AAPL', Timestamp('2023-10-30 14:55:00+0000', tz='UTC'))":169.634792,"('AAPL', Timestamp('2023-10-30 15:00:00+0000', tz='UTC'))":169.796629,"('AAPL', Timestamp('2023-10-30 15:05:00+0000', tz='UTC'))":170.013115,"('AAPL', Timestamp('2023-10-30 15:10:00+0000', tz='UTC'))":169.957565,"('AAPL', Timestamp('2023-10-30 15:15:00+0000', tz='UTC'))":169.967376,"('AAPL', Timestamp('2023-10-30 15:20:00+0000', tz='UTC'))":169.802709,"('AAPL', Timestamp('2023-10-30 15:25:00+0000', tz='UTC'))":169.55266,"('AAPL', Timestamp('2023-10-30 15:30:00+0000', tz='UTC'))":169.823306,"('AAPL', Timestamp('2023-10-30 15:35:00+0000', tz='UTC'))":170.029105,"('AAPL', Timestamp('2023-10-30 15:40:00+0000', tz='UTC'))":169.662443,"('AAPL', Timestamp('2023-10-30 15:45:00+0000', tz='UTC'))":169.74148,"('AAPL', Timestamp('2023-10-30 15:50:00+0000', tz='UTC'))":169.839963,"('AAPL', Timestamp('2023-10-30 15:55:00+0000', tz='UTC'))":169.883167,"('AAPL', Timestamp('2023-10-30 16:00:00+0000', tz='UTC'))":169.892073,"('AAPL', Timestamp('2023-10-30 16:05:00+0000', tz='UTC'))":169.733295,"('AAPL', Timestamp('2023-10-30 16:10:00+0000', tz='UTC'))":169.821736,"('AAPL', Timestamp('2023-10-30 16:15:00+0000', tz='UTC'))":169.728269,"('AAPL', Timestamp('2023-10-30 16:20:00+0000', tz='UTC'))":169.487087,"('AAPL', Timestamp('2023-10-30 16:25:00+0000', tz='UTC'))":169.495197,"('AAPL', Timestamp('2023-10-30 16:30:00+0000', tz='UTC'))":169.464522,"('AAPL', Timestamp('2023-10-30 16:35:00+0000', tz='UTC'))":169.583759,"('AAPL', Timestamp('2023-10-30 16:40:00+0000', tz='UTC'))":169.330056,"('AAPL', Timestamp('2023-10-30 16:45:00+0000', tz='UTC'))":169.25392,"('AAPL', Timestamp('2023-10-30 16:50:00+0000', tz='UTC'))":169.30205,"('AAPL', Timestamp('2023-10-30 16:55:00+0000', tz='UTC'))":169.215425,"('AAPL', Timestamp('2023-10-30 17:00:00+0000', tz='UTC'))":169.294643,"('AAPL', Timestamp('2023-10-30 17:05:00+0000', tz='UTC'))":169.460403,"('AAPL', Timestamp('2023-10-30 17:10:00+0000', tz='UTC'))":169.497878,"('AAPL', Timestamp('2023-10-30 17:15:00+0000', tz='UTC'))":169.390215,"('AAPL', Timestamp('2023-10-30 17:20:00+0000', tz='UTC'))":169.475177,"('AAPL', Timestamp('2023-10-30 17:25:00+0000', tz='UTC'))":169.879402,"('AAPL', Timestamp('2023-10-30 17:30:00+0000', tz='UTC'))":170.094483,"('AAPL', Timestamp('2023-10-30 17:35:00+0000', tz='UTC'))":169.952189,"('AAPL', Timestamp('2023-10-30 17:40:00+0000', tz='UTC'))":170.016573,"('AAPL', Timestamp('2023-10-30 17:45:00+0000', tz='UTC'))":170.191944,"('AAPL', Timestamp('2023-10-30 17:50:00+0000', tz='UTC'))":170.312113,"('AAPL', Timestamp('2023-10-30 17:55:00+0000', tz='UTC'))":170.239864,"('AAPL', Timestamp('2023-10-30 18:00:00+0000', tz='UTC'))":170.30285,"('AAPL', Timestamp('2023-10-30 18:05:00+0000', tz='UTC'))":170.342256,"('AAPL', Timestamp('2023-10-30 18:10:00+0000', tz='UTC'))":170.393607,"('AAPL', Timestamp('2023-10-30 18:15:00+0000', tz='UTC'))":170.208824,"('AAPL', Timestamp('2023-10-30 18:20:00+0000', tz='UTC'))":170.323158,"('AAPL', Timestamp('2023-10-30 18:25:00+0000', tz='UTC'))":170.353334,"('AAPL', Timestamp('2023-10-30 18:30:00+0000', tz='UTC'))":170.387036,"('AAPL', Timestamp('2023-10-30 18:35:00+0000', tz='UTC'))":170.535441,"('AAPL', Timestamp('2023-10-30 18:40:00+0000', tz='UTC'))":170.662075,"('AAPL', Timestamp('2023-10-30 18:45:00+0000', tz='UTC'))":170.743092,"('AAPL', Timestamp('2023-10-30 18:50:00+0000', tz='UTC'))":170.6795,"('AAPL', Timestamp('2023-10-30 18:55:00+0000', tz='UTC'))":170.536038,"('AAPL', Timestamp('2023-10-30 19:00:00+0000', tz='UTC'))":170.496955,"('AAPL', Timestamp('2023-10-30 19:05:00+0000', tz='UTC'))":170.351914,"('AAPL', Timestamp('2023-10-30 19:10:00+0000', tz='UTC'))":170.112752,"('AAPL', Timestamp('2023-10-30 19:15:00+0000', tz='UTC'))":170.107574,"('AAPL', Timestamp('2023-10-30 19:20:00+0000', tz='UTC'))":170.12087,"('AAPL', Timestamp('2023-10-30 19:25:00+0000', tz='UTC'))":169.995154,"('AAPL', Timestamp('2023-10-30 19:30:00+0000', tz='UTC'))":169.93721,"('AAPL', Timestamp('2023-10-30 19:35:00+0000', tz='UTC'))":170.09879,"('AAPL', Timestamp('2023-10-30 19:40:00+0000', tz='UTC'))":170.151264,"('AAPL', Timestamp('2023-10-30 19:45:00+0000', tz='UTC'))":170.235556,"('AAPL', Timestamp('2023-10-30 19:50:00+0000', tz='UTC'))":170.344963,"('AAPL', Timestamp('2023-10-30 19:55:00+0000', tz='UTC'))":170.242158,"('AAPL', Timestamp('2023-10-30 20:00:00+0000', tz='UTC'))":170.288947,"('AAPL', Timestamp('2023-10-30 20:05:00+0000', tz='UTC'))":170.162951,"('AAPL', Timestamp('2023-10-30 20:10:00+0000', tz='UTC'))":170.020245,"('AAPL', Timestamp('2023-10-30 20:15:00+0000', tz='UTC'))":170.176197,"('AAPL', Timestamp('2023-10-30 20:20:00+0000', tz='UTC'))":170.226427,"('AAPL', Timestamp('2023-10-30 20:25:00+0000', tz='UTC'))":170.062524,"('AAPL', Timestamp('2023-10-30 20:30:00+0000', tz='UTC'))":170.018317,"('AAPL', Timestamp('2023-10-30 20:35:00+0000', tz='UTC'))":170.24485,"('AAPL', Timestamp('2023-10-30 20:40:00+0000', tz='UTC'))":169.948683,"('AAPL', Timestamp('2023-10-30 20:45:00+0000', tz='UTC'))":169.961179,"('AAPL', Timestamp('2023-10-30 20:50:00+0000', tz='UTC'))":169.981111,"('AAPL', Timestamp('2023-10-30 20:55:00+0000', tz='UTC'))":169.955037,"('AAPL', Timestamp('2023-10-30 21:00:00+0000', tz='UTC'))":170.026131,"('AAPL', Timestamp('2023-10-30 21:05:00+0000', tz='UTC'))":170.011158,"('AAPL', Timestamp('2023-10-30 21:10:00+0000', tz='UTC'))":169.975554,"('AAPL', Timestamp('2023-10-30 21:15:00+0000', tz='UTC'))":170.98571,"('AAPL', Timestamp('2023-10-30 21:20:00+0000', tz='UTC'))":170.17814,"('AAPL', Timestamp('2023-10-30 21:25:00+0000', tz='UTC'))":170.288634,"('AAPL', Timestamp('2023-10-30 21:30:00+0000', tz='UTC'))":169.291174,"('AAPL', Timestamp('2023-10-30 21:35:00+0000', tz='UTC'))":170.021349,"('AAPL', Timestamp('2023-10-30 21:40:00+0000', tz='UTC'))":169.991534,"('AAPL', Timestamp('2023-10-30 21:45:00+0000', tz='UTC'))":170.018628,"('AAPL', Timestamp('2023-10-30 21:50:00+0000', tz='UTC'))":170.001275,"('AAPL', Timestamp('2023-10-30 21:55:00+0000', tz='UTC'))":169.953015,"('AAPL', Timestamp('2023-10-30 22:00:00+0000', tz='UTC'))":169.948574,"('AAPL', Timestamp('2023-10-30 22:05:00+0000', tz='UTC'))":169.913667,"('AAPL', Timestamp('2023-10-30 22:10:00+0000', tz='UTC'))":169.863674,"('AAPL', Timestamp('2023-10-30 22:15:00+0000', tz='UTC'))":169.893774,"('AAPL', Timestamp('2023-10-30 22:20:00+0000', tz='UTC'))":169.823202,"('AAPL', Timestamp('2023-10-30 22:25:00+0000', tz='UTC'))":169.822024,"('AAPL', Timestamp('2023-10-30 22:30:00+0000', tz='UTC'))":169.862426,"('AAPL', Timestamp('2023-10-30 22:35:00+0000', tz='UTC'))":169.842185,"('AAPL', Timestamp('2023-10-30 22:40:00+0000', tz='UTC'))":169.893379,"('AAPL', Timestamp('2023-10-30 22:50:00+0000', tz='UTC'))":169.843914,"('AAPL', Timestamp('2023-10-30 22:55:00+0000', tz='UTC'))":169.869471,"('AAPL', Timestamp('2023-10-30 23:00:00+0000', tz='UTC'))":169.875634,"('AAPL', Timestamp('2023-10-30 23:05:00+0000', tz='UTC'))":169.882131,"('AAPL', Timestamp('2023-10-30 23:10:00+0000', tz='UTC'))":169.833952,"('AAPL', Timestamp('2023-10-30 23:15:00+0000', tz='UTC'))":169.858187,"('AAPL', Timestamp('2023-10-30 23:20:00+0000', tz='UTC'))":169.866685,"('AAPL', Timestamp('2023-10-30 23:25:00+0000', tz='UTC'))":169.85006,"('AAPL', Timestamp('2023-10-30 23:30:00+0000', tz='UTC'))":169.849938,"('AAPL', Timestamp('2023-10-30 23:35:00+0000', tz='UTC'))":169.851147,"('AAPL', Timestamp('2023-10-30 23:40:00+0000', tz='UTC'))":169.837734,"('AAPL', Timestamp('2023-10-30 23:45:00+0000', tz='UTC'))":169.77522,"('AAPL', Timestamp('2023-10-30 23:50:00+0000', tz='UTC'))":169.770915}}